Workbook

Sheet Readme
A1: Scratchpad Dungeon · authoritative balance workbook
A2: Edit blue Value cells only. IDs, columns, sheets and protected metadata must stay intact.
A3: Import: npm run balance:import -- path/to/edited.xlsx
A4: Validate without writing: npm run balance:validate -- path/to/edited.xlsx
A5: Export fresh after an import: npm run balance:export
A6: The importer rejects formulas in input cells, unknown/missing/duplicate fields, invalid types, unsafe text and broken references.
A7: All sheets are validated together before any source or build is replaced.
A8: data/balance.json is the runtime source. This workbook is an editable export.
A9: Statistics recalculate in Excel/LibreOffice; import recomputes build data from input cells, never cached formula results.
A10: Reel statistics: level-one base face power and triple-match probability; excludes class powers, buffs, gear and target armour.
A11: Enemy HP statistics use the normal/boss/stronghold curve plus per-type multiplier. Other figures are baseline snapshots regenerated after import.
A12: Schema | B12: 1
A13: Schema digest | B13: b889ae28d1107419968dc059d0969609db38bb31509262f7e6a6fbb815743682
A14: Balance revision | B14: 1
A15: Source digest | B15: 6d2d6d6b8c46a364f6ff46f66d21672c4674b7105692c45eaccbeb8e2a59e7b3

Sheet Engine
A1: Stable field ID | B1: Entity ID | C1: Field / label | D1: Value (edit blue cells) | E1: Type | F1: Unit | G1: Minimum | H1: Maximum | I1: Notes
A2: /engine/mapWidth | B2: rule.engine | C2: mapWidth | D2: 11 | E2: number | G2: 0 | H2: 100000 | I2: READ ONLY
A3: /engine/mapHeight | B3: rule.engine | C3: mapHeight | D3: 9 | E3: number | G3: 0 | H3: 100000 | I3: READ ONLY
A4: /engine/maxSupportedParty | B4: rule.engine | C4: maxSupportedParty | D4: 3 | E4: number | G4: 0 | H4: 100000 | I4: READ ONLY
A5: /engine/reelsPerMachine | B5: rule.engine | C5: reelsPerMachine | D5: 3 | E5: number | G5: 0 | H5: 100000 | I5: READ ONLY
A6: /engine/criticalMatches | B6: rule.engine | C6: criticalMatches | D6: 3 | E6: number | G6: 0 | H6: 100000 | I6: READ ONLY

Sheet Progression
A1: Stable field ID | B1: Entity ID | C1: Field / label | D1: Value (edit blue cells) | E1: Type | F1: Unit | G1: Minimum | H1: Maximum | I1: Notes
A2: /rules/maxParty | B2: rule.rules | C2: maxParty | D2: 3 | E2: number | G2: 1 | H2: 3
A3: /rules/bagTypes | B3: rule.rules | C3: bagTypes | D3: 3 | E3: number | G3: 1 | H3: 3
A4: /rules/floors | B4: rule.rules | C4: floors | D4: 10 | E4: number | G4: 10 | H4: 10
A5: /rules/startingPoints | B5: rule.rules | C5: startingPoints | D5: 3 | E5: number | G5: 0 | H5: 100000
A6: /rules/levelHp | B6: rule.rules | C6: levelHp | D6: 6 | E6: number | G6: 1 | H6: 1000
A7: /rules/levelPoints | B7: rule.rules | C7: levelPoints | D7: 4 | E7: number | G7: 1 | H7: 1000
A8: /rules/xpPerLevel | B8: rule.rules | C8: xpPerLevel | D8: 12 | E8: number | G8: 1 | H8: 1000
A9: /rules/blankInscriptionCost | B9: rule.rules | C9: blankInscriptionCost | D9: 3 | E9: number | G9: 1 | H9: 1000
A10: /rules/stunArmourCost | B10: rule.rules | C10: stunArmourCost | D10: 6 | E10: number | G10: 1 | H10: 1000
A11: /rules/reviveHealthFraction | B11: rule.rules | C11: reviveHealthFraction | D11: 0.75 | E11: number | G11: 0.0001 | H11: 1
A12: /rules/fountainHealthFraction | B12: rule.rules | C12: fountainHealthFraction | D12: 0.3 | E12: number | G12: 0.0001 | H12: 1
A13: /rules/descentHeal | B13: rule.rules | C13: descentHeal | D13: 5 | E13: number | G13: 0 | H13: 100000
... A17: /rules/areaAttackTier | B17: rule.rules | C17: areaAttackTier | D17: 3 | E17: number | G17: 1 | H17: 4
A18: /tuning/victory.coefficient.1/value | B18: rule.tuning.victory.coefficient.1 | C18: victory · coefficient 1 | D18: 8 | E18: number | F18: count or coefficient | G18: 1 | H18: 100 | I18: Coefficient in: ( h, Math.round( (8 + state.depth * 2) * 0.85 *
A19: /tuning/victory.coefficient.1/category | B19: rule.tuning.victory.coefficient.1 | C19: victory · coefficient 1 | D19: Progression | E19: string | F19: count or coefficient | I19: READ ONLY
A20: /tuning/victory.coefficient.1/label | B20: rule.tuning.victory.coefficient.1 | C20: victory · coefficient 1 | D20: victory · coefficient 1 | E20: string | F20: count or coefficient | I20: READ ONLY
A21: /tuning/victory.coefficient.1/description | B21: rule.tuning.victory.coefficient.1 | C21: victory · coefficient 1 | D21: Coefficient in: ( h, Math.round( (8 + state.depth * 2) * 0.85 * | E21: string | F21: count or coefficient | I21: READ ONLY
A22: /tuning/victory.coefficient.1/unit | B22: rule.tuning.victory.coefficient.1 | C22: victory · coefficient 1 | D22: count or coefficient | E22: string | F22: count or coefficient | I22: READ ONLY
A23: /tuning/victory.coefficient.1/min | B23: rule.tuning.victory.coefficient.1 | C23: victory · coefficient 1 | D23: 0 | E23: number | F23: count or coefficient | G23: 1 | H23: 100 | I23: READ ONLY
A24: /tuning/victory.coefficient.1/max | B24: rule.tuning.victory.coefficient.1 | C24: victory · coefficient 1 | D24: 100 | E24: number | F24: count or coefficient | G24: 1 | H24: 100 | I24: READ ONLY
A25: /tuning/victory.coefficient.1/integer | B25: rule.tuning.victory.coefficient.1 | C25: victory · coefficient 1 | D25: TRUE | E25: boolean | F25: count or coefficient | I25: READ ONLY
A26: /tuning/victory.coefficient.2/value | B26: rule.tuning.victory.coefficient.2 | C26: victory · coefficient 2 | D26: 2 | E26: number | F26: count or coefficient | G26: 1 | H26: 100 | I26: Coefficient in: ath.round( (8 + state.depth * 2) * 0.85 * (state.
A27: /tuning/victory.coefficient.2/category | B27: rule.tuning.victory.coefficient.2 | C27: victory · coefficient 2 | D27: Progression | E27: string | F27: count or coefficient | I27: READ ONLY
A28: /tuning/victory.coefficient.2/label | B28: rule.tuning.victory.coefficient.2 | C28: victory · coefficient 2 | D28: victory · coefficient 2 | E28: string | F28: count or coefficient | I28: READ ONLY
A29: /tuning/victory.coefficient.2/description | B29: rule.tuning.victory.coefficient.2 | C29: victory · coefficient 2 | D29: Coefficient in: ath.round( (8 + state.depth * 2) * 0.85 * (state. | E29: string | F29: count or coefficient | I29: READ ONLY
A30: /tuning/victory.coefficient.2/unit | B30: rule.tuning.victory.coefficient.2 | C30: victory · coefficient 2 | D30: count or coefficient | E30: string | F30: count or coefficient | I30: READ ONLY
A31: /tuning/victory.coefficient.2/min | B31: rule.tuning.victory.coefficient.2 | C31: victory · coefficient 2 | D31: 0 | E31: number | F31: count or coefficient | G31: 1 | H31: 100 | I31: READ ONLY
A32: /tuning/victory.coefficient.2/max | B32: rule.tuning.victory.coefficient.2 | C32: victory · coefficient 2 | D32: 100 | E32: number | F32: count or coefficient | G32: 1 | H32: 100 | I32: READ ONLY
A33: /tuning/victory.coefficient.2/integer | B33: rule.tuning.victory.coefficient.2 | C33: victory · coefficient 2 | D33: TRUE | E33: boolean | F33: count or coefficient | I33: READ ONLY
A34: /tuning/victory.coefficient.3/value | B34: rule.tuning.victory.coefficient.3 | C34: victory · coefficient 3 | D34: 0.85 | E34: number | F34: probability or multiplier | G34: 0 | H34: 1 | I34: Coefficient in: (8 + state.depth * 2) * 0.85 * (state.encounterReward?.c
A35: /tuning/victory.coefficient.3/category | B35: rule.tuning.victory.coefficient.3 | C35: victory · coefficient 3 | D35: Progression | E35: string | F35: probability or multiplier | I35: READ ONLY
A36: /tuning/victory.coefficient.3/label | B36: rule.tuning.victory.coefficient.3 | C36: victory · coefficient 3 | D36: victory · coefficient 3 | E36: string | F36: probability or multiplier | I36: READ ONLY
A37: /tuning/victory.coefficient.3/description | B37: rule.tuning.victory.coefficient.3 | C37: victory · coefficient 3 | D37: Coefficient in: (8 + state.depth * 2) * 0.85 * (state.encounterReward?.c | E37: string | F37: probability or multiplier | I37: READ ONLY
A38: /tuning/victory.coefficient.3/unit | B38: rule.tuning.victory.coefficient.3 | C38: victory · coefficient 3 | D38: probability or multiplier | E38: string | F38: probability or multiplier | I38: READ ONLY
A39: /tuning/victory.coefficient.3/min | B39: rule.tuning.victory.coefficient.3 | C39: victory · coefficient 3 | D39: 0 | E39: number | F39: probability or multiplier | G39: 0 | H39: 1 | I39: READ ONLY
A40: /tuning/victory.coefficient.3/max | B40: rule.tuning.victory.coefficient.3 | C40: victory · coefficient 3 | D40: 1 | E40: number | F40: probability or multiplier | G40: 0 | H40: 1 | I40: READ ONLY
A41: /tuning/victory.coefficient.3/integer | B41: rule.tuning.victory.coefficient.3 | C41: victory · coefficient 3 | D41: FALSE | E41: boolean | F41: probability or multiplier | I41: READ ONLY
A42: /tuning/victory.coefficient.4/value | B42: rule.tuning.victory.coefficient.4 | C42: victory · coefficient 4 | D42: 2 | E42: number | F42: count or coefficient | G42: 1 | H42: 100 | I42: Coefficient in: unt || 1) * (e.stronghold ? 2 : e.boss ? 1.35 : e.elite ? 1.2 : 1),
A43: /tuning/victory.coefficient.4/category | B43: rule.tuning.victory.coefficient.4 | C43: victory · coefficient 4 | D43: Progression | E43: string | F43: count or coefficient | I43: READ ONLY
A44: /tuning/victory.coefficient.4/label | B44: rule.tuning.victory.coefficient.4 | C44: victory · coefficient 4 | D44: victory · coefficient 4 | E44: string | F44: count or coefficient | I44: READ ONLY
A45: /tuning/victory.coefficient.4/description | B45: rule.tuning.victory.coefficient.4 | C45: victory · coefficient 4 | D45: Coefficient in: unt || 1) * (e.stronghold ? 2 : e.boss ? 1.35 : e.elite ? 1.2 : 1), | E45: string | F45: count or coefficient | I45: READ ONLY
A46: /tuning/victory.coefficient.4/unit | B46: rule.tuning.victory.coefficient.4 | C46: victory · coefficient 4 | D46: count or coefficient | E46: string | F46: count or coefficient | I46: READ ONLY
A47: /tuning/victory.coefficient.4/min | B47: rule.tuning.victory.coefficient.4 | C47: victory · coefficient 4 | D47: 0 | E47: number | F47: count or coefficient | G47: 1 | H47: 100 | I47: READ ONLY
A48: /tuning/victory.coefficient.4/max | B48: rule.tuning.victory.coefficient.4 | C48: victory · coefficient 4 | D48: 100 | E48: number | F48: count or coefficient | G48: 1 | H48: 100 | I48: READ ONLY
A49: /tuning/victory.coefficient.4/integer | B49: rule.tuning.victory.coefficient.4 | C49: victory · coefficient 4 | D49: TRUE | E49: boolean | F49: count or coefficient | I49: READ ONLY
A50: /tuning/victory.coefficient.5/value | B50: rule.tuning.victory.coefficient.5 | C50: victory · coefficient 5 | D50: 1.35 | E50: number | F50: count or coefficient | G50: 0 | H50: 100 | I50: Coefficient in: (e.stronghold ? 2 : e.boss ? 1.35 : e.elite ? 1.2 : 1), ), );
A51: /tuning/victory.coefficient.5/category | B51: rule.tuning.victory.coefficient.5 | C51: victory · coefficient 5 | D51: Progression | E51: string | F51: count or coefficient | I51: READ ONLY
A52: /tuning/victory.coefficient.5/label | B52: rule.tuning.victory.coefficient.5 | C52: victory · coefficient 5 | D52: victory · coefficient 5 | E52: string | F52: count or coefficient | I52: READ ONLY
A53: /tuning/victory.coefficient.5/description | B53: rule.tuning.victory.coefficient.5 | C53: victory · coefficient 5 | D53: Coefficient in: (e.stronghold ? 2 : e.boss ? 1.35 : e.elite ? 1.2 : 1), ), ); | E53: string | F53: count or coefficient | I53: READ ONLY
A54: /tuning/victory.coefficient.5/unit | B54: rule.tuning.victory.coefficient.5 | C54: victory · coefficient 5 | D54: count or coefficient | E54: string | F54: count or coefficient | I54: READ ONLY
A55: /tuning/victory.coefficient.5/min | B55: rule.tuning.victory.coefficient.5 | C55: victory · coefficient 5 | D55: 0 | E55: number | F55: count or coefficient | G55: 0 | H55: 100 | I55: READ ONLY
A56: /tuning/victory.coefficient.5/max | B56: rule.tuning.victory.coefficient.5 | C56: victory · coefficient 5 | D56: 100 | E56: number | F56: count or coefficient | G56: 0 | H56: 100 | I56: READ ONLY
A57: /tuning/victory.coefficient.5/integer | B57: rule.tuning.victory.coefficient.5 | C57: victory · coefficient 5 | D57: FALSE | E57: boolean | F57: count or coefficient | I57: READ ONLY
A58: /tuning/victory.coefficient.6/value | B58: rule.tuning.victory.coefficient.6 | C58: victory · coefficient 6 | D58: 1.2 | E58: number | F58: count or coefficient | G58: 0 | H58: 100 | I58: Coefficient in: ghold ? 2 : e.boss ? 1.35 : e.elite ? 1.2 : 1), ), ); h.points++;
A59: /tuning/victory.coefficient.6/category | B59: rule.tuning.victory.coefficient.6 | C59: victory · coefficient 6 | D59: Progression | E59: string | F59: count or coefficient | I59: READ ONLY
A60: /tuning/victory.coefficient.6/label | B60: rule.tuning.victory.coefficient.6 | C60: victory · coefficient 6 | D60: victory · coefficient 6 | E60: string | F60: count or coefficient | I60: READ ONLY
A61: /tuning/victory.coefficient.6/description | B61: rule.tuning.victory.coefficient.6 | C61: victory · coefficient 6 | D61: Coefficient in: ghold ? 2 : e.boss ? 1.35 : e.elite ? 1.2 : 1), ), ); h.points++; | E61: string | F61: count or coefficient | I61: READ ONLY
A62: /tuning/victory.coefficient.6/unit | B62: rule.tuning.victory.coefficient.6 | C62: victory · coefficient 6 | D62: count or coefficient | E62: string | F62: count or coefficient | I62: READ ONLY
A63: /tuning/victory.coefficient.6/min | B63: rule.tuning.victory.coefficient.6 | C63: victory · coefficient 6 | D63: 0 | E63: number | F63: count or coefficient | G63: 0 | H63: 100 | I63: READ ONLY
A64: /tuning/victory.coefficient.6/max | B64: rule.tuning.victory.coefficient.6 | C64: victory · coefficient 6 | D64: 100 | E64: number | F64: count or coefficient | G64: 0 | H64: 100 | I64: READ ONLY
A65: /tuning/victory.coefficient.6/integer | B65: rule.tuning.victory.coefficient.6 | C65: victory · coefficient 6 | D65: FALSE | E65: boolean | F65: count or coefficient | I65: READ ONLY
A66: /tuning/prepareRecruit.budget.1/value | B66: rule.tuning.prepareRecruit.budget.1 | C66: prepareRecruit · budget 1 | D66: 2 | E66: number | F66: count or coefficient | G66: 1 | H66: 100 | I66: Coefficient in: nts, budget = Math.floor(earned / 2); let remaining = budget; // Pref
A67: /tuning/prepareRecruit.budget.1/category | B67: rule.tuning.prepareRecruit.budget.1 | C67: prepareRecruit · budget 1 | D67: Progression | E67: string | F67: count or coefficient | I67: READ ONLY
A68: /tuning/prepareRecruit.budget.1/label | B68: rule.tuning.prepareRecruit.budget.1 | C68: prepareRecruit · budget 1 | D68: prepareRecruit · budget 1 | E68: string | F68: count or coefficient | I68: READ ONLY
A69: /tuning/prepareRecruit.budget.1/description | B69: rule.tuning.prepareRecruit.budget.1 | C69: prepareRecruit · budget 1 | D69: Coefficient in: nts, budget = Math.floor(earned / 2); let remaining = budget; // Pref | E69: string | F69: count or coefficient | I69: READ ONLY
A70: /tuning/prepareRecruit.budget.1/unit | B70: rule.tuning.prepareRecruit.budget.1 | C70: prepareRecruit · budget 1 | D70: count or coefficient | E70: string | F70: count or coefficient | I70: READ ONLY
A71: /tuning/prepareRecruit.budget.1/min | B71: rule.tuning.prepareRecruit.budget.1 | C71: prepareRecruit · budget 1 | D71: 0 | E71: number | F71: count or coefficient | G71: 1 | H71: 100 | I71: READ ONLY
A72: /tuning/prepareRecruit.budget.1/max | B72: rule.tuning.prepareRecruit.budget.1 | C72: prepareRecruit · budget 1 | D72: 100 | E72: number | F72: count or coefficient | G72: 1 | H72: 100 | I72: READ ONLY
A73: /tuning/prepareRecruit.budget.1/integer | B73: rule.tuning.prepareRecruit.budget.1 | C73: prepareRecruit · budget 1 | D73: TRUE | E73: boolean | F73: count or coefficient | I73: READ ONLY

Sheet Slots
A1: Stable field ID | B1: Entity ID | C1: Field / label | D1: Value (edit blue cells) | E1: Type | F1: Unit | G1: Minimum | H1: Maximum | I1: Notes
A2: /slots/types/0 | B2: rule.slots.types | C2: 0 | D2: attack | E2: string | I2: READ ONLY
A3: /slots/types/1 | B3: rule.slots.types | C3: 1 | D3: magic | E3: string | I3: READ ONLY
A4: /slots/types/2 | B4: rule.slots.types | C4: 2 | D4: poison | E4: string | I4: READ ONLY
A5: /slots/types/3 | B5: rule.slots.types | C5: 3 | D5: stimulant | E5: string | I5: READ ONLY
A6: /slots/types/4 | B6: rule.slots.types | C6: 4 | D6: heal | E6: string | I6: READ ONLY
A7: /slots/types/5 | B7: rule.slots.types | C7: 5 | D7: block | E7: string | I7: READ ONLY
A8: /slots/types/6 | B8: rule.slots.types | C8: 6 | D8: stun | E8: string | I8: READ ONLY
A9: /slots/types/7 | B9: rule.slots.types | C9: 7 | D9: class | E9: string | I9: READ ONLY
A10: /slots/types/8 | B10: rule.slots.types | C10: 8 | D10: blank | E10: string | I10: READ ONLY
A11: /slots/icons/attack | B11: rule.slots.icons | C11: attack | D11: sword | E11: string | I11: READ ONLY
A12: /slots/icons/magic | B12: rule.slots.icons | C12: magic | D12: magic | E12: string | I12: READ ONLY
A13: /slots/icons/poison | B13: rule.slots.icons | C13: poison | D13: poison | E13: string | I13: READ ONLY
... A21: /slots/icons/blank | B21: rule.slots.icons | C21: blank | D21: blank | E21: string | I21: READ ONLY
A22: /slots/power/poison | B22: rule.slots.power | C22: poison | D22: 1 | E22: number | G22: 0 | H22: 100000
A23: /slots/power/stimulant | B23: rule.slots.power | C23: stimulant | D23: 1 | E23: number | G23: 0 | H23: 100000
A24: /slots/power/heal | B24: rule.slots.power | C24: heal | D24: 2 | E24: number | G24: 0 | H24: 100000
A25: /slots/power/block | B25: rule.slots.power | C25: block | D25: 1 | E25: number | G25: 0 | H25: 100000
A26: /slots/power/stun | B26: rule.slots.power | C26: stun | D26: 1 | E26: number | G26: 0 | H26: 100000
A27: /slots/power/class | B27: rule.slots.power | C27: class | D27: 0 | E27: number | G27: 0 | H27: 100000
A28: /slots/power/blank | B28: rule.slots.power | C28: blank | D28: 0 | E28: number | G28: 0 | H28: 100000
A29: /slots/attackPower/0 | B29: rule.slots.attackPower | C29: 0 | D29: 0 | E29: number | G29: 0 | H29: 100000
A30: /slots/attackPower/1 | B30: rule.slots.attackPower | C30: 1 | D30: 2 | E30: number | G30: 0 | H30: 100000
A31: /slots/attackPower/2 | B31: rule.slots.attackPower | C31: 2 | D31: 4 | E31: number | G31: 0 | H31: 100000
A32: /slots/attackPower/3 | B32: rule.slots.attackPower | C32: 3 | D32: 7 | E32: number | G32: 0 | H32: 100000
A33: /slots/attackPower/4 | B33: rule.slots.attackPower | C33: 4 | D33: 11 | E33: number | G33: 0 | H33: 100000
... A41: /slots/criticalMultipliers/3 | B41: rule.slots.criticalMultipliers | C41: 3 | D41: 4 | E41: number | G41: 0 | H41: 100000

Sheet Classes
A1: Stable field ID | B1: Entity ID | C1: Field / label | D1: Value (edit blue cells) | E1: Type | F1: Unit | G1: Minimum | H1: Maximum | I1: Notes
A2: /classes/fighter/id | B2: class.fighter | C2: id | D2: class.fighter | E2: string | I2: READ ONLY
A3: /classes/fighter/name | B3: class.fighter | C3: name | D3: Tank | E3: string
A4: /classes/fighter/maxHp | B4: class.fighter | C4: maxHp | D4: 44 | E4: number | F4: HP | G4: 1 | H4: 100000
A5: /classes/fighter/last/0/type | B5: class.fighter | C5: last · 0 · type | D5: attack | E5: string | I5: READ ONLY
A6: /classes/fighter/last/0/tier | B6: class.fighter | C6: last · 0 · tier | D6: 1 | E6: number | F6: tier | G6: 1 | H6: 4 | I6: READ ONLY
A7: /classes/fighter/last/1/type | B7: class.fighter | C7: last · 1 · type | D7: block | E7: string | I7: READ ONLY
A8: /classes/fighter/last/1/tier | B8: class.fighter | C8: last · 1 · tier | D8: 1 | E8: number | F8: tier | G8: 1 | H8: 4 | I8: READ ONLY
A9: /classes/fighter/last/2/type | B9: class.fighter | C9: last · 2 · type | D9: blank | E9: string | I9: READ ONLY
A10: /classes/fighter/last/2/tier | B10: class.fighter | C10: last · 2 · tier | D10: 1 | E10: number | F10: tier | G10: 1 | H10: 4 | I10: READ ONLY
A11: /classes/healer/id | B11: class.healer | C11: id | D11: class.healer | E11: string | I11: READ ONLY
A12: /classes/healer/name | B12: class.healer | C12: name | D12: Healer | E12: string
A13: /classes/healer/maxHp | B13: class.healer | C13: maxHp | D13: 32 | E13: number | F13: HP | G13: 1 | H13: 100000
A14: /classes/healer/last/0/type | B14: class.healer | C14: last · 0 · type | D14: heal | E14: string | I14: READ ONLY
A15: /classes/healer/last/0/tier | B15: class.healer | C15: last · 0 · tier | D15: 1 | E15: number | F15: tier | G15: 1 | H15: 4 | I15: READ ONLY
A16: /classes/healer/last/1/type | B16: class.healer | C16: last · 1 · type | D16: heal | E16: string | I16: READ ONLY
A17: /classes/healer/last/1/tier | B17: class.healer | C17: last · 1 · tier | D17: 2 | E17: number | F17: tier | G17: 1 | H17: 4 | I17: READ ONLY
A18: /classes/healer/last/2/type | B18: class.healer | C18: last · 2 · type | D18: blank | E18: string | I18: READ ONLY
A19: /classes/healer/last/2/tier | B19: class.healer | C19: last · 2 · tier | D19: 1 | E19: number | F19: tier | G19: 1 | H19: 4 | I19: READ ONLY
A20: /classes/rogue/id | B20: class.rogue | C20: id | D20: class.rogue | E20: string | I20: READ ONLY
A21: /classes/rogue/name | B21: class.rogue | C21: name | D21: Rogue | E21: string
A22: /classes/rogue/maxHp | B22: class.rogue | C22: maxHp | D22: 26 | E22: number | F22: HP | G22: 1 | H22: 100000
A23: /classes/rogue/last/0/type | B23: class.rogue | C23: last · 0 · type | D23: attack | E23: string | I23: READ ONLY
A24: /classes/rogue/last/0/tier | B24: class.rogue | C24: last · 0 · tier | D24: 1 | E24: number | F24: tier | G24: 1 | H24: 4 | I24: READ ONLY
A25: /classes/rogue/last/1/type | B25: class.rogue | C25: last · 1 · type | D25: attack | E25: string | I25: READ ONLY
A26: /classes/rogue/last/1/tier | B26: class.rogue | C26: last · 1 · tier | D26: 3 | E26: number | F26: tier | G26: 1 | H26: 4 | I26: READ ONLY
A27: /classes/rogue/last/2/type | B27: class.rogue | C27: last · 2 · type | D27: blank | E27: string | I27: READ ONLY
A28: /classes/rogue/last/2/tier | B28: class.rogue | C28: last · 2 · tier | D28: 1 | E28: number | F28: tier | G28: 1 | H28: 4 | I28: READ ONLY
A29: /classes/mage/id | B29: class.mage | C29: id | D29: class.mage | E29: string | I29: READ ONLY
A30: /classes/mage/name | B30: class.mage | C30: name | D30: Mage | E30: string
A31: /classes/mage/maxHp | B31: class.mage | C31: maxHp | D31: 28 | E31: number | F31: HP | G31: 1 | H31: 100000
A32: /classes/mage/last/0/type | B32: class.mage | C32: last · 0 · type | D32: magic | E32: string | I32: READ ONLY
A33: /classes/mage/last/0/tier | B33: class.mage | C33: last · 0 · tier | D33: 1 | E33: number | F33: tier | G33: 1 | H33: 4 | I33: READ ONLY
A34: /classes/mage/last/1/type | B34: class.mage | C34: last · 1 · type | D34: stimulant | E34: string | I34: READ ONLY
A35: /classes/mage/last/1/tier | B35: class.mage | C35: last · 1 · tier | D35: 1 | E35: number | F35: tier | G35: 1 | H35: 4 | I35: READ ONLY
A36: /classes/mage/last/2/type | B36: class.mage | C36: last · 2 · type | D36: blank | E36: string | I36: READ ONLY
A37: /classes/mage/last/2/tier | B37: class.mage | C37: last · 2 · tier | D37: 1 | E37: number | F37: tier | G37: 1 | H37: 4 | I37: READ ONLY

Sheet Reels
A1: Stable field ID | B1: Entity ID | C1: Field / label | D1: Value (edit blue cells) | E1: Type | F1: Unit | G1: Minimum | H1: Maximum | I1: Notes
A2: /classes/fighter/reels/0/0/type | B2: class.fighter | C2: reels · 0 · 0 · type | D2: attack | E2: string
A3: /classes/fighter/reels/0/0/tier | B3: class.fighter | C3: reels · 0 · 0 · tier | D3: 1 | E3: number | F3: tier | G3: 1 | H3: 4
A4: /classes/fighter/reels/0/0/weight | B4: class.fighter | C4: reels · 0 · 0 · weight | D4: 9 | E4: number | F4: relative weight | G4: 0.0001 | H4: 100000
A5: /classes/fighter/reels/0/1/type | B5: class.fighter | C5: reels · 0 · 1 · type | D5: attack | E5: string
A6: /classes/fighter/reels/0/1/tier | B6: class.fighter | C6: reels · 0 · 1 · tier | D6: 2 | E6: number | F6: tier | G6: 1 | H6: 4
A7: /classes/fighter/reels/0/1/weight | B7: class.fighter | C7: reels · 0 · 1 · weight | D7: 5 | E7: number | F7: relative weight | G7: 0.0001 | H7: 100000
A8: /classes/fighter/reels/0/2/type | B8: class.fighter | C8: reels · 0 · 2 · type | D8: block | E8: string
A9: /classes/fighter/reels/0/2/tier | B9: class.fighter | C9: reels · 0 · 2 · tier | D9: 1 | E9: number | F9: tier | G9: 1 | H9: 4
A10: /classes/fighter/reels/0/2/weight | B10: class.fighter | C10: reels · 0 · 2 · weight | D10: 7 | E10: number | F10: relative weight | G10: 0.0001 | H10: 100000
A11: /classes/fighter/reels/0/3/type | B11: class.fighter | C11: reels · 0 · 3 · type | D11: block | E11: string
A12: /classes/fighter/reels/0/3/tier | B12: class.fighter | C12: reels · 0 · 3 · tier | D12: 2 | E12: number | F12: tier | G12: 1 | H12: 4
A13: /classes/fighter/reels/0/3/weight | B13: class.fighter | C13: reels · 0 · 3 · weight | D13: 3 | E13: number | F13: relative weight | G13: 0.0001 | H13: 100000
A14: /classes/fighter/reels/0/4/type | B14: class.fighter | C14: reels · 0 · 4 · type | D14: heal | E14: string
A15: /classes/fighter/reels/0/4/tier | B15: class.fighter | C15: reels · 0 · 4 · tier | D15: 1 | E15: number | F15: tier | G15: 1 | H15: 4
A16: /classes/fighter/reels/0/4/weight | B16: class.fighter | C16: reels · 0 · 4 · weight | D16: 1 | E16: number | F16: relative weight | G16: 0.0001 | H16: 100000
A17: /classes/fighter/reels/0/5/type | B17: class.fighter | C17: reels · 0 · 5 · type | D17: blank | E17: string
A18: /classes/fighter/reels/0/5/tier | B18: class.fighter | C18: reels · 0 · 5 · tier | D18: 1 | E18: number | F18: tier | G18: 1 | H18: 4
A19: /classes/fighter/reels/0/5/weight | B19: class.fighter | C19: reels · 0 · 5 · weight | D19: 5 | E19: number | F19: relative weight | G19: 0.0001 | H19: 100000
A20: /classes/fighter/reels/1/0/type | B20: class.fighter | C20: reels · 1 · 0 · type | D20: attack | E20: string
A21: /classes/fighter/reels/1/0/tier | B21: class.fighter | C21: reels · 1 · 0 · tier | D21: 1 | E21: number | F21: tier | G21: 1 | H21: 4
A22: /classes/fighter/reels/1/0/weight | B22: class.fighter | C22: reels · 1 · 0 · weight | D22: 9 | E22: number | F22: relative weight | G22: 0.0001 | H22: 100000
A23: /classes/fighter/reels/1/1/type | B23: class.fighter | C23: reels · 1 · 1 · type | D23: attack | E23: string
A24: /classes/fighter/reels/1/1/tier | B24: class.fighter | C24: reels · 1 · 1 · tier | D24: 2 | E24: number | F24: tier | G24: 1 | H24: 4
A25: /classes/fighter/reels/1/1/weight | B25: class.fighter | C25: reels · 1 · 1 · weight | D25: 5 | E25: number | F25: relative weight | G25: 0.0001 | H25: 100000
A26: /classes/fighter/reels/1/2/type | B26: class.fighter | C26: reels · 1 · 2 · type | D26: block | E26: string
A27: /classes/fighter/reels/1/2/tier | B27: class.fighter | C27: reels · 1 · 2 · tier | D27: 1 | E27: number | F27: tier | G27: 1 | H27: 4
A28: /classes/fighter/reels/1/2/weight | B28: class.fighter | C28: reels · 1 · 2 · weight | D28: 7 | E28: number | F28: relative weight | G28: 0.0001 | H28: 100000
A29: /classes/fighter/reels/1/3/type | B29: class.fighter | C29: reels · 1 · 3 · type | D29: block | E29: string
A30: /classes/fighter/reels/1/3/tier | B30: class.fighter | C30: reels · 1 · 3 · tier | D30: 2 | E30: number | F30: tier | G30: 1 | H30: 4
A31: /classes/fighter/reels/1/3/weight | B31: class.fighter | C31: reels · 1 · 3 · weight | D31: 3 | E31: number | F31: relative weight | G31: 0.0001 | H31: 100000
A32: /classes/fighter/reels/1/4/type | B32: class.fighter | C32: reels · 1 · 4 · type | D32: heal | E32: string
A33: /classes/fighter/reels/1/4/tier | B33: class.fighter | C33: reels · 1 · 4 · tier | D33: 1 | E33: number | F33: tier | G33: 1 | H33: 4
A34: /classes/fighter/reels/1/4/weight | B34: class.fighter | C34: reels · 1 · 4 · weight | D34: 1 | E34: number | F34: relative weight | G34: 0.0001 | H34: 100000
A35: /classes/fighter/reels/1/5/type | B35: class.fighter | C35: reels · 1 · 5 · type | D35: blank | E35: string
A36: /classes/fighter/reels/1/5/tier | B36: class.fighter | C36: reels · 1 · 5 · tier | D36: 1 | E36: number | F36: tier | G36: 1 | H36: 4
A37: /classes/fighter/reels/1/5/weight | B37: class.fighter | C37: reels · 1 · 5 · weight | D37: 5 | E37: number | F37: relative weight | G37: 0.0001 | H37: 100000
A38: /classes/fighter/reels/1/6/type | B38: class.fighter | C38: reels · 1 · 6 · type | D38: class | E38: string
A39: /classes/fighter/reels/1/6/tier | B39: class.fighter | C39: reels · 1 · 6 · tier | D39: 1 | E39: number | F39: tier | G39: 1 | H39: 4
A40: /classes/fighter/reels/1/6/weight | B40: class.fighter | C40: reels · 1 · 6 · weight | D40: 3 | E40: number | F40: relative weight | G40: 0.0001 | H40: 100000
A41: /classes/fighter/reels/1/6/job | B41: class.fighter | C41: reels · 1 · 6 · job | D41: fighter | E41: string
A42: /classes/fighter/reels/2/0/type | B42: class.fighter | C42: reels · 2 · 0 · type | D42: attack | E42: string
A43: /classes/fighter/reels/2/0/tier | B43: class.fighter | C43: reels · 2 · 0 · tier | D43: 1 | E43: number | F43: tier | G43: 1 | H43: 4
A44: /classes/fighter/reels/2/0/weight | B44: class.fighter | C44: reels · 2 · 0 · weight | D44: 9 | E44: number | F44: relative weight | G44: 0.0001 | H44: 100000
A45: /classes/fighter/reels/2/1/type | B45: class.fighter | C45: reels · 2 · 1 · type | D45: attack | E45: string
A46: /classes/fighter/reels/2/1/tier | B46: class.fighter | C46: reels · 2 · 1 · tier | D46: 2 | E46: number | F46: tier | G46: 1 | H46: 4
A47: /classes/fighter/reels/2/1/weight | B47: class.fighter | C47: reels · 2 · 1 · weight | D47: 5 | E47: number | F47: relative weight | G47: 0.0001 | H47: 100000
A48: /classes/fighter/reels/2/2/type | B48: class.fighter | C48: reels · 2 · 2 · type | D48: block | E48: string
A49: /classes/fighter/reels/2/2/tier | B49: class.fighter | C49: reels · 2 · 2 · tier | D49: 1 | E49: number | F49: tier | G49: 1 | H49: 4
A50: /classes/fighter/reels/2/2/weight | B50: class.fighter | C50: reels · 2 · 2 · weight | D50: 7 | E50: number | F50: relative weight | G50: 0.0001 | H50: 100000
A51: /classes/fighter/reels/2/3/type | B51: class.fighter | C51: reels · 2 · 3 · type | D51: block | E51: string
A52: /classes/fighter/reels/2/3/tier | B52: class.fighter | C52: reels · 2 · 3 · tier | D52: 2 | E52: number | F52: tier | G52: 1 | H52: 4
A53: /classes/fighter/reels/2/3/weight | B53: class.fighter | C53: reels · 2 · 3 · weight | D53: 3 | E53: number | F53: relative weight | G53: 0.0001 | H53: 100000
A54: /classes/fighter/reels/2/4/type | B54: class.fighter | C54: reels · 2 · 4 · type | D54: heal | E54: string
A55: /classes/fighter/reels/2/4/tier | B55: class.fighter | C55: reels · 2 · 4 · tier | D55: 1 | E55: number | F55: tier | G55: 1 | H55: 4
A56: /classes/fighter/reels/2/4/weight | B56: class.fighter | C56: reels · 2 · 4 · weight | D56: 1 | E56: number | F56: relative weight | G56: 0.0001 | H56: 100000
A57: /classes/fighter/reels/2/5/type | B57: class.fighter | C57: reels · 2 · 5 · type | D57: blank | E57: string
A58: /classes/fighter/reels/2/5/tier | B58: class.fighter | C58: reels · 2 · 5 · tier | D58: 1 | E58: number | F58: tier | G58: 1 | H58: 4
A59: /classes/fighter/reels/2/5/weight | B59: class.fighter | C59: reels · 2 · 5 · weight | D59: 5 | E59: number | F59: relative weight | G59: 0.0001 | H59: 100000
A60: /classes/healer/reels/0/0/type | B60: class.healer | C60: reels · 0 · 0 · type | D60: heal | E60: string
A61: /classes/healer/reels/0/0/tier | B61: class.healer | C61: reels · 0 · 0 · tier | D61: 1 | E61: number | F61: tier | G61: 1 | H61: 4
A62: /classes/healer/reels/0/0/weight | B62: class.healer | C62: reels · 0 · 0 · weight | D62: 14 | E62: number | F62: relative weight | G62: 0.0001 | H62: 100000
A63: /classes/healer/reels/0/1/type | B63: class.healer | C63: reels · 0 · 1 · type | D63: heal | E63: string
A64: /classes/healer/reels/0/1/tier | B64: class.healer | C64: reels · 0 · 1 · tier | D64: 2 | E64: number | F64: tier | G64: 1 | H64: 4
A65: /classes/healer/reels/0/1/weight | B65: class.healer | C65: reels · 0 · 1 · weight | D65: 12 | E65: number | F65: relative weight | G65: 0.0001 | H65: 100000
A66: /classes/healer/reels/0/2/type | B66: class.healer | C66: reels · 0 · 2 · type | D66: block | E66: string
A67: /classes/healer/reels/0/2/tier | B67: class.healer | C67: reels · 0 · 2 · tier | D67: 1 | E67: number | F67: tier | G67: 1 | H67: 4
A68: /classes/healer/reels/0/2/weight | B68: class.healer | C68: reels · 0 · 2 · weight | D68: 2 | E68: number | F68: relative weight | G68: 0.0001 | H68: 100000
A69: /classes/healer/reels/0/3/type | B69: class.healer | C69: reels · 0 · 3 · type | D69: stun | E69: string
A70: /classes/healer/reels/0/3/tier | B70: class.healer | C70: reels · 0 · 3 · tier | D70: 1 | E70: number | F70: tier | G70: 1 | H70: 4
A71: /classes/healer/reels/0/3/weight | B71: class.healer | C71: reels · 0 · 3 · weight | D71: 1 | E71: number | F71: relative weight | G71: 0.0001 | H71: 100000
A72: /classes/healer/reels/0/4/type | B72: class.healer | C72: reels · 0 · 4 · type | D72: magic | E72: string
A73: /classes/healer/reels/0/4/tier | B73: class.healer | C73: reels · 0 · 4 · tier | D73: 1 | E73: number | F73: tier | G73: 1 | H73: 4
A74: /classes/healer/reels/0/4/weight | B74: class.healer | C74: reels · 0 · 4 · weight | D74: 1 | E74: number | F74: relative weight | G74: 0.0001 | H74: 100000
A75: /classes/healer/reels/0/5/type | B75: class.healer | C75: reels · 0 · 5 · type | D75: blank | E75: string
A76: /classes/healer/reels/0/5/tier | B76: class.healer | C76: reels · 0 · 5 · tier | D76: 1 | E76: number | F76: tier | G76: 1 | H76: 4
A77: /classes/healer/reels/0/5/weight | B77: class.healer | C77: reels · 0 · 5 · weight | D77: 4 | E77: number | F77: relative weight | G77: 0.0001 | H77: 100000
A78: /classes/healer/reels/1/0/type | B78: class.healer | C78: reels · 1 · 0 · type | D78: heal | E78: string
A79: /classes/healer/reels/1/0/tier | B79: class.healer | C79: reels · 1 · 0 · tier | D79: 1 | E79: number | F79: tier | G79: 1 | H79: 4
A80: /classes/healer/reels/1/0/weight | B80: class.healer | C80: reels · 1 · 0 · weight | D80: 14 | E80: number | F80: relative weight | G80: 0.0001 | H80: 100000
A81: /classes/healer/reels/1/1/type | B81: class.healer | C81: reels · 1 · 1 · type | D81: heal | E81: string
A82: /classes/healer/reels/1/1/tier | B82: class.healer | C82: reels · 1 · 1 · tier | D82: 2 | E82: number | F82: tier | G82: 1 | H82: 4
A83: /classes/healer/reels/1/1/weight | B83: class.healer | C83: reels · 1 · 1 · weight | D83: 12 | E83: number | F83: relative weight | G83: 0.0001 | H83: 100000
A84: /classes/healer/reels/1/2/type | B84: class.healer | C84: reels · 1 · 2 · type | D84: block | E84: string
A85: /classes/healer/reels/1/2/tier | B85: class.healer | C85: reels · 1 · 2 · tier | D85: 1 | E85: number | F85: tier | G85: 1 | H85: 4
A86: /classes/healer/reels/1/2/weight | B86: class.healer | C86: reels · 1 · 2 · weight | D86: 2 | E86: number | F86: relative weight | G86: 0.0001 | H86: 100000
A87: /classes/healer/reels/1/3/type | B87: class.healer | C87: reels · 1 · 3 · type | D87: stun | E87: string
A88: /classes/healer/reels/1/3/tier | B88: class.healer | C88: reels · 1 · 3 · tier | D88: 1 | E88: number | F88: tier | G88: 1 | H88: 4
A89: /classes/healer/reels/1/3/weight | B89: class.healer | C89: reels · 1 · 3 · weight | D89: 1 | E89: number | F89: relative weight | G89: 0.0001 | H89: 100000
A90: /classes/healer/reels/1/4/type | B90: class.healer | C90: reels · 1 · 4 · type | D90: magic | E90: string
A91: /classes/healer/reels/1/4/tier | B91: class.healer | C91: reels · 1 · 4 · tier | D91: 1 | E91: number | F91: tier | G91: 1 | H91: 4
A92: /classes/healer/reels/1/4/weight | B92: class.healer | C92: reels · 1 · 4 · weight | D92: 1 | E92: number | F92: relative weight | G92: 0.0001 | H92: 100000
A93: /classes/healer/reels/1/5/type | B93: class.healer | C93: reels · 1 · 5 · type | D93: blank | E93: string
A94: /classes/healer/reels/1/5/tier | B94: class.healer | C94: reels · 1 · 5 · tier | D94: 1 | E94: number | F94: tier | G94: 1 | H94: 4
A95: /classes/healer/reels/1/5/weight | B95: class.healer | C95: reels · 1 · 5 · weight | D95: 4 | E95: number | F95: relative weight | G95: 0.0001 | H95: 100000
A96: /classes/healer/reels/1/6/type | B96: class.healer | C96: reels · 1 · 6 · type | D96: class | E96: string
A97: /classes/healer/reels/1/6/tier | B97: class.healer | C97: reels · 1 · 6 · tier | D97: 1 | E97: number | F97: tier | G97: 1 | H97: 4
A98: /classes/healer/reels/1/6/weight | B98: class.healer | C98: reels · 1 · 6 · weight | D98: 3 | E98: number | F98: relative weight | G98: 0.0001 | H98: 100000
A99: /classes/healer/reels/1/6/job | B99: class.healer | C99: reels · 1 · 6 · job | D99: healer | E99: string
A100: /classes/healer/reels/2/0/type | B100: class.healer | C100: reels · 2 · 0 · type | D100: heal | E100: string
...

Sheet Items
A1: Stable field ID | B1: Entity ID | C1: Field / label | D1: Value (edit blue cells) | E1: Type | F1: Unit | G1: Minimum | H1: Maximum | I1: Notes
A2: /items/potion/name | B2: item.potion | C2: name | D2: Healing tonic | E2: string
A3: /items/potion/icon | B3: item.potion | C3: icon | D3: potion | E3: string
A4: /items/potion/brief | B4: item.potion | C4: brief | D4: {heal} HP | E4: string
A5: /items/potion/description | B5: item.potion | C5: description | D5: Restore {heal} HP to the selected living hero. | E5: string
A6: /items/potion/id | B6: item.potion | C6: id | D6: item.potion | E6: string | I6: READ ONLY
A7: /items/potion/heal | B7: item.potion | C7: heal | D7: 16 | E7: number | G7: 0 | H7: 100000
A8: /items/bomb/name | B8: item.bomb | C8: name | D8: Ink bomb | E8: string
A9: /items/bomb/icon | B9: item.bomb | C9: icon | D9: bomb | E9: string
A10: /items/bomb/brief | B10: item.bomb | C10: brief | D10: Roll damage + poison | E10: string
A11: /items/bomb/combat | B11: item.bomb | C11: combat | D11: TRUE | E11: boolean
A12: /items/bomb/description | B12: item.bomb | C12: description | D12: Roll three reels for damage and poison against the selected enemy. Three alike can crit. | E12: string
A13: /items/bomb/id | B13: item.bomb | C13: id | D13: item.bomb | E13: string | I13: READ ONLY
A14: /items/ward/name | B14: item.ward | C14: name | D14: Paper ward | E14: string
A15: /items/ward/icon | B15: item.ward | C15: icon | D15: ward | E15: string
A16: /items/ward/brief | B16: item.ward | C16: brief | D16: {block} team block | E16: string
A17: /items/ward/combat | B17: item.ward | C17: combat | D17: TRUE | E17: boolean
A18: /items/ward/description | B18: item.ward | C18: description | D18: Add {block} shared block for this battle. | E18: string
A19: /items/ward/id | B19: item.ward | C19: id | D19: item.ward | E19: string | I19: READ ONLY
A20: /items/ward/block | B20: item.ward | C20: block | D20: 5 | E20: number | G20: 0 | H20: 100000
A21: /items/antidote/name | B21: item.antidote | C21: name | D21: Antidote | E21: string
A22: /items/antidote/icon | B22: item.antidote | C22: icon | D22: antidote | E22: string
A23: /items/antidote/brief | B23: item.antidote | C23: brief | D23: Cure poison | E23: string
A24: /items/antidote/description | B24: item.antidote | C24: description | D24: Remove poison from the selected living hero. | E24: string
A25: /items/antidote/id | B25: item.antidote | C25: id | D25: item.antidote | E25: string | I25: READ ONLY
A26: /items/bandage/name | B26: item.bandage | C26: name | D26: Bandage | E26: string
A27: /items/bandage/icon | B27: item.bandage | C27: icon | D27: bandage | E27: string
A28: /items/bandage/brief | B28: item.bandage | C28: brief | D28: {heal} HP | E28: string
A29: /items/bandage/description | B29: item.bandage | C29: description | D29: Restore {heal} HP to the selected living hero. | E29: string
A30: /items/bandage/id | B30: item.bandage | C30: id | D30: item.bandage | E30: string | I30: READ ONLY
A31: /items/bandage/heal | B31: item.bandage | C31: heal | D31: 8 | E31: number | G31: 0 | H31: 100000
A32: /items/salve/name | B32: item.salve | C32: name | D32: Mending salve | E32: string
A33: /items/salve/icon | B33: item.salve | C33: icon | D33: salve | E33: string
A34: /items/salve/brief | B34: item.salve | C34: brief | D34: {heal} HP to everyone | E34: string
A35: /items/salve/description | B35: item.salve | C35: description | D35: Restore {heal} HP to every living party member. | E35: string
A36: /items/salve/id | B36: item.salve | C36: id | D36: item.salve | E36: string | I36: READ ONLY
A37: /items/salve/heal | B37: item.salve | C37: heal | D37: 6 | E37: number | G37: 0 | H37: 100000
A38: /items/ember/name | B38: item.ember | C38: name | D38: Ember draught | E38: string
A39: /items/ember/icon | B39: item.ember | C39: icon | D39: flame | E39: string
A40: /items/ember/brief | B40: item.ember | C40: brief | D40: Damage + protection | E40: string
A41: /items/ember/combat | B41: item.ember | C41: combat | D41: TRUE | E41: boolean
A42: /items/ember/description | B42: item.ember | C42: description | D42: Stimulate the selected hero: a small damage and defence bonus for {stimulantTurns} of their actions. | E42: string
A43: /items/ember/id | B43: item.ember | C43: id | D43: item.ember | E43: string | I43: READ ONLY
A44: /items/ember/stimulant | B44: item.ember | C44: stimulant | D44: 2 | E44: number | G44: 0 | H44: 100000
A45: /items/oil/name | B45: item.oil | C45: name | D45: Sharpening oil | E45: string
A46: /items/oil/icon | B46: item.oil | C46: icon | D46: oil | E46: string
A47: /items/oil/brief | B47: item.oil | C47: brief | D47: +{rage} rage | E47: string
A48: /items/oil/combat | B48: item.oil | C48: combat | D48: TRUE | E48: boolean
A49: /items/oil/description | B49: item.oil | C49: description | D49: Give the selected hero {rage} rage, adding damage until this battle ends. | E49: string
A50: /items/oil/id | B50: item.oil | C50: id | D50: item.oil | E50: string | I50: READ ONLY
A51: /items/oil/rage | B51: item.oil | C51: rage | D51: 2 | E51: number | G51: 0 | H51: 100000
A52: /items/frost/name | B52: item.frost | C52: name | D52: Frost vial | E52: string
A53: /items/frost/icon | B53: item.frost | C53: icon | D53: frost | E53: string
A54: /items/frost/brief | B54: item.frost | C54: brief | D54: Stun one enemy | E54: string
A55: /items/frost/combat | B55: item.frost | C55: combat | D55: TRUE | E55: boolean
A56: /items/frost/description | B56: item.frost | C56: description | D56: Attempt a strength-{stun} stun on the selected enemy. Armour can absorb it. | E56: string
A57: /items/frost/id | B57: item.frost | C57: id | D57: item.frost | E57: string | I57: READ ONLY
A58: /items/frost/stun | B58: item.frost | C58: stun | D58: 2 | E58: number | G58: 0 | H58: 100000
A59: /items/firebomb/name | B59: item.firebomb | C59: name | D59: Cinder flask | E59: string
A60: /items/firebomb/icon | B60: item.firebomb | C60: icon | D60: flame | E60: string
A61: /items/firebomb/brief | B61: item.firebomb | C61: brief | D61: Scorch all enemies | E61: string
A62: /items/firebomb/combat | B62: item.firebomb | C62: combat | D62: TRUE | E62: boolean
A63: /items/firebomb/description | B63: item.firebomb | C63: description | D63: Deal {damageBase} plus floor depth divided by {depthDivisor}, rounded down, in magic damage to every enemy. | E63: string
A64: /items/firebomb/id | B64: item.firebomb | C64: id | D64: item.firebomb | E64: string | I64: READ ONLY
A65: /items/firebomb/damageBase | B65: item.firebomb | C65: damageBase | D65: 8 | E65: number | G65: 0 | H65: 100000
A66: /items/firebomb/depthDivisor | B66: item.firebomb | C66: depthDivisor | D66: 2 | E66: number | G66: 1 | H66: 10000
A67: /items/venom/name | B67: item.venom | C67: name | D67: Venom vial | E67: string
A68: /items/venom/icon | B68: item.venom | C68: icon | D68: poison | E68: string
A69: /items/venom/brief | B69: item.venom | C69: brief | D69: Poison for {poisonTurns} turns | E69: string
A70: /items/venom/combat | B70: item.venom | C70: combat | D70: TRUE | E70: boolean
A71: /items/venom/description | B71: item.venom | C71: description | D71: Poison the selected enemy for {poisonTurns} tiny, armour-piercing damage ticks. | E71: string
A72: /items/venom/id | B72: item.venom | C72: id | D72: item.venom | E72: string | I72: READ ONLY
A73: /items/venom/poison | B73: item.venom | C73: poison | D73: 4 | E73: number | G73: 0 | H73: 100000
A74: /items/chalk/name | B74: item.chalk | C74: name | D74: Chalk map | E74: string
A75: /items/chalk/icon | B75: item.chalk | C75: icon | D75: chalk | E75: string
A76: /items/chalk/brief | B76: item.chalk | C76: brief | D76: Reveal neighbours | E76: string
A77: /items/chalk/outside | B77: item.chalk | C77: outside | D77: TRUE | E77: boolean
A78: /items/chalk/description | B78: item.chalk | C78: description | D78: Reveal adjacent and diagonal tiles without activating them. Cannot be used during combat. | E78: string
A79: /items/chalk/id | B79: item.chalk | C79: id | D79: item.chalk | E79: string | I79: READ ONLY
A80: /items/ration/name | B80: item.ration | C80: name | D80: Trail ration | E80: string
A81: /items/ration/icon | B81: item.ration | C81: icon | D81: ration | E81: string
A82: /items/ration/brief | B82: item.ration | C82: brief | D82: {healthPercent}% maximum HP | E82: string
A83: /items/ration/description | B83: item.ration | C83: description | D83: Restore {healthPercent}% of the selected hero’s maximum HP. | E83: string
A84: /items/ration/id | B84: item.ration | C84: id | D84: item.ration | E84: string | I84: READ ONLY
A85: /items/ration/healthFraction | B85: item.ration | C85: healthFraction | D85: 0.3 | E85: number | G85: 0.0001 | H85: 1
A86: /tuning/rollInkBomb.coefficient.1/value | B86: rule.tuning.rollInkBomb.coefficient.1 | C86: rollInkBomb · coefficient 1 | D86: 3 | E86: number | F86: count or coefficient | G86: 1 | H86: 100 | I86: Coefficient in: se.attack += Math.floor(state.depth / 3); const multiplier = await rollCrit
A87: /tuning/rollInkBomb.coefficient.1/category | B87: rule.tuning.rollInkBomb.coefficient.1 | C87: rollInkBomb · coefficient 1 | D87: Items | E87: string | F87: count or coefficient | I87: READ ONLY
A88: /tuning/rollInkBomb.coefficient.1/label | B88: rule.tuning.rollInkBomb.coefficient.1 | C88: rollInkBomb · coefficient 1 | D88: rollInkBomb · coefficient 1 | E88: string | F88: count or coefficient | I88: READ ONLY
A89: /tuning/rollInkBomb.coefficient.1/description | B89: rule.tuning.rollInkBomb.coefficient.1 | C89: rollInkBomb · coefficient 1 | D89: Coefficient in: se.attack += Math.floor(state.depth / 3); const multiplier = await rollCrit | E89: string | F89: count or coefficient | I89: READ ONLY
A90: /tuning/rollInkBomb.coefficient.1/unit | B90: rule.tuning.rollInkBomb.coefficient.1 | C90: rollInkBomb · coefficient 1 | D90: count or coefficient | E90: string | F90: count or coefficient | I90: READ ONLY
A91: /tuning/rollInkBomb.coefficient.1/min | B91: rule.tuning.rollInkBomb.coefficient.1 | C91: rollInkBomb · coefficient 1 | D91: 0 | E91: number | F91: count or coefficient | G91: 1 | H91: 100 | I91: READ ONLY
A92: /tuning/rollInkBomb.coefficient.1/max | B92: rule.tuning.rollInkBomb.coefficient.1 | C92: rollInkBomb · coefficient 1 | D92: 100 | E92: number | F92: count or coefficient | G92: 1 | H92: 100 | I92: READ ONLY
A93: /tuning/rollInkBomb.coefficient.1/integer | B93: rule.tuning.rollInkBomb.coefficient.1 | C93: rollInkBomb · coefficient 1 | D93: TRUE | E93: boolean | F93: count or coefficient | I93: READ ONLY

Sheet Equipment
A1: Stable field ID | B1: Entity ID | C1: Field / label | D1: Value (edit blue cells) | E1: Type | F1: Unit | G1: Minimum | H1: Maximum | I1: Notes
A2: /equipment/ironSignet/name | B2: equipment.ironSignet | C2: name | D2: Iron Signet | E2: string
A3: /equipment/ironSignet/icon | B3: equipment.ironSignet | C3: icon | D3: rage | E3: string
A4: /equipment/ironSignet/job | B4: equipment.ironSignet | C4: job | D4: fighter | E4: string
A5: /equipment/ironSignet/brief | B5: equipment.ironSignet | C5: brief | D5: +{attack} blade damage | E5: string
A6: /equipment/ironSignet/description | B6: equipment.ironSignet | C6: description | D6: Tank equipment. Every damaging roll gains {attack} damage. | E6: string
A7: /equipment/ironSignet/attack | B7: equipment.ironSignet | C7: attack | D7: 2 | E7: number | G7: 0 | H7: 100000
A8: /equipment/ironSignet/id | B8: equipment.ironSignet | C8: id | D8: equipment.ironSignet | E8: string | I8: READ ONLY
A9: /equipment/bulwarkBadge/name | B9: equipment.bulwarkBadge | C9: name | D9: Bulwark Badge | E9: string
A10: /equipment/bulwarkBadge/icon | B10: equipment.bulwarkBadge | C10: icon | D10: block | E10: string
A11: /equipment/bulwarkBadge/job | B11: equipment.bulwarkBadge | C11: job | D11: fighter | E11: string
A12: /equipment/bulwarkBadge/brief | B12: equipment.bulwarkBadge | C12: brief | D12: +{guard} opening armour | E12: string
A13: /equipment/bulwarkBadge/description | B13: equipment.bulwarkBadge | C13: description | D13: Tank equipment. Start fights with {guard} team block; resist {defence} damage per incoming hit. | E13: string
A14: /equipment/bulwarkBadge/guard | B14: equipment.bulwarkBadge | C14: guard | D14: 3 | E14: number | G14: 0 | H14: 100000
A15: /equipment/bulwarkBadge/defence | B15: equipment.bulwarkBadge | C15: defence | D15: 1 | E15: number | G15: 0 | H15: 100000
A16: /equipment/bulwarkBadge/id | B16: equipment.bulwarkBadge | C16: id | D16: equipment.bulwarkBadge | E16: string | I16: READ ONLY
A17: /equipment/glassRosary/name | B17: equipment.glassRosary | C17: name | D17: Glass Rosary | E17: string
A18: /equipment/glassRosary/icon | B18: equipment.glassRosary | C18: icon | D18: heal | E18: string
A19: /equipment/glassRosary/job | B19: equipment.glassRosary | C19: job | D19: healer | E19: string
A20: /equipment/glassRosary/brief | B20: equipment.glassRosary | C20: brief | D20: +{heal} healing | E20: string
A21: /equipment/glassRosary/description | B21: equipment.glassRosary | C21: description | D21: Healer equipment. Add {heal} HP to healing rolls. | E21: string
A22: /equipment/glassRosary/heal | B22: equipment.glassRosary | C22: heal | D22: 2 | E22: number | G22: 0 | H22: 100000
A23: /equipment/glassRosary/id | B23: equipment.glassRosary | C23: id | D23: equipment.glassRosary | E23: string | I23: READ ONLY
A24: /equipment/mercyBell/name | B24: equipment.mercyBell | C24: name | D24: Mercy Bell | E24: string
A25: /equipment/mercyBell/icon | B25: equipment.mercyBell | C25: icon | D25: blessing | E25: string
A26: /equipment/mercyBell/job | B26: equipment.mercyBell | C26: job | D26: healer | E26: string
A27: /equipment/mercyBell/brief | B27: equipment.mercyBell | C27: brief | D27: A little sanctuary | E27: string
A28: /equipment/mercyBell/description | B28: equipment.mercyBell | C28: description | D28: Healer equipment. Every roll heals the party by {teamHeal} and adds {block} team block. | E28: string
A29: /equipment/mercyBell/teamHeal | B29: equipment.mercyBell | C29: teamHeal | D29: 1 | E29: number | G29: 0 | H29: 100000
A30: /equipment/mercyBell/block | B30: equipment.mercyBell | C30: block | D30: 1 | E30: number | G30: 0 | H30: 100000
A31: /equipment/mercyBell/id | B31: equipment.mercyBell | C31: id | D31: equipment.mercyBell | E31: string | I31: READ ONLY
A32: /equipment/silentBoots/name | B32: equipment.silentBoots | C32: name | D32: Silent Boots | E32: string
A33: /equipment/silentBoots/icon | B33: equipment.silentBoots | C33: icon | D33: flurry | E33: string
A34: /equipment/silentBoots/job | B34: equipment.silentBoots | C34: job | D34: rogue | E34: string
A35: /equipment/silentBoots/brief | B35: equipment.silentBoots | C35: brief | D35: Every {stunEveryOrdinal} roll stuns | E35: string
A36: /equipment/silentBoots/description | B36: equipment.silentBoots | C36: description | D36: Rogue equipment. +{attack} damage; every {stunEveryOrdinal} roll stuns the target. | E36: string
A37: /equipment/silentBoots/attack | B37: equipment.silentBoots | C37: attack | D37: 1 | E37: number | G37: 0 | H37: 100000
A38: /equipment/silentBoots/stunEvery | B38: equipment.silentBoots | C38: stunEvery | D38: 4 | E38: number | G38: 0 | H38: 100000
A39: /equipment/silentBoots/id | B39: equipment.silentBoots | C39: id | D39: equipment.silentBoots | E39: string | I39: READ ONLY
A40: /equipment/serpentPin/name | B40: equipment.serpentPin | C40: name | D40: Serpent Pin | E40: string
A41: /equipment/serpentPin/icon | B41: equipment.serpentPin | C41: icon | D41: poison | E41: string
A42: /equipment/serpentPin/job | B42: equipment.serpentPin | C42: job | D42: rogue | E42: string
A43: /equipment/serpentPin/brief | B43: equipment.serpentPin | C43: brief | D43: Venom-tipped blades | E43: string
A44: /equipment/serpentPin/description | B44: equipment.serpentPin | C44: description | D44: Rogue equipment. Damaging rolls add a short poison. | E44: string
A45: /equipment/serpentPin/poison | B45: equipment.serpentPin | C45: poison | D45: 1 | E45: number | G45: 0 | H45: 100000
A46: /equipment/serpentPin/id | B46: equipment.serpentPin | C46: id | D46: equipment.serpentPin | E46: string | I46: READ ONLY
A47: /equipment/starLens/name | B47: equipment.starLens | C47: name | D47: Star Lens | E47: string
A48: /equipment/starLens/icon | B48: equipment.starLens | C48: icon | D48: magic | E48: string
A49: /equipment/starLens/job | B49: equipment.starLens | C49: job | D49: mage | E49: string
A50: /equipment/starLens/brief | B50: equipment.starLens | C50: brief | D50: +{magic} magic damage | E50: string
A51: /equipment/starLens/description | B51: equipment.starLens | C51: description | D51: Mage equipment. Add {magic} magic damage to every damaging roll. | E51: string
A52: /equipment/starLens/magic | B52: equipment.starLens | C52: magic | D52: 2 | E52: number | G52: 0 | H52: 100000
A53: /equipment/starLens/id | B53: equipment.starLens | C53: id | D53: equipment.starLens | E53: string | I53: READ ONLY
A54: /equipment/stormQuill/name | B54: equipment.stormQuill | C54: name | D54: Storm Quill | E54: string
A55: /equipment/stormQuill/icon | B55: equipment.stormQuill | C55: icon | D55: flame | E55: string
A56: /equipment/stormQuill/job | B56: equipment.stormQuill | C56: job | D56: mage | E56: string
A57: /equipment/stormQuill/brief | B57: equipment.stormQuill | C57: brief | D57: Power every {stimEveryOrdinal} roll | E57: string
A58: /equipment/stormQuill/description | B58: equipment.stormQuill | C58: description | D58: Mage equipment. Every {stimEveryOrdinal} roll grants a stimulant; +{magic} magic damage. | E58: string
A59: /equipment/stormQuill/magic | B59: equipment.stormQuill | C59: magic | D59: 1 | E59: number | G59: 0 | H59: 100000
A60: /equipment/stormQuill/stimEvery | B60: equipment.stormQuill | C60: stimEvery | D60: 3 | E60: number | G60: 0 | H60: 100000
A61: /equipment/stormQuill/id | B61: equipment.stormQuill | C61: id | D61: equipment.stormQuill | E61: string | I61: READ ONLY
A62: /equipment/stormQuill/stimulantPower | B62: equipment.stormQuill | C62: stimulantPower | D62: 2 | E62: number | G62: 0 | H62: 100000

Sheet Artefacts
A1: Stable field ID | B1: Entity ID | C1: Field / label | D1: Value (edit blue cells) | E1: Type | F1: Unit | G1: Minimum | H1: Maximum | I1: Notes
A2: /artefacts/0/key | B2: artefact.attack | C2: key | D2: attack | E2: string
A3: /artefacts/0/name | B3: artefact.attack | C3: name | D3: Fang of the Margin | E3: string
A4: /artefacts/0/base | B4: artefact.attack | C4: base | D4: 1 | E4: number | G4: 0 | H4: 100000
A5: /artefacts/0/scale | B5: artefact.attack | C5: scale | D5: 0.6 | E5: number | G5: 0 | H5: 100000
A6: /artefacts/0/id | B6: artefact.attack | C6: id | D6: artefact.attack | E6: string | I6: READ ONLY
A7: /artefacts/1/key | B7: artefact.heal | C7: key | D7: heal | E7: string
A8: /artefacts/1/name | B8: artefact.heal | C8: name | D8: The Glass Tear | E8: string
A9: /artefacts/1/base | B9: artefact.heal | C9: base | D9: 1 | E9: number | G9: 0 | H9: 100000
A10: /artefacts/1/scale | B10: artefact.heal | C10: scale | D10: 0.5 | E10: number | G10: 0 | H10: 100000
A11: /artefacts/1/id | B11: artefact.heal | C11: id | D11: artefact.heal | E11: string | I11: READ ONLY
A12: /artefacts/2/key | B12: artefact.block | C12: key | D12: block | E12: string
A13: /artefacts/2/name | B13: artefact.block | C13: name | D13: Iron Pennant | E13: string
A14: /artefacts/2/base | B14: artefact.block | C14: base | D14: 1 | E14: number | G14: 0 | H14: 100000
A15: /artefacts/2/scale | B15: artefact.block | C15: scale | D15: 0.5 | E15: number | G15: 0 | H15: 100000
A16: /artefacts/2/id | B16: artefact.block | C16: id | D16: artefact.block | E16: string | I16: READ ONLY
A17: /artefacts/3/key | B17: artefact.gold | C17: key | D17: gold | E17: string
A18: /artefacts/3/name | B18: artefact.gold | C18: name | D18: Lucky Farthing | E18: string
A19: /artefacts/3/base | B19: artefact.gold | C19: base | D19: 10 | E19: number | G19: 0 | H19: 100000
A20: /artefacts/3/scale | B20: artefact.gold | C20: scale | D20: 3 | E20: number | G20: 0 | H20: 100000
A21: /artefacts/3/id | B21: artefact.gold | C21: id | D21: artefact.gold | E21: string | I21: READ ONLY
A22: /artefacts/4/key | B22: artefact.guard | C22: key | D22: guard | E22: string
A23: /artefacts/4/name | B23: artefact.guard | C23: name | D23: Ember Seal | E23: string
A24: /artefacts/4/base | B24: artefact.guard | C24: base | D24: 1 | E24: number | G24: 0 | H24: 100000
A25: /artefacts/4/scale | B25: artefact.guard | C25: scale | D25: 0.5 | E25: number | G25: 0 | H25: 100000
A26: /artefacts/4/id | B26: artefact.guard | C26: id | D26: artefact.guard | E26: string | I26: READ ONLY
A27: /artefacts/5/key | B27: artefact.revive | C27: key | D27: revive | E27: string
A28: /artefacts/5/name | B28: artefact.revive | C28: name | D28: Revive Stone | E28: string
A29: /artefacts/5/base | B29: artefact.revive | C29: base | D29: 1 | E29: number | G29: 0 | H29: 100000
A30: /artefacts/5/scale | B30: artefact.revive | C30: scale | D30: 0 | E30: number | G30: 0 | H30: 100000
A31: /artefacts/5/id | B31: artefact.revive | C31: id | D31: artefact.revive | E31: string | I31: READ ONLY
A32: /tuning/makeArtefact.name.1/value | B32: rule.tuning.makeArtefact.name.1 | C32: makeArtefact · name 1 | D32: 3 | E32: number | F32: count or coefficient | G32: 0 | H32: 3 | I32: Coefficient in: ["I", "II", "III", "IV"][Math.min(3, Math.floor((depth - 1) / 3))], k
A33: /tuning/makeArtefact.name.1/category | B33: rule.tuning.makeArtefact.name.1 | C33: makeArtefact · name 1 | D33: Artefacts | E33: string | F33: count or coefficient | I33: READ ONLY
A34: /tuning/makeArtefact.name.1/label | B34: rule.tuning.makeArtefact.name.1 | C34: makeArtefact · name 1 | D34: makeArtefact · name 1 | E34: string | F34: count or coefficient | I34: READ ONLY
A35: /tuning/makeArtefact.name.1/description | B35: rule.tuning.makeArtefact.name.1 | C35: makeArtefact · name 1 | D35: Coefficient in: ["I", "II", "III", "IV"][Math.min(3, Math.floor((depth - 1) / 3))], k | E35: string | F35: count or coefficient | I35: READ ONLY
A36: /tuning/makeArtefact.name.1/unit | B36: rule.tuning.makeArtefact.name.1 | C36: makeArtefact · name 1 | D36: count or coefficient | E36: string | F36: count or coefficient | I36: READ ONLY
A37: /tuning/makeArtefact.name.1/min | B37: rule.tuning.makeArtefact.name.1 | C37: makeArtefact · name 1 | D37: 0 | E37: number | F37: count or coefficient | G37: 0 | H37: 3 | I37: READ ONLY
A38: /tuning/makeArtefact.name.1/max | B38: rule.tuning.makeArtefact.name.1 | C38: makeArtefact · name 1 | D38: 100 | E38: number | F38: count or coefficient | G38: 0 | H38: 3 | I38: READ ONLY
A39: /tuning/makeArtefact.name.1/integer | B39: rule.tuning.makeArtefact.name.1 | C39: makeArtefact · name 1 | D39: TRUE | E39: boolean | F39: count or coefficient | I39: READ ONLY
A40: /tuning/makeArtefact.name.2/value | B40: rule.tuning.makeArtefact.name.2 | C40: makeArtefact · name 2 | D40: 3 | E40: number | F40: count or coefficient | G40: 1 | H40: 100 | I40: Coefficient in: [Math.min(3, Math.floor((depth - 1) / 3))], key: t.key, power: Math.c
A41: /tuning/makeArtefact.name.2/category | B41: rule.tuning.makeArtefact.name.2 | C41: makeArtefact · name 2 | D41: Artefacts | E41: string | F41: count or coefficient | I41: READ ONLY
A42: /tuning/makeArtefact.name.2/label | B42: rule.tuning.makeArtefact.name.2 | C42: makeArtefact · name 2 | D42: makeArtefact · name 2 | E42: string | F42: count or coefficient | I42: READ ONLY
A43: /tuning/makeArtefact.name.2/description | B43: rule.tuning.makeArtefact.name.2 | C43: makeArtefact · name 2 | D43: Coefficient in: [Math.min(3, Math.floor((depth - 1) / 3))], key: t.key, power: Math.c | E43: string | F43: count or coefficient | I43: READ ONLY
A44: /tuning/makeArtefact.name.2/unit | B44: rule.tuning.makeArtefact.name.2 | C44: makeArtefact · name 2 | D44: count or coefficient | E44: string | F44: count or coefficient | I44: READ ONLY
A45: /tuning/makeArtefact.name.2/min | B45: rule.tuning.makeArtefact.name.2 | C45: makeArtefact · name 2 | D45: 0 | E45: number | F45: count or coefficient | G45: 1 | H45: 100 | I45: READ ONLY
A46: /tuning/makeArtefact.name.2/max | B46: rule.tuning.makeArtefact.name.2 | C46: makeArtefact · name 2 | D46: 100 | E46: number | F46: count or coefficient | G46: 1 | H46: 100 | I46: READ ONLY
A47: /tuning/makeArtefact.name.2/integer | B47: rule.tuning.makeArtefact.name.2 | C47: makeArtefact · name 2 | D47: TRUE | E47: boolean | F47: count or coefficient | I47: READ ONLY

Sheet Enemies
A1: Stable field ID | B1: Entity ID | C1: Field / label | D1: Value (edit blue cells) | E1: Type | F1: Unit | G1: Minimum | H1: Maximum | I1: Notes
A2: /enemies/enemy.ink-rat/id | B2: enemy.ink-rat | C2: id | D2: enemy.ink-rat | E2: string | I2: READ ONLY
A3: /enemies/enemy.ink-rat/name | B3: enemy.ink-rat | C3: name | D3: The ink rat | E3: string
A4: /enemies/enemy.ink-rat/art | B4: enemy.ink-rat | C4: art | D4: rat | E4: string
A5: /enemies/enemy.ink-rat/minFloor | B5: enemy.ink-rat | C5: minFloor | D5: 1 | E5: number | G5: 1 | H5: 10
A6: /enemies/enemy.ink-rat/maxFloor | B6: enemy.ink-rat | C6: maxFloor | D6: 3 | E6: number | G6: 1 | H6: 10
A7: /enemies/enemy.ink-rat/hpMultiplier | B7: enemy.ink-rat | C7: hpMultiplier | D7: 1 | E7: number | G7: 0.0001 | H7: 100
A8: /enemies/enemy.ink-rat/damageMultiplier | B8: enemy.ink-rat | C8: damageMultiplier | D8: 1 | E8: number | G8: 0.0001 | H8: 100
A9: /enemies/enemy.ink-rat/frequencyOverride | B9: enemy.ink-rat | C9: frequencyOverride | D9: 0 | E9: number | G9: 0 | H9: 10
A10: /enemies/enemy.ink-rat/strikesOverride | B10: enemy.ink-rat | C10: strikesOverride | D10: 0 | E10: number | G10: 0 | H10: 10
A11: /enemies/enemy.ink-rat/reelSet | B11: enemy.ink-rat | C11: reelSet | D11: reel.enemy.rat | E11: string
A12: /enemies/enemy.margin-wraith/id | B12: enemy.margin-wraith | C12: id | D12: enemy.margin-wraith | E12: string | I12: READ ONLY
A13: /enemies/enemy.margin-wraith/name | B13: enemy.margin-wraith | C13: name | D13: Margin wraith | E13: string
A14: /enemies/enemy.margin-wraith/art | B14: enemy.margin-wraith | C14: art | D14: ghost | E14: string
A15: /enemies/enemy.margin-wraith/minFloor | B15: enemy.margin-wraith | C15: minFloor | D15: 1 | E15: number | G15: 1 | H15: 10
A16: /enemies/enemy.margin-wraith/maxFloor | B16: enemy.margin-wraith | C16: maxFloor | D16: 3 | E16: number | G16: 1 | H16: 10
A17: /enemies/enemy.margin-wraith/hpMultiplier | B17: enemy.margin-wraith | C17: hpMultiplier | D17: 1 | E17: number | G17: 0.0001 | H17: 100
A18: /enemies/enemy.margin-wraith/damageMultiplier | B18: enemy.margin-wraith | C18: damageMultiplier | D18: 1 | E18: number | G18: 0.0001 | H18: 100
A19: /enemies/enemy.margin-wraith/frequencyOverride | B19: enemy.margin-wraith | C19: frequencyOverride | D19: 0 | E19: number | G19: 0 | H19: 10
A20: /enemies/enemy.margin-wraith/strikesOverride | B20: enemy.margin-wraith | C20: strikesOverride | D20: 0 | E20: number | G20: 0 | H20: 10
A21: /enemies/enemy.margin-wraith/reelSet | B21: enemy.margin-wraith | C21: reelSet | D21: reel.enemy.ghost | E21: string
A22: /enemies/enemy.blotling/id | B22: enemy.blotling | C22: id | D22: enemy.blotling | E22: string | I22: READ ONLY
A23: /enemies/enemy.blotling/name | B23: enemy.blotling | C23: name | D23: Blotling | E23: string
A24: /enemies/enemy.blotling/art | B24: enemy.blotling | C24: art | D24: slime | E24: string
A25: /enemies/enemy.blotling/minFloor | B25: enemy.blotling | C25: minFloor | D25: 1 | E25: number | G25: 1 | H25: 10
A26: /enemies/enemy.blotling/maxFloor | B26: enemy.blotling | C26: maxFloor | D26: 3 | E26: number | G26: 1 | H26: 10
A27: /enemies/enemy.blotling/hpMultiplier | B27: enemy.blotling | C27: hpMultiplier | D27: 1 | E27: number | G27: 0.0001 | H27: 100
A28: /enemies/enemy.blotling/damageMultiplier | B28: enemy.blotling | C28: damageMultiplier | D28: 1 | E28: number | G28: 0.0001 | H28: 100
A29: /enemies/enemy.blotling/frequencyOverride | B29: enemy.blotling | C29: frequencyOverride | D29: 0 | E29: number | G29: 0 | H29: 10
A30: /enemies/enemy.blotling/strikesOverride | B30: enemy.blotling | C30: strikesOverride | D30: 0 | E30: number | G30: 0 | H30: 10
A31: /enemies/enemy.blotling/reelSet | B31: enemy.blotling | C31: reelSet | D31: reel.enemy.slime | E31: string
A32: /enemies/enemy.skeletal-warrior/id | B32: enemy.skeletal-warrior | C32: id | D32: enemy.skeletal-warrior | E32: string | I32: READ ONLY
A33: /enemies/enemy.skeletal-warrior/name | B33: enemy.skeletal-warrior | C33: name | D33: Skeletal warrior | E33: string
A34: /enemies/enemy.skeletal-warrior/art | B34: enemy.skeletal-warrior | C34: art | D34: skull | E34: string
A35: /enemies/enemy.skeletal-warrior/minFloor | B35: enemy.skeletal-warrior | C35: minFloor | D35: 1 | E35: number | G35: 1 | H35: 10
A36: /enemies/enemy.skeletal-warrior/maxFloor | B36: enemy.skeletal-warrior | C36: maxFloor | D36: 3 | E36: number | G36: 1 | H36: 10
A37: /enemies/enemy.skeletal-warrior/hpMultiplier | B37: enemy.skeletal-warrior | C37: hpMultiplier | D37: 1 | E37: number | G37: 0.0001 | H37: 100
A38: /enemies/enemy.skeletal-warrior/damageMultiplier | B38: enemy.skeletal-warrior | C38: damageMultiplier | D38: 1 | E38: number | G38: 0.0001 | H38: 100
A39: /enemies/enemy.skeletal-warrior/frequencyOverride | B39: enemy.skeletal-warrior | C39: frequencyOverride | D39: 0 | E39: number | G39: 0 | H39: 10
A40: /enemies/enemy.skeletal-warrior/strikesOverride | B40: enemy.skeletal-warrior | C40: strikesOverride | D40: 0 | E40: number | G40: 0 | H40: 10
A41: /enemies/enemy.skeletal-warrior/reelSet | B41: enemy.skeletal-warrior | C41: reelSet | D41: reel.enemy.skull | E41: string
A42: /enemies/enemy.chainbound-revenant/id | B42: enemy.chainbound-revenant | C42: id | D42: enemy.chainbound-revenant | E42: string | I42: READ ONLY
A43: /enemies/enemy.chainbound-revenant/name | B43: enemy.chainbound-revenant | C43: name | D43: Chainbound revenant | E43: string
A44: /enemies/enemy.chainbound-revenant/art | B44: enemy.chainbound-revenant | C44: art | D44: revenant | E44: string
A45: /enemies/enemy.chainbound-revenant/minFloor | B45: enemy.chainbound-revenant | C45: minFloor | D45: 4 | E45: number | G45: 1 | H45: 10
A46: /enemies/enemy.chainbound-revenant/maxFloor | B46: enemy.chainbound-revenant | C46: maxFloor | D46: 7 | E46: number | G46: 1 | H46: 10
A47: /enemies/enemy.chainbound-revenant/hpMultiplier | B47: enemy.chainbound-revenant | C47: hpMultiplier | D47: 1 | E47: number | G47: 0.0001 | H47: 100
A48: /enemies/enemy.chainbound-revenant/damageMultiplier | B48: enemy.chainbound-revenant | C48: damageMultiplier | D48: 1 | E48: number | G48: 0.0001 | H48: 100
A49: /enemies/enemy.chainbound-revenant/frequencyOverride | B49: enemy.chainbound-revenant | C49: frequencyOverride | D49: 0 | E49: number | G49: 0 | H49: 10
A50: /enemies/enemy.chainbound-revenant/strikesOverride | B50: enemy.chainbound-revenant | C50: strikesOverride | D50: 0 | E50: number | G50: 0 | H50: 10
A51: /enemies/enemy.chainbound-revenant/reelSet | B51: enemy.chainbound-revenant | C51: reelSet | D51: reel.enemy.skull | E51: string
A52: /enemies/enemy.ash-horned-fiend/id | B52: enemy.ash-horned-fiend | C52: id | D52: enemy.ash-horned-fiend | E52: string | I52: READ ONLY
A53: /enemies/enemy.ash-horned-fiend/name | B53: enemy.ash-horned-fiend | C53: name | D53: Ash-horned fiend | E53: string
A54: /enemies/enemy.ash-horned-fiend/art | B54: enemy.ash-horned-fiend | C54: art | D54: demon | E54: string
A55: /enemies/enemy.ash-horned-fiend/minFloor | B55: enemy.ash-horned-fiend | C55: minFloor | D55: 4 | E55: number | G55: 1 | H55: 10
A56: /enemies/enemy.ash-horned-fiend/maxFloor | B56: enemy.ash-horned-fiend | C56: maxFloor | D56: 7 | E56: number | G56: 1 | H56: 10
A57: /enemies/enemy.ash-horned-fiend/hpMultiplier | B57: enemy.ash-horned-fiend | C57: hpMultiplier | D57: 1 | E57: number | G57: 0.0001 | H57: 100
A58: /enemies/enemy.ash-horned-fiend/damageMultiplier | B58: enemy.ash-horned-fiend | C58: damageMultiplier | D58: 1 | E58: number | G58: 0.0001 | H58: 100
A59: /enemies/enemy.ash-horned-fiend/frequencyOverride | B59: enemy.ash-horned-fiend | C59: frequencyOverride | D59: 0 | E59: number | G59: 0 | H59: 10
A60: /enemies/enemy.ash-horned-fiend/strikesOverride | B60: enemy.ash-horned-fiend | C60: strikesOverride | D60: 0 | E60: number | G60: 0 | H60: 10
A61: /enemies/enemy.ash-horned-fiend/reelSet | B61: enemy.ash-horned-fiend | C61: reelSet | D61: reel.enemy.enemy-ash-horned-fiend | E61: string
A62: /enemies/enemy.hollow-cantor/id | B62: enemy.hollow-cantor | C62: id | D62: enemy.hollow-cantor | E62: string | I62: READ ONLY
A63: /enemies/enemy.hollow-cantor/name | B63: enemy.hollow-cantor | C63: name | D63: The hollow cantor | E63: string
A64: /enemies/enemy.hollow-cantor/art | B64: enemy.hollow-cantor | C64: art | D64: lich | E64: string
A65: /enemies/enemy.hollow-cantor/minFloor | B65: enemy.hollow-cantor | C65: minFloor | D65: 4 | E65: number | G65: 1 | H65: 10
A66: /enemies/enemy.hollow-cantor/maxFloor | B66: enemy.hollow-cantor | C66: maxFloor | D66: 7 | E66: number | G66: 1 | H66: 10
A67: /enemies/enemy.hollow-cantor/hpMultiplier | B67: enemy.hollow-cantor | C67: hpMultiplier | D67: 1 | E67: number | G67: 0.0001 | H67: 100
A68: /enemies/enemy.hollow-cantor/damageMultiplier | B68: enemy.hollow-cantor | C68: damageMultiplier | D68: 1 | E68: number | G68: 0.0001 | H68: 100
A69: /enemies/enemy.hollow-cantor/frequencyOverride | B69: enemy.hollow-cantor | C69: frequencyOverride | D69: 0 | E69: number | G69: 0 | H69: 10
A70: /enemies/enemy.hollow-cantor/strikesOverride | B70: enemy.hollow-cantor | C70: strikesOverride | D70: 0 | E70: number | G70: 0 | H70: 10
A71: /enemies/enemy.hollow-cantor/reelSet | B71: enemy.hollow-cantor | C71: reelSet | D71: reel.enemy.enemy-hollow-cantor | E71: string
A72: /enemies/enemy.marrow-lich/id | B72: enemy.marrow-lich | C72: id | D72: enemy.marrow-lich | E72: string | I72: READ ONLY
A73: /enemies/enemy.marrow-lich/name | B73: enemy.marrow-lich | C73: name | D73: The marrow lich | E73: string
A74: /enemies/enemy.marrow-lich/art | B74: enemy.marrow-lich | C74: art | D74: lich | E74: string
A75: /enemies/enemy.marrow-lich/minFloor | B75: enemy.marrow-lich | C75: minFloor | D75: 8 | E75: number | G75: 1 | H75: 10
A76: /enemies/enemy.marrow-lich/maxFloor | B76: enemy.marrow-lich | C76: maxFloor | D76: 10 | E76: number | G76: 1 | H76: 10
A77: /enemies/enemy.marrow-lich/hpMultiplier | B77: enemy.marrow-lich | C77: hpMultiplier | D77: 1 | E77: number | G77: 0.0001 | H77: 100
A78: /enemies/enemy.marrow-lich/damageMultiplier | B78: enemy.marrow-lich | C78: damageMultiplier | D78: 1 | E78: number | G78: 0.0001 | H78: 100
A79: /enemies/enemy.marrow-lich/frequencyOverride | B79: enemy.marrow-lich | C79: frequencyOverride | D79: 0 | E79: number | G79: 0 | H79: 10
A80: /enemies/enemy.marrow-lich/strikesOverride | B80: enemy.marrow-lich | C80: strikesOverride | D80: 0 | E80: number | G80: 0 | H80: 10
A81: /enemies/enemy.marrow-lich/reelSet | B81: enemy.marrow-lich | C81: reelSet | D81: reel.enemy.enemy-hollow-cantor | E81: string
A82: /enemies/enemy.furnace-devil/id | B82: enemy.furnace-devil | C82: id | D82: enemy.furnace-devil | E82: string | I82: READ ONLY
A83: /enemies/enemy.furnace-devil/name | B83: enemy.furnace-devil | C83: name | D83: The furnace devil | E83: string
A84: /enemies/enemy.furnace-devil/art | B84: enemy.furnace-devil | C84: art | D84: demon | E84: string
A85: /enemies/enemy.furnace-devil/minFloor | B85: enemy.furnace-devil | C85: minFloor | D85: 8 | E85: number | G85: 1 | H85: 10
A86: /enemies/enemy.furnace-devil/maxFloor | B86: enemy.furnace-devil | C86: maxFloor | D86: 10 | E86: number | G86: 1 | H86: 10
A87: /enemies/enemy.furnace-devil/hpMultiplier | B87: enemy.furnace-devil | C87: hpMultiplier | D87: 1 | E87: number | G87: 0.0001 | H87: 100
A88: /enemies/enemy.furnace-devil/damageMultiplier | B88: enemy.furnace-devil | C88: damageMultiplier | D88: 1 | E88: number | G88: 0.0001 | H88: 100
A89: /enemies/enemy.furnace-devil/frequencyOverride | B89: enemy.furnace-devil | C89: frequencyOverride | D89: 0 | E89: number | G89: 0 | H89: 10
A90: /enemies/enemy.furnace-devil/strikesOverride | B90: enemy.furnace-devil | C90: strikesOverride | D90: 0 | E90: number | G90: 0 | H90: 10
A91: /enemies/enemy.furnace-devil/reelSet | B91: enemy.furnace-devil | C91: reelSet | D91: reel.enemy.enemy-ash-horned-fiend | E91: string
A92: /enemies/enemy.stitched-horror/id | B92: enemy.stitched-horror | C92: id | D92: enemy.stitched-horror | E92: string | I92: READ ONLY
A93: /enemies/enemy.stitched-horror/name | B93: enemy.stitched-horror | C93: name | D93: The stitched horror | E93: string
A94: /enemies/enemy.stitched-horror/art | B94: enemy.stitched-horror | C94: art | D94: abomination | E94: string
A95: /enemies/enemy.stitched-horror/minFloor | B95: enemy.stitched-horror | C95: minFloor | D95: 8 | E95: number | G95: 1 | H95: 10
A96: /enemies/enemy.stitched-horror/maxFloor | B96: enemy.stitched-horror | C96: maxFloor | D96: 10 | E96: number | G96: 1 | H96: 10
A97: /enemies/enemy.stitched-horror/hpMultiplier | B97: enemy.stitched-horror | C97: hpMultiplier | D97: 1 | E97: number | G97: 0.0001 | H97: 100
A98: /enemies/enemy.stitched-horror/damageMultiplier | B98: enemy.stitched-horror | C98: damageMultiplier | D98: 1 | E98: number | G98: 0.0001 | H98: 100
A99: /enemies/enemy.stitched-horror/frequencyOverride | B99: enemy.stitched-horror | C99: frequencyOverride | D99: 0 | E99: number | G99: 0 | H99: 10
A100: /enemies/enemy.stitched-horror/strikesOverride | B100: enemy.stitched-horror | C100: strikesOverride | D100: 0 | E100: number | G100: 0 | H100: 10
...

Sheet World
A1: Stable field ID | B1: Entity ID | C1: Field / label | D1: Value (edit blue cells) | E1: Type | F1: Unit | G1: Minimum | H1: Maximum | I1: Notes
A2: /tuning/generateFloor.start.1/value | B2: rule.tuning.generateFloor.start.1 | C2: generateFloor · start 1 | D2: 7 | E2: number | F2: count or coefficient | G2: 7 | H2: 7 | I2: Coefficient in: Pity || 0, ) { const start = pos(1, 7), map = Array.from({ length: W *
A3: /tuning/generateFloor.start.1/category | B3: rule.tuning.generateFloor.start.1 | C3: generateFloor · start 1 | D3: World | E3: string | F3: count or coefficient | I3: READ ONLY
A4: /tuning/generateFloor.start.1/label | B4: rule.tuning.generateFloor.start.1 | C4: generateFloor · start 1 | D4: generateFloor · start 1 | E4: string | F4: count or coefficient | I4: READ ONLY
A5: /tuning/generateFloor.start.1/description | B5: rule.tuning.generateFloor.start.1 | C5: generateFloor · start 1 | D5: Coefficient in: Pity || 0, ) { const start = pos(1, 7), map = Array.from({ length: W * | E5: string | F5: count or coefficient | I5: READ ONLY
A6: /tuning/generateFloor.start.1/unit | B6: rule.tuning.generateFloor.start.1 | C6: generateFloor · start 1 | D6: count or coefficient | E6: string | F6: count or coefficient | I6: READ ONLY
A7: /tuning/generateFloor.start.1/min | B7: rule.tuning.generateFloor.start.1 | C7: generateFloor · start 1 | D7: 0 | E7: number | F7: count or coefficient | G7: 0 | H7: 0 | I7: READ ONLY
A8: /tuning/generateFloor.start.1/max | B8: rule.tuning.generateFloor.start.1 | C8: generateFloor · start 1 | D8: 100 | E8: number | F8: count or coefficient | G8: 100 | H8: 100 | I8: READ ONLY
A9: /tuning/generateFloor.start.1/integer | B9: rule.tuning.generateFloor.start.1 | C9: generateFloor · start 1 | D9: TRUE | E9: boolean | F9: count or coefficient | I9: READ ONLY
A10: /tuning/generateFloor.coefficient.1/value | B10: rule.tuning.generateFloor.coefficient.1 | C10: generateFloor · coefficient 1 | D10: 0.11 | E10: number | F10: probability or multiplier | G10: 0 | H10: 1 | I10: Coefficient in: os(x, y) !== start && Math.random() < 0.11) Object.assign(map[pos(x, y)]
A11: /tuning/generateFloor.coefficient.1/category | B11: rule.tuning.generateFloor.coefficient.1 | C11: generateFloor · coefficient 1 | D11: World | E11: string | F11: probability or multiplier | I11: READ ONLY
A12: /tuning/generateFloor.coefficient.1/label | B12: rule.tuning.generateFloor.coefficient.1 | C12: generateFloor · coefficient 1 | D12: generateFloor · coefficient 1 | E12: string | F12: probability or multiplier | I12: READ ONLY
A13: /tuning/generateFloor.coefficient.1/description | B13: rule.tuning.generateFloor.coefficient.1 | C13: generateFloor · coefficient 1 | D13: Coefficient in: os(x, y) !== start && Math.random() < 0.11) Object.assign(map[pos(x, y)] | E13: string | F13: probability or multiplier | I13: READ ONLY
A14: /tuning/generateFloor.coefficient.1/unit | B14: rule.tuning.generateFloor.coefficient.1 | C14: generateFloor · coefficient 1 | D14: probability or multiplier | E14: string | F14: probability or multiplier | I14: READ ONLY
A15: /tuning/generateFloor.coefficient.1/min | B15: rule.tuning.generateFloor.coefficient.1 | C15: generateFloor · coefficient 1 | D15: 0 | E15: number | F15: probability or multiplier | G15: 0 | H15: 1 | I15: READ ONLY
A16: /tuning/generateFloor.coefficient.1/max | B16: rule.tuning.generateFloor.coefficient.1 | C16: generateFloor · coefficient 1 | D16: 1 | E16: number | F16: probability or multiplier | G16: 0 | H16: 1 | I16: READ ONLY
A17: /tuning/generateFloor.coefficient.1/integer | B17: rule.tuning.generateFloor.coefficient.1 | C17: generateFloor · coefficient 1 | D17: FALSE | E17: boolean | F17: probability or multiplier | I17: READ ONLY
A18: /tuning/generateFloor.riverCount.1/value | B18: rule.tuning.generateFloor.riverCount.1 | C18: generateFloor · riverCount 1 | D18: 0.012 | E18: number | F18: probability or multiplier | G18: 0 | H18: 1 | I18: Coefficient in: andom(), riverCount = riverRoll < 0.012 ? 2 : riverRoll < 0.35 ? 1 : 0; for
A19: /tuning/generateFloor.riverCount.1/category | B19: rule.tuning.generateFloor.riverCount.1 | C19: generateFloor · riverCount 1 | D19: World | E19: string | F19: probability or multiplier | I19: READ ONLY
A20: /tuning/generateFloor.riverCount.1/label | B20: rule.tuning.generateFloor.riverCount.1 | C20: generateFloor · riverCount 1 | D20: generateFloor · riverCount 1 | E20: string | F20: probability or multiplier | I20: READ ONLY
A21: /tuning/generateFloor.riverCount.1/description | B21: rule.tuning.generateFloor.riverCount.1 | C21: generateFloor · riverCount 1 | D21: Coefficient in: andom(), riverCount = riverRoll < 0.012 ? 2 : riverRoll < 0.35 ? 1 : 0; for | E21: string | F21: probability or multiplier | I21: READ ONLY
A22: /tuning/generateFloor.riverCount.1/unit | B22: rule.tuning.generateFloor.riverCount.1 | C22: generateFloor · riverCount 1 | D22: probability or multiplier | E22: string | F22: probability or multiplier | I22: READ ONLY
A23: /tuning/generateFloor.riverCount.1/min | B23: rule.tuning.generateFloor.riverCount.1 | C23: generateFloor · riverCount 1 | D23: 0 | E23: number | F23: probability or multiplier | G23: 0 | H23: 1 | I23: READ ONLY
A24: /tuning/generateFloor.riverCount.1/max | B24: rule.tuning.generateFloor.riverCount.1 | C24: generateFloor · riverCount 1 | D24: 1 | E24: number | F24: probability or multiplier | G24: 0 | H24: 1 | I24: READ ONLY
A25: /tuning/generateFloor.riverCount.1/integer | B25: rule.tuning.generateFloor.riverCount.1 | C25: generateFloor · riverCount 1 | D25: FALSE | E25: boolean | F25: probability or multiplier | I25: READ ONLY
A26: /tuning/generateFloor.riverCount.2/value | B26: rule.tuning.generateFloor.riverCount.2 | C26: generateFloor · riverCount 2 | D26: 2 | E26: number | F26: count or coefficient | G26: 1 | H26: 2 | I26: Coefficient in: riverCount = riverRoll < 0.012 ? 2 : riverRoll < 0.35 ? 1 : 0; for (le
A27: /tuning/generateFloor.riverCount.2/category | B27: rule.tuning.generateFloor.riverCount.2 | C27: generateFloor · riverCount 2 | D27: World | E27: string | F27: count or coefficient | I27: READ ONLY
A28: /tuning/generateFloor.riverCount.2/label | B28: rule.tuning.generateFloor.riverCount.2 | C28: generateFloor · riverCount 2 | D28: generateFloor · riverCount 2 | E28: string | F28: count or coefficient | I28: READ ONLY
A29: /tuning/generateFloor.riverCount.2/description | B29: rule.tuning.generateFloor.riverCount.2 | C29: generateFloor · riverCount 2 | D29: Coefficient in: riverCount = riverRoll < 0.012 ? 2 : riverRoll < 0.35 ? 1 : 0; for (le | E29: string | F29: count or coefficient | I29: READ ONLY
A30: /tuning/generateFloor.riverCount.2/unit | B30: rule.tuning.generateFloor.riverCount.2 | C30: generateFloor · riverCount 2 | D30: count or coefficient | E30: string | F30: count or coefficient | I30: READ ONLY
A31: /tuning/generateFloor.riverCount.2/min | B31: rule.tuning.generateFloor.riverCount.2 | C31: generateFloor · riverCount 2 | D31: 0 | E31: number | F31: count or coefficient | G31: 1 | H31: 2 | I31: READ ONLY
A32: /tuning/generateFloor.riverCount.2/max | B32: rule.tuning.generateFloor.riverCount.2 | C32: generateFloor · riverCount 2 | D32: 100 | E32: number | F32: count or coefficient | G32: 1 | H32: 2 | I32: READ ONLY
A33: /tuning/generateFloor.riverCount.2/integer | B33: rule.tuning.generateFloor.riverCount.2 | C33: generateFloor · riverCount 2 | D33: TRUE | E33: boolean | F33: count or coefficient | I33: READ ONLY
A34: /tuning/generateFloor.riverCount.3/value | B34: rule.tuning.generateFloor.riverCount.3 | C34: generateFloor · riverCount 3 | D34: 0.35 | E34: number | F34: probability or multiplier | G34: 0 | H34: 1 | I34: Coefficient in: = riverRoll < 0.012 ? 2 : riverRoll < 0.35 ? 1 : 0; for (let stream = 0; strea
A35: /tuning/generateFloor.riverCount.3/category | B35: rule.tuning.generateFloor.riverCount.3 | C35: generateFloor · riverCount 3 | D35: World | E35: string | F35: probability or multiplier | I35: READ ONLY
A36: /tuning/generateFloor.riverCount.3/label | B36: rule.tuning.generateFloor.riverCount.3 | C36: generateFloor · riverCount 3 | D36: generateFloor · riverCount 3 | E36: string | F36: probability or multiplier | I36: READ ONLY
A37: /tuning/generateFloor.riverCount.3/description | B37: rule.tuning.generateFloor.riverCount.3 | C37: generateFloor · riverCount 3 | D37: Coefficient in: = riverRoll < 0.012 ? 2 : riverRoll < 0.35 ? 1 : 0; for (let stream = 0; strea | E37: string | F37: probability or multiplier | I37: READ ONLY
A38: /tuning/generateFloor.riverCount.3/unit | B38: rule.tuning.generateFloor.riverCount.3 | C38: generateFloor · riverCount 3 | D38: probability or multiplier | E38: string | F38: probability or multiplier | I38: READ ONLY
A39: /tuning/generateFloor.riverCount.3/min | B39: rule.tuning.generateFloor.riverCount.3 | C39: generateFloor · riverCount 3 | D39: 0 | E39: number | F39: probability or multiplier | G39: 0 | H39: 1 | I39: READ ONLY
A40: /tuning/generateFloor.riverCount.3/max | B40: rule.tuning.generateFloor.riverCount.3 | C40: generateFloor · riverCount 3 | D40: 1 | E40: number | F40: probability or multiplier | G40: 0 | H40: 1 | I40: READ ONLY
A41: /tuning/generateFloor.riverCount.3/integer | B41: rule.tuning.generateFloor.riverCount.3 | C41: generateFloor · riverCount 3 | D41: FALSE | E41: boolean | F41: probability or multiplier | I41: READ ONLY
A42: /tuning/generateFloor.horizontal.1/value | B42: rule.tuning.generateFloor.horizontal.1 | C42: generateFloor · horizontal 1 | D42: 0.45 | E42: number | F42: probability or multiplier | G42: 0 | H42: 1 | I42: Coefficient in: = riverCount === 1 && Math.random() < 0.45, low = riverCount === 2 ? (stre
A43: /tuning/generateFloor.horizontal.1/category | B43: rule.tuning.generateFloor.horizontal.1 | C43: generateFloor · horizontal 1 | D43: World | E43: string | F43: probability or multiplier | I43: READ ONLY
A44: /tuning/generateFloor.horizontal.1/label | B44: rule.tuning.generateFloor.horizontal.1 | C44: generateFloor · horizontal 1 | D44: generateFloor · horizontal 1 | E44: string | F44: probability or multiplier | I44: READ ONLY
A45: /tuning/generateFloor.horizontal.1/description | B45: rule.tuning.generateFloor.horizontal.1 | C45: generateFloor · horizontal 1 | D45: Coefficient in: = riverCount === 1 && Math.random() < 0.45, low = riverCount === 2 ? (stre | E45: string | F45: probability or multiplier | I45: READ ONLY
A46: /tuning/generateFloor.horizontal.1/unit | B46: rule.tuning.generateFloor.horizontal.1 | C46: generateFloor · horizontal 1 | D46: probability or multiplier | E46: string | F46: probability or multiplier | I46: READ ONLY
A47: /tuning/generateFloor.horizontal.1/min | B47: rule.tuning.generateFloor.horizontal.1 | C47: generateFloor · horizontal 1 | D47: 0 | E47: number | F47: probability or multiplier | G47: 0 | H47: 1 | I47: READ ONLY
A48: /tuning/generateFloor.horizontal.1/max | B48: rule.tuning.generateFloor.horizontal.1 | C48: generateFloor · horizontal 1 | D48: 1 | E48: number | F48: probability or multiplier | G48: 0 | H48: 1 | I48: READ ONLY
A49: /tuning/generateFloor.horizontal.1/integer | B49: rule.tuning.generateFloor.horizontal.1 | C49: generateFloor · horizontal 1 | D49: FALSE | E49: boolean | F49: probability or multiplier | I49: READ ONLY
A50: /tuning/generateFloor.low.1/value | B50: rule.tuning.generateFloor.low.1 | C50: generateFloor · low 1 | D50: 2 | E50: number | F50: count or coefficient | G50: 2 | H50: 2 | I50: Coefficient in: () < 0.45, low = riverCount === 2 ? (stream === 0 ? 2 : 6) : 2, h
A51: /tuning/generateFloor.low.1/category | B51: rule.tuning.generateFloor.low.1 | C51: generateFloor · low 1 | D51: World | E51: string | F51: count or coefficient | I51: READ ONLY
A52: /tuning/generateFloor.low.1/label | B52: rule.tuning.generateFloor.low.1 | C52: generateFloor · low 1 | D52: generateFloor · low 1 | E52: string | F52: count or coefficient | I52: READ ONLY
A53: /tuning/generateFloor.low.1/description | B53: rule.tuning.generateFloor.low.1 | C53: generateFloor · low 1 | D53: Coefficient in: () < 0.45, low = riverCount === 2 ? (stream === 0 ? 2 : 6) : 2, h | E53: string | F53: count or coefficient | I53: READ ONLY
A54: /tuning/generateFloor.low.1/unit | B54: rule.tuning.generateFloor.low.1 | C54: generateFloor · low 1 | D54: count or coefficient | E54: string | F54: count or coefficient | I54: READ ONLY
A55: /tuning/generateFloor.low.1/min | B55: rule.tuning.generateFloor.low.1 | C55: generateFloor · low 1 | D55: 0 | E55: number | F55: count or coefficient | G55: 0 | H55: 0 | I55: READ ONLY
A56: /tuning/generateFloor.low.1/max | B56: rule.tuning.generateFloor.low.1 | C56: generateFloor · low 1 | D56: 100 | E56: number | F56: count or coefficient | G56: 100 | H56: 100 | I56: READ ONLY
A57: /tuning/generateFloor.low.1/integer | B57: rule.tuning.generateFloor.low.1 | C57: generateFloor · low 1 | D57: TRUE | E57: boolean | F57: count or coefficient | I57: READ ONLY
A58: /tuning/generateFloor.low.2/value | B58: rule.tuning.generateFloor.low.2 | C58: generateFloor · low 2 | D58: 2 | E58: number | F58: count or coefficient | G58: 2 | H58: 2 | I58: Coefficient in: = riverCount === 2 ? (stream === 0 ? 2 : 6) : 2, high = riverCount ===
A59: /tuning/generateFloor.low.2/category | B59: rule.tuning.generateFloor.low.2 | C59: generateFloor · low 2 | D59: World | E59: string | F59: count or coefficient | I59: READ ONLY
A60: /tuning/generateFloor.low.2/label | B60: rule.tuning.generateFloor.low.2 | C60: generateFloor · low 2 | D60: generateFloor · low 2 | E60: string | F60: count or coefficient | I60: READ ONLY
A61: /tuning/generateFloor.low.2/description | B61: rule.tuning.generateFloor.low.2 | C61: generateFloor · low 2 | D61: Coefficient in: = riverCount === 2 ? (stream === 0 ? 2 : 6) : 2, high = riverCount === | E61: string | F61: count or coefficient | I61: READ ONLY
A62: /tuning/generateFloor.low.2/unit | B62: rule.tuning.generateFloor.low.2 | C62: generateFloor · low 2 | D62: count or coefficient | E62: string | F62: count or coefficient | I62: READ ONLY
A63: /tuning/generateFloor.low.2/min | B63: rule.tuning.generateFloor.low.2 | C63: generateFloor · low 2 | D63: 0 | E63: number | F63: count or coefficient | G63: 0 | H63: 0 | I63: READ ONLY
A64: /tuning/generateFloor.low.2/max | B64: rule.tuning.generateFloor.low.2 | C64: generateFloor · low 2 | D64: 100 | E64: number | F64: count or coefficient | G64: 100 | H64: 100 | I64: READ ONLY
A65: /tuning/generateFloor.low.2/integer | B65: rule.tuning.generateFloor.low.2 | C65: generateFloor · low 2 | D65: TRUE | E65: boolean | F65: count or coefficient | I65: READ ONLY
A66: /tuning/generateFloor.low.3/value | B66: rule.tuning.generateFloor.low.3 | C66: generateFloor · low 3 | D66: 6 | E66: number | F66: count or coefficient | G66: 6 | H66: 6 | I66: Coefficient in: iverCount === 2 ? (stream === 0 ? 2 : 6) : 2, high = riverCount === 2 ?
A67: /tuning/generateFloor.low.3/category | B67: rule.tuning.generateFloor.low.3 | C67: generateFloor · low 3 | D67: World | E67: string | F67: count or coefficient | I67: READ ONLY
A68: /tuning/generateFloor.low.3/label | B68: rule.tuning.generateFloor.low.3 | C68: generateFloor · low 3 | D68: generateFloor · low 3 | E68: string | F68: count or coefficient | I68: READ ONLY
A69: /tuning/generateFloor.low.3/description | B69: rule.tuning.generateFloor.low.3 | C69: generateFloor · low 3 | D69: Coefficient in: iverCount === 2 ? (stream === 0 ? 2 : 6) : 2, high = riverCount === 2 ? | E69: string | F69: count or coefficient | I69: READ ONLY
A70: /tuning/generateFloor.low.3/unit | B70: rule.tuning.generateFloor.low.3 | C70: generateFloor · low 3 | D70: count or coefficient | E70: string | F70: count or coefficient | I70: READ ONLY
A71: /tuning/generateFloor.low.3/min | B71: rule.tuning.generateFloor.low.3 | C71: generateFloor · low 3 | D71: 0 | E71: number | F71: count or coefficient | G71: 0 | H71: 0 | I71: READ ONLY
A72: /tuning/generateFloor.low.3/max | B72: rule.tuning.generateFloor.low.3 | C72: generateFloor · low 3 | D72: 100 | E72: number | F72: count or coefficient | G72: 100 | H72: 100 | I72: READ ONLY
A73: /tuning/generateFloor.low.3/integer | B73: rule.tuning.generateFloor.low.3 | C73: generateFloor · low 3 | D73: TRUE | E73: boolean | F73: count or coefficient | I73: READ ONLY
A74: /tuning/generateFloor.low.4/value | B74: rule.tuning.generateFloor.low.4 | C74: generateFloor · low 4 | D74: 2 | E74: number | F74: count or coefficient | G74: 2 | H74: 2 | I74: Coefficient in: ount === 2 ? (stream === 0 ? 2 : 6) : 2, high = riverCount === 2 ? low
A75: /tuning/generateFloor.low.4/category | B75: rule.tuning.generateFloor.low.4 | C75: generateFloor · low 4 | D75: World | E75: string | F75: count or coefficient | I75: READ ONLY
A76: /tuning/generateFloor.low.4/label | B76: rule.tuning.generateFloor.low.4 | C76: generateFloor · low 4 | D76: generateFloor · low 4 | E76: string | F76: count or coefficient | I76: READ ONLY
A77: /tuning/generateFloor.low.4/description | B77: rule.tuning.generateFloor.low.4 | C77: generateFloor · low 4 | D77: Coefficient in: ount === 2 ? (stream === 0 ? 2 : 6) : 2, high = riverCount === 2 ? low | E77: string | F77: count or coefficient | I77: READ ONLY
A78: /tuning/generateFloor.low.4/unit | B78: rule.tuning.generateFloor.low.4 | C78: generateFloor · low 4 | D78: count or coefficient | E78: string | F78: count or coefficient | I78: READ ONLY
A79: /tuning/generateFloor.low.4/min | B79: rule.tuning.generateFloor.low.4 | C79: generateFloor · low 4 | D79: 0 | E79: number | F79: count or coefficient | G79: 0 | H79: 0 | I79: READ ONLY
A80: /tuning/generateFloor.low.4/max | B80: rule.tuning.generateFloor.low.4 | C80: generateFloor · low 4 | D80: 100 | E80: number | F80: count or coefficient | G80: 100 | H80: 100 | I80: READ ONLY
A81: /tuning/generateFloor.low.4/integer | B81: rule.tuning.generateFloor.low.4 | C81: generateFloor · low 4 | D81: TRUE | E81: boolean | F81: count or coefficient | I81: READ ONLY
A82: /tuning/generateFloor.high.1/value | B82: rule.tuning.generateFloor.high.1 | C82: generateFloor · high 1 | D82: 2 | E82: number | F82: count or coefficient | G82: 2 | H82: 2 | I82: Coefficient in: : 6) : 2, high = riverCount === 2 ? low + 1 : horizontal ? 5 : 8,
A83: /tuning/generateFloor.high.1/category | B83: rule.tuning.generateFloor.high.1 | C83: generateFloor · high 1 | D83: World | E83: string | F83: count or coefficient | I83: READ ONLY
A84: /tuning/generateFloor.high.1/label | B84: rule.tuning.generateFloor.high.1 | C84: generateFloor · high 1 | D84: generateFloor · high 1 | E84: string | F84: count or coefficient | I84: READ ONLY
A85: /tuning/generateFloor.high.1/description | B85: rule.tuning.generateFloor.high.1 | C85: generateFloor · high 1 | D85: Coefficient in: : 6) : 2, high = riverCount === 2 ? low + 1 : horizontal ? 5 : 8, | E85: string | F85: count or coefficient | I85: READ ONLY
A86: /tuning/generateFloor.high.1/unit | B86: rule.tuning.generateFloor.high.1 | C86: generateFloor · high 1 | D86: count or coefficient | E86: string | F86: count or coefficient | I86: READ ONLY
A87: /tuning/generateFloor.high.1/min | B87: rule.tuning.generateFloor.high.1 | C87: generateFloor · high 1 | D87: 0 | E87: number | F87: count or coefficient | G87: 0 | H87: 0 | I87: READ ONLY
A88: /tuning/generateFloor.high.1/max | B88: rule.tuning.generateFloor.high.1 | C88: generateFloor · high 1 | D88: 100 | E88: number | F88: count or coefficient | G88: 100 | H88: 100 | I88: READ ONLY
A89: /tuning/generateFloor.high.1/integer | B89: rule.tuning.generateFloor.high.1 | C89: generateFloor · high 1 | D89: TRUE | E89: boolean | F89: count or coefficient | I89: READ ONLY
A90: /tuning/generateFloor.high.2/value | B90: rule.tuning.generateFloor.high.2 | C90: generateFloor · high 2 | D90: 5 | E90: number | F90: count or coefficient | G90: 5 | H90: 5 | I90: Coefficient in: rCount === 2 ? low + 1 : horizontal ? 5 : 8, river = []; let offset
A91: /tuning/generateFloor.high.2/category | B91: rule.tuning.generateFloor.high.2 | C91: generateFloor · high 2 | D91: World | E91: string | F91: count or coefficient | I91: READ ONLY
A92: /tuning/generateFloor.high.2/label | B92: rule.tuning.generateFloor.high.2 | C92: generateFloor · high 2 | D92: generateFloor · high 2 | E92: string | F92: count or coefficient | I92: READ ONLY
A93: /tuning/generateFloor.high.2/description | B93: rule.tuning.generateFloor.high.2 | C93: generateFloor · high 2 | D93: Coefficient in: rCount === 2 ? low + 1 : horizontal ? 5 : 8, river = []; let offset | E93: string | F93: count or coefficient | I93: READ ONLY
A94: /tuning/generateFloor.high.2/unit | B94: rule.tuning.generateFloor.high.2 | C94: generateFloor · high 2 | D94: count or coefficient | E94: string | F94: count or coefficient | I94: READ ONLY
A95: /tuning/generateFloor.high.2/min | B95: rule.tuning.generateFloor.high.2 | C95: generateFloor · high 2 | D95: 0 | E95: number | F95: count or coefficient | G95: 0 | H95: 0 | I95: READ ONLY
A96: /tuning/generateFloor.high.2/max | B96: rule.tuning.generateFloor.high.2 | C96: generateFloor · high 2 | D96: 100 | E96: number | F96: count or coefficient | G96: 100 | H96: 100 | I96: READ ONLY
A97: /tuning/generateFloor.high.2/integer | B97: rule.tuning.generateFloor.high.2 | C97: generateFloor · high 2 | D97: TRUE | E97: boolean | F97: count or coefficient | I97: READ ONLY
A98: /tuning/generateFloor.high.3/value | B98: rule.tuning.generateFloor.high.3 | C98: generateFloor · high 3 | D98: 8 | E98: number | F98: count or coefficient | G98: 8 | H98: 8 | I98: Coefficient in: nt === 2 ? low + 1 : horizontal ? 5 : 8, river = []; let offset = l
A99: /tuning/generateFloor.high.3/category | B99: rule.tuning.generateFloor.high.3 | C99: generateFloor · high 3 | D99: World | E99: string | F99: count or coefficient | I99: READ ONLY
A100: /tuning/generateFloor.high.3/label | B100: rule.tuning.generateFloor.high.3 | C100: generateFloor · high 3 | D100: generateFloor · high 3 | E100: string | F100: count or coefficient | I100: READ ONLY
...

Sheet Loot
A1: Stable field ID | B1: Entity ID | C1: Field / label | D1: Value (edit blue cells) | E1: Type | F1: Unit | G1: Minimum | H1: Maximum | I1: Notes
A2: /tuning/treasureRoll.baseGold.1/value | B2: rule.tuning.treasureRoll.baseGold.1 | C2: treasureRoll · baseGold 1 | D2: 2 | E2: number | F2: count or coefficient | G2: 1 | H2: 100 | I2: Coefficient in: faces, faces, faces]), baseGold = 2 + state.depth, counts = {}, f
A3: /tuning/treasureRoll.baseGold.1/category | B3: rule.tuning.treasureRoll.baseGold.1 | C3: treasureRoll · baseGold 1 | D3: Loot | E3: string | F3: count or coefficient | I3: READ ONLY
A4: /tuning/treasureRoll.baseGold.1/label | B4: rule.tuning.treasureRoll.baseGold.1 | C4: treasureRoll · baseGold 1 | D4: treasureRoll · baseGold 1 | E4: string | F4: count or coefficient | I4: READ ONLY
A5: /tuning/treasureRoll.baseGold.1/description | B5: rule.tuning.treasureRoll.baseGold.1 | C5: treasureRoll · baseGold 1 | D5: Coefficient in: faces, faces, faces]), baseGold = 2 + state.depth, counts = {}, f | E5: string | F5: count or coefficient | I5: READ ONLY
A6: /tuning/treasureRoll.baseGold.1/unit | B6: rule.tuning.treasureRoll.baseGold.1 | C6: treasureRoll · baseGold 1 | D6: count or coefficient | E6: string | F6: count or coefficient | I6: READ ONLY
A7: /tuning/treasureRoll.baseGold.1/min | B7: rule.tuning.treasureRoll.baseGold.1 | C7: treasureRoll · baseGold 1 | D7: 0 | E7: number | F7: count or coefficient | G7: 1 | H7: 100 | I7: READ ONLY
A8: /tuning/treasureRoll.baseGold.1/max | B8: rule.tuning.treasureRoll.baseGold.1 | C8: treasureRoll · baseGold 1 | D8: 100 | E8: number | F8: count or coefficient | G8: 1 | H8: 100 | I8: READ ONLY
A9: /tuning/treasureRoll.baseGold.1/integer | B9: rule.tuning.treasureRoll.baseGold.1 | C9: treasureRoll · baseGold 1 | D9: TRUE | E9: boolean | F9: count or coefficient | I9: READ ONLY
A10: /tuning/treasureRoll.coefficient.1/value | B10: rule.tuning.treasureRoll.coefficient.1 | C10: treasureRoll · coefficient 1 | D10: 2 | E10: number | F10: count or coefficient | G10: 1 | H10: 100 | I10: Coefficient in: baseGold += s.tier * (battle ? 2 + state.depth : 4 + state.depth);
A11: /tuning/treasureRoll.coefficient.1/category | B11: rule.tuning.treasureRoll.coefficient.1 | C11: treasureRoll · coefficient 1 | D11: Loot | E11: string | F11: count or coefficient | I11: READ ONLY
A12: /tuning/treasureRoll.coefficient.1/label | B12: rule.tuning.treasureRoll.coefficient.1 | C12: treasureRoll · coefficient 1 | D12: treasureRoll · coefficient 1 | E12: string | F12: count or coefficient | I12: READ ONLY
A13: /tuning/treasureRoll.coefficient.1/description | B13: rule.tuning.treasureRoll.coefficient.1 | C13: treasureRoll · coefficient 1 | D13: Coefficient in: baseGold += s.tier * (battle ? 2 + state.depth : 4 + state.depth); | E13: string | F13: count or coefficient | I13: READ ONLY
A14: /tuning/treasureRoll.coefficient.1/unit | B14: rule.tuning.treasureRoll.coefficient.1 | C14: treasureRoll · coefficient 1 | D14: count or coefficient | E14: string | F14: count or coefficient | I14: READ ONLY
A15: /tuning/treasureRoll.coefficient.1/min | B15: rule.tuning.treasureRoll.coefficient.1 | C15: treasureRoll · coefficient 1 | D15: 0 | E15: number | F15: count or coefficient | G15: 1 | H15: 100 | I15: READ ONLY
A16: /tuning/treasureRoll.coefficient.1/max | B16: rule.tuning.treasureRoll.coefficient.1 | C16: treasureRoll · coefficient 1 | D16: 100 | E16: number | F16: count or coefficient | G16: 1 | H16: 100 | I16: READ ONLY
A17: /tuning/treasureRoll.coefficient.1/integer | B17: rule.tuning.treasureRoll.coefficient.1 | C17: treasureRoll · coefficient 1 | D17: TRUE | E17: boolean | F17: count or coefficient | I17: READ ONLY
A18: /tuning/treasureRoll.coefficient.2/value | B18: rule.tuning.treasureRoll.coefficient.2 | C18: treasureRoll · coefficient 2 | D18: 4 | E18: number | F18: count or coefficient | G18: 1 | H18: 100 | I18: Coefficient in: s.tier * (battle ? 2 + state.depth : 4 + state.depth); if (s.type === "a
A19: /tuning/treasureRoll.coefficient.2/category | B19: rule.tuning.treasureRoll.coefficient.2 | C19: treasureRoll · coefficient 2 | D19: Loot | E19: string | F19: count or coefficient | I19: READ ONLY
A20: /tuning/treasureRoll.coefficient.2/label | B20: rule.tuning.treasureRoll.coefficient.2 | C20: treasureRoll · coefficient 2 | D20: treasureRoll · coefficient 2 | E20: string | F20: count or coefficient | I20: READ ONLY
A21: /tuning/treasureRoll.coefficient.2/description | B21: rule.tuning.treasureRoll.coefficient.2 | C21: treasureRoll · coefficient 2 | D21: Coefficient in: s.tier * (battle ? 2 + state.depth : 4 + state.depth); if (s.type === "a | E21: string | F21: count or coefficient | I21: READ ONLY
A22: /tuning/treasureRoll.coefficient.2/unit | B22: rule.tuning.treasureRoll.coefficient.2 | C22: treasureRoll · coefficient 2 | D22: count or coefficient | E22: string | F22: count or coefficient | I22: READ ONLY
A23: /tuning/treasureRoll.coefficient.2/min | B23: rule.tuning.treasureRoll.coefficient.2 | C23: treasureRoll · coefficient 2 | D23: 0 | E23: number | F23: count or coefficient | G23: 1 | H23: 100 | I23: READ ONLY
A24: /tuning/treasureRoll.coefficient.2/max | B24: rule.tuning.treasureRoll.coefficient.2 | C24: treasureRoll · coefficient 2 | D24: 100 | E24: number | F24: count or coefficient | G24: 1 | H24: 100 | I24: READ ONLY
A25: /tuning/treasureRoll.coefficient.2/integer | B25: rule.tuning.treasureRoll.coefficient.2 | C25: treasureRoll · coefficient 2 | D25: TRUE | E25: boolean | F25: count or coefficient | I25: READ ONLY
A26: /tuning/treasureRoll.coefficient.3/value | B26: rule.tuning.treasureRoll.coefficient.3 | C26: treasureRoll · coefficient 3 | D26: 2 | E26: number | F26: count or coefficient | G26: 1 | H26: 100 | I26: Coefficient in: if (source === "boss") baseGold *= 2; if (elite) { baseGold *= 3;
A27: /tuning/treasureRoll.coefficient.3/category | B27: rule.tuning.treasureRoll.coefficient.3 | C27: treasureRoll · coefficient 3 | D27: Loot | E27: string | F27: count or coefficient | I27: READ ONLY
A28: /tuning/treasureRoll.coefficient.3/label | B28: rule.tuning.treasureRoll.coefficient.3 | C28: treasureRoll · coefficient 3 | D28: treasureRoll · coefficient 3 | E28: string | F28: count or coefficient | I28: READ ONLY
A29: /tuning/treasureRoll.coefficient.3/description | B29: rule.tuning.treasureRoll.coefficient.3 | C29: treasureRoll · coefficient 3 | D29: Coefficient in: if (source === "boss") baseGold *= 2; if (elite) { baseGold *= 3; | E29: string | F29: count or coefficient | I29: READ ONLY
A30: /tuning/treasureRoll.coefficient.3/unit | B30: rule.tuning.treasureRoll.coefficient.3 | C30: treasureRoll · coefficient 3 | D30: count or coefficient | E30: string | F30: count or coefficient | I30: READ ONLY
A31: /tuning/treasureRoll.coefficient.3/min | B31: rule.tuning.treasureRoll.coefficient.3 | C31: treasureRoll · coefficient 3 | D31: 0 | E31: number | F31: count or coefficient | G31: 1 | H31: 100 | I31: READ ONLY
A32: /tuning/treasureRoll.coefficient.3/max | B32: rule.tuning.treasureRoll.coefficient.3 | C32: treasureRoll · coefficient 3 | D32: 100 | E32: number | F32: count or coefficient | G32: 1 | H32: 100 | I32: READ ONLY
A33: /tuning/treasureRoll.coefficient.3/integer | B33: rule.tuning.treasureRoll.coefficient.3 | C33: treasureRoll · coefficient 3 | D33: TRUE | E33: boolean | F33: count or coefficient | I33: READ ONLY
A34: /tuning/treasureRoll.coefficient.4/value | B34: rule.tuning.treasureRoll.coefficient.4 | C34: treasureRoll · coefficient 4 | D34: 3 | E34: number | F34: count or coefficient | G34: 1 | H34: 100 | I34: Coefficient in: *= 2; if (elite) { baseGold *= 3; const prized = makeArtefact(stat
A35: /tuning/treasureRoll.coefficient.4/category | B35: rule.tuning.treasureRoll.coefficient.4 | C35: treasureRoll · coefficient 4 | D35: Loot | E35: string | F35: count or coefficient | I35: READ ONLY
A36: /tuning/treasureRoll.coefficient.4/label | B36: rule.tuning.treasureRoll.coefficient.4 | C36: treasureRoll · coefficient 4 | D36: treasureRoll · coefficient 4 | E36: string | F36: count or coefficient | I36: READ ONLY
A37: /tuning/treasureRoll.coefficient.4/description | B37: rule.tuning.treasureRoll.coefficient.4 | C37: treasureRoll · coefficient 4 | D37: Coefficient in: *= 2; if (elite) { baseGold *= 3; const prized = makeArtefact(stat | E37: string | F37: count or coefficient | I37: READ ONLY
A38: /tuning/treasureRoll.coefficient.4/unit | B38: rule.tuning.treasureRoll.coefficient.4 | C38: treasureRoll · coefficient 4 | D38: count or coefficient | E38: string | F38: count or coefficient | I38: READ ONLY
A39: /tuning/treasureRoll.coefficient.4/min | B39: rule.tuning.treasureRoll.coefficient.4 | C39: treasureRoll · coefficient 4 | D39: 0 | E39: number | F39: count or coefficient | G39: 1 | H39: 100 | I39: READ ONLY
A40: /tuning/treasureRoll.coefficient.4/max | B40: rule.tuning.treasureRoll.coefficient.4 | C40: treasureRoll · coefficient 4 | D40: 100 | E40: number | F40: count or coefficient | G40: 1 | H40: 100 | I40: READ ONLY
A41: /tuning/treasureRoll.coefficient.4/integer | B41: rule.tuning.treasureRoll.coefficient.4 | C41: treasureRoll · coefficient 4 | D41: TRUE | E41: boolean | F41: count or coefficient | I41: READ ONLY
A42: /tuning/treasureRoll.prized.1/value | B42: rule.tuning.treasureRoll.prized.1 | C42: treasureRoll · prized 1 | D42: 2 | E42: number | F42: count or coefficient | G42: 1 | H42: 100 | I42: Coefficient in: t prized = makeArtefact(state.depth + 2); prized.depth = state.depth;
A43: /tuning/treasureRoll.prized.1/category | B43: rule.tuning.treasureRoll.prized.1 | C43: treasureRoll · prized 1 | D43: Loot | E43: string | F43: count or coefficient | I43: READ ONLY
A44: /tuning/treasureRoll.prized.1/label | B44: rule.tuning.treasureRoll.prized.1 | C44: treasureRoll · prized 1 | D44: treasureRoll · prized 1 | E44: string | F44: count or coefficient | I44: READ ONLY
A45: /tuning/treasureRoll.prized.1/description | B45: rule.tuning.treasureRoll.prized.1 | C45: treasureRoll · prized 1 | D45: Coefficient in: t prized = makeArtefact(state.depth + 2); prized.depth = state.depth; | E45: string | F45: count or coefficient | I45: READ ONLY
A46: /tuning/treasureRoll.prized.1/unit | B46: rule.tuning.treasureRoll.prized.1 | C46: treasureRoll · prized 1 | D46: count or coefficient | E46: string | F46: count or coefficient | I46: READ ONLY
A47: /tuning/treasureRoll.prized.1/min | B47: rule.tuning.treasureRoll.prized.1 | C47: treasureRoll · prized 1 | D47: 0 | E47: number | F47: count or coefficient | G47: 1 | H47: 100 | I47: READ ONLY
A48: /tuning/treasureRoll.prized.1/max | B48: rule.tuning.treasureRoll.prized.1 | C48: treasureRoll · prized 1 | D48: 100 | E48: number | F48: count or coefficient | G48: 1 | H48: 100 | I48: READ ONLY
A49: /tuning/treasureRoll.prized.1/integer | B49: rule.tuning.treasureRoll.prized.1 | C49: treasureRoll · prized 1 | D49: TRUE | E49: boolean | F49: count or coefficient | I49: READ ONLY
A50: /loot/coins/0/type | B50: rule.loot.coins.0 | C50: 0 · type | D50: coin | E50: string
A51: /loot/coins/0/tier | B51: rule.loot.coins.0 | C51: 0 · tier | D51: 1 | E51: number | F51: tier | G51: 1 | H51: 4
A52: /loot/coins/0/weight | B52: rule.loot.coins.0 | C52: 0 · weight | D52: 536 | E52: number | F52: relative weight | G52: 0.0001 | H52: 100000
A53: /loot/coins/1/type | B53: rule.loot.coins.1 | C53: 1 · type | D53: coin | E53: string
A54: /loot/coins/1/tier | B54: rule.loot.coins.1 | C54: 1 · tier | D54: 2 | E54: number | F54: tier | G54: 1 | H54: 4
A55: /loot/coins/1/weight | B55: rule.loot.coins.1 | C55: 1 · weight | D55: 280 | E55: number | F55: relative weight | G55: 0.0001 | H55: 100000
A56: /loot/coins/2/type | B56: rule.loot.coins.2 | C56: 2 · type | D56: coin | E56: string
A57: /loot/coins/2/tier | B57: rule.loot.coins.2 | C57: 2 · tier | D57: 3 | E57: number | F57: tier | G57: 1 | H57: 4
A58: /loot/coins/2/weight | B58: rule.loot.coins.2 | C58: 2 · weight | D58: 110 | E58: number | F58: relative weight | G58: 0.0001 | H58: 100000
A59: /loot/pointWeight | B59: rule.loot | C59: pointWeight | D59: 35 | E59: number | G59: 0.0001 | H59: 100000
A60: /loot/itemWeight | B60: rule.loot | C60: itemWeight | D60: 21 | E60: number | G60: 0.0001 | H60: 100000
A61: /loot/artefactWeight | B61: rule.loot | C61: artefactWeight | D61: 18 | E61: number | G61: 0.0001 | H61: 100000

Sheet Economy
A1: Stable field ID | B1: Entity ID | C1: Field / label | D1: Value (edit blue cells) | E1: Type | F1: Unit | G1: Minimum | H1: Maximum | I1: Notes
A2: /tuning/shopPrices.coefficient.1/value | B2: rule.tuning.shopPrices.coefficient.1 | C2: shopPrices · coefficient 1 | D2: 14 | E2: number | F2: count or coefficient | G2: 1 | H2: 100 | I2: Coefficient in: .keys(ITEM_DEFS).map((type) => [type, 14 + state.depth * 2]), ), potio
A3: /tuning/shopPrices.coefficient.1/category | B3: rule.tuning.shopPrices.coefficient.1 | C3: shopPrices · coefficient 1 | D3: Economy | E3: string | F3: count or coefficient | I3: READ ONLY
A4: /tuning/shopPrices.coefficient.1/label | B4: rule.tuning.shopPrices.coefficient.1 | C4: shopPrices · coefficient 1 | D4: shopPrices · coefficient 1 | E4: string | F4: count or coefficient | I4: READ ONLY
A5: /tuning/shopPrices.coefficient.1/description | B5: rule.tuning.shopPrices.coefficient.1 | C5: shopPrices · coefficient 1 | D5: Coefficient in: .keys(ITEM_DEFS).map((type) => [type, 14 + state.depth * 2]), ), potio | E5: string | F5: count or coefficient | I5: READ ONLY
A6: /tuning/shopPrices.coefficient.1/unit | B6: rule.tuning.shopPrices.coefficient.1 | C6: shopPrices · coefficient 1 | D6: count or coefficient | E6: string | F6: count or coefficient | I6: READ ONLY
A7: /tuning/shopPrices.coefficient.1/min | B7: rule.tuning.shopPrices.coefficient.1 | C7: shopPrices · coefficient 1 | D7: 0 | E7: number | F7: count or coefficient | G7: 1 | H7: 100 | I7: READ ONLY
A8: /tuning/shopPrices.coefficient.1/max | B8: rule.tuning.shopPrices.coefficient.1 | C8: shopPrices · coefficient 1 | D8: 140 | E8: number | F8: count or coefficient | G8: 1 | H8: 100 | I8: READ ONLY
A9: /tuning/shopPrices.coefficient.1/integer | B9: rule.tuning.shopPrices.coefficient.1 | C9: shopPrices · coefficient 1 | D9: TRUE | E9: boolean | F9: count or coefficient | I9: READ ONLY
A10: /tuning/shopPrices.coefficient.2/value | B10: rule.tuning.shopPrices.coefficient.2 | C10: shopPrices · coefficient 2 | D10: 2 | E10: number | F10: count or coefficient | G10: 1 | H10: 100 | I10: Coefficient in: p((type) => [type, 14 + state.depth * 2]), ), potion: 14 + state.dept
A11: /tuning/shopPrices.coefficient.2/category | B11: rule.tuning.shopPrices.coefficient.2 | C11: shopPrices · coefficient 2 | D11: Economy | E11: string | F11: count or coefficient | I11: READ ONLY
A12: /tuning/shopPrices.coefficient.2/label | B12: rule.tuning.shopPrices.coefficient.2 | C12: shopPrices · coefficient 2 | D12: shopPrices · coefficient 2 | E12: string | F12: count or coefficient | I12: READ ONLY
A13: /tuning/shopPrices.coefficient.2/description | B13: rule.tuning.shopPrices.coefficient.2 | C13: shopPrices · coefficient 2 | D13: Coefficient in: p((type) => [type, 14 + state.depth * 2]), ), potion: 14 + state.dept | E13: string | F13: count or coefficient | I13: READ ONLY
A14: /tuning/shopPrices.coefficient.2/unit | B14: rule.tuning.shopPrices.coefficient.2 | C14: shopPrices · coefficient 2 | D14: count or coefficient | E14: string | F14: count or coefficient | I14: READ ONLY
A15: /tuning/shopPrices.coefficient.2/min | B15: rule.tuning.shopPrices.coefficient.2 | C15: shopPrices · coefficient 2 | D15: 0 | E15: number | F15: count or coefficient | G15: 1 | H15: 100 | I15: READ ONLY
A16: /tuning/shopPrices.coefficient.2/max | B16: rule.tuning.shopPrices.coefficient.2 | C16: shopPrices · coefficient 2 | D16: 100 | E16: number | F16: count or coefficient | G16: 1 | H16: 100 | I16: READ ONLY
A17: /tuning/shopPrices.coefficient.2/integer | B17: rule.tuning.shopPrices.coefficient.2 | C17: shopPrices · coefficient 2 | D17: TRUE | E17: boolean | F17: count or coefficient | I17: READ ONLY
A18: /tuning/shopPrices.potion.1/value | B18: rule.tuning.shopPrices.potion.1 | C18: shopPrices · potion 1 | D18: 14 | E18: number | F18: count or coefficient | G18: 1 | H18: 100 | I18: Coefficient in: state.depth * 2]), ), potion: 14 + state.depth * 2, bomb: 18 + sta
A19: /tuning/shopPrices.potion.1/category | B19: rule.tuning.shopPrices.potion.1 | C19: shopPrices · potion 1 | D19: Economy | E19: string | F19: count or coefficient | I19: READ ONLY
A20: /tuning/shopPrices.potion.1/label | B20: rule.tuning.shopPrices.potion.1 | C20: shopPrices · potion 1 | D20: shopPrices · potion 1 | E20: string | F20: count or coefficient | I20: READ ONLY
A21: /tuning/shopPrices.potion.1/description | B21: rule.tuning.shopPrices.potion.1 | C21: shopPrices · potion 1 | D21: Coefficient in: state.depth * 2]), ), potion: 14 + state.depth * 2, bomb: 18 + sta | E21: string | F21: count or coefficient | I21: READ ONLY
A22: /tuning/shopPrices.potion.1/unit | B22: rule.tuning.shopPrices.potion.1 | C22: shopPrices · potion 1 | D22: count or coefficient | E22: string | F22: count or coefficient | I22: READ ONLY
A23: /tuning/shopPrices.potion.1/min | B23: rule.tuning.shopPrices.potion.1 | C23: shopPrices · potion 1 | D23: 0 | E23: number | F23: count or coefficient | G23: 1 | H23: 100 | I23: READ ONLY
A24: /tuning/shopPrices.potion.1/max | B24: rule.tuning.shopPrices.potion.1 | C24: shopPrices · potion 1 | D24: 140 | E24: number | F24: count or coefficient | G24: 1 | H24: 100 | I24: READ ONLY
A25: /tuning/shopPrices.potion.1/integer | B25: rule.tuning.shopPrices.potion.1 | C25: shopPrices · potion 1 | D25: TRUE | E25: boolean | F25: count or coefficient | I25: READ ONLY
A26: /tuning/shopPrices.potion.2/value | B26: rule.tuning.shopPrices.potion.2 | C26: shopPrices · potion 2 | D26: 2 | E26: number | F26: count or coefficient | G26: 1 | H26: 100 | I26: Coefficient in: ), potion: 14 + state.depth * 2, bomb: 18 + state.depth * 2,
A27: /tuning/shopPrices.potion.2/category | B27: rule.tuning.shopPrices.potion.2 | C27: shopPrices · potion 2 | D27: Economy | E27: string | F27: count or coefficient | I27: READ ONLY
A28: /tuning/shopPrices.potion.2/label | B28: rule.tuning.shopPrices.potion.2 | C28: shopPrices · potion 2 | D28: shopPrices · potion 2 | E28: string | F28: count or coefficient | I28: READ ONLY
A29: /tuning/shopPrices.potion.2/description | B29: rule.tuning.shopPrices.potion.2 | C29: shopPrices · potion 2 | D29: Coefficient in: ), potion: 14 + state.depth * 2, bomb: 18 + state.depth * 2, | E29: string | F29: count or coefficient | I29: READ ONLY
A30: /tuning/shopPrices.potion.2/unit | B30: rule.tuning.shopPrices.potion.2 | C30: shopPrices · potion 2 | D30: count or coefficient | E30: string | F30: count or coefficient | I30: READ ONLY
A31: /tuning/shopPrices.potion.2/min | B31: rule.tuning.shopPrices.potion.2 | C31: shopPrices · potion 2 | D31: 0 | E31: number | F31: count or coefficient | G31: 1 | H31: 100 | I31: READ ONLY
A32: /tuning/shopPrices.potion.2/max | B32: rule.tuning.shopPrices.potion.2 | C32: shopPrices · potion 2 | D32: 100 | E32: number | F32: count or coefficient | G32: 1 | H32: 100 | I32: READ ONLY
A33: /tuning/shopPrices.potion.2/integer | B33: rule.tuning.shopPrices.potion.2 | C33: shopPrices · potion 2 | D33: TRUE | E33: boolean | F33: count or coefficient | I33: READ ONLY
A34: /tuning/shopPrices.bomb.1/value | B34: rule.tuning.shopPrices.bomb.1 | C34: shopPrices · bomb 1 | D34: 18 | E34: number | F34: count or coefficient | G34: 1 | H34: 100 | I34: Coefficient in: tion: 14 + state.depth * 2, bomb: 18 + state.depth * 2, ward: 12 + sta
A35: /tuning/shopPrices.bomb.1/category | B35: rule.tuning.shopPrices.bomb.1 | C35: shopPrices · bomb 1 | D35: Economy | E35: string | F35: count or coefficient | I35: READ ONLY
A36: /tuning/shopPrices.bomb.1/label | B36: rule.tuning.shopPrices.bomb.1 | C36: shopPrices · bomb 1 | D36: shopPrices · bomb 1 | E36: string | F36: count or coefficient | I36: READ ONLY
A37: /tuning/shopPrices.bomb.1/description | B37: rule.tuning.shopPrices.bomb.1 | C37: shopPrices · bomb 1 | D37: Coefficient in: tion: 14 + state.depth * 2, bomb: 18 + state.depth * 2, ward: 12 + sta | E37: string | F37: count or coefficient | I37: READ ONLY
A38: /tuning/shopPrices.bomb.1/unit | B38: rule.tuning.shopPrices.bomb.1 | C38: shopPrices · bomb 1 | D38: count or coefficient | E38: string | F38: count or coefficient | I38: READ ONLY
A39: /tuning/shopPrices.bomb.1/min | B39: rule.tuning.shopPrices.bomb.1 | C39: shopPrices · bomb 1 | D39: 0 | E39: number | F39: count or coefficient | G39: 1 | H39: 100 | I39: READ ONLY
A40: /tuning/shopPrices.bomb.1/max | B40: rule.tuning.shopPrices.bomb.1 | C40: shopPrices · bomb 1 | D40: 180 | E40: number | F40: count or coefficient | G40: 1 | H40: 100 | I40: READ ONLY
A41: /tuning/shopPrices.bomb.1/integer | B41: rule.tuning.shopPrices.bomb.1 | C41: shopPrices · bomb 1 | D41: TRUE | E41: boolean | F41: count or coefficient | I41: READ ONLY
A42: /tuning/shopPrices.bomb.2/value | B42: rule.tuning.shopPrices.bomb.2 | C42: shopPrices · bomb 2 | D42: 2 | E42: number | F42: count or coefficient | G42: 1 | H42: 100 | I42: Coefficient in: pth * 2, bomb: 18 + state.depth * 2, ward: 12 + state.depth * 2,
A43: /tuning/shopPrices.bomb.2/category | B43: rule.tuning.shopPrices.bomb.2 | C43: shopPrices · bomb 2 | D43: Economy | E43: string | F43: count or coefficient | I43: READ ONLY
A44: /tuning/shopPrices.bomb.2/label | B44: rule.tuning.shopPrices.bomb.2 | C44: shopPrices · bomb 2 | D44: shopPrices · bomb 2 | E44: string | F44: count or coefficient | I44: READ ONLY
A45: /tuning/shopPrices.bomb.2/description | B45: rule.tuning.shopPrices.bomb.2 | C45: shopPrices · bomb 2 | D45: Coefficient in: pth * 2, bomb: 18 + state.depth * 2, ward: 12 + state.depth * 2, | E45: string | F45: count or coefficient | I45: READ ONLY
A46: /tuning/shopPrices.bomb.2/unit | B46: rule.tuning.shopPrices.bomb.2 | C46: shopPrices · bomb 2 | D46: count or coefficient | E46: string | F46: count or coefficient | I46: READ ONLY
A47: /tuning/shopPrices.bomb.2/min | B47: rule.tuning.shopPrices.bomb.2 | C47: shopPrices · bomb 2 | D47: 0 | E47: number | F47: count or coefficient | G47: 1 | H47: 100 | I47: READ ONLY
A48: /tuning/shopPrices.bomb.2/max | B48: rule.tuning.shopPrices.bomb.2 | C48: shopPrices · bomb 2 | D48: 100 | E48: number | F48: count or coefficient | G48: 1 | H48: 100 | I48: READ ONLY
A49: /tuning/shopPrices.bomb.2/integer | B49: rule.tuning.shopPrices.bomb.2 | C49: shopPrices · bomb 2 | D49: TRUE | E49: boolean | F49: count or coefficient | I49: READ ONLY
A50: /tuning/shopPrices.ward.1/value | B50: rule.tuning.shopPrices.ward.1 | C50: shopPrices · ward 1 | D50: 12 | E50: number | F50: count or coefficient | G50: 1 | H50: 100 | I50: Coefficient in: bomb: 18 + state.depth * 2, ward: 12 + state.depth * 2, heal: 22 + sta
A51: /tuning/shopPrices.ward.1/category | B51: rule.tuning.shopPrices.ward.1 | C51: shopPrices · ward 1 | D51: Economy | E51: string | F51: count or coefficient | I51: READ ONLY
A52: /tuning/shopPrices.ward.1/label | B52: rule.tuning.shopPrices.ward.1 | C52: shopPrices · ward 1 | D52: shopPrices · ward 1 | E52: string | F52: count or coefficient | I52: READ ONLY
A53: /tuning/shopPrices.ward.1/description | B53: rule.tuning.shopPrices.ward.1 | C53: shopPrices · ward 1 | D53: Coefficient in: bomb: 18 + state.depth * 2, ward: 12 + state.depth * 2, heal: 22 + sta | E53: string | F53: count or coefficient | I53: READ ONLY
A54: /tuning/shopPrices.ward.1/unit | B54: rule.tuning.shopPrices.ward.1 | C54: shopPrices · ward 1 | D54: count or coefficient | E54: string | F54: count or coefficient | I54: READ ONLY
A55: /tuning/shopPrices.ward.1/min | B55: rule.tuning.shopPrices.ward.1 | C55: shopPrices · ward 1 | D55: 0 | E55: number | F55: count or coefficient | G55: 1 | H55: 100 | I55: READ ONLY
A56: /tuning/shopPrices.ward.1/max | B56: rule.tuning.shopPrices.ward.1 | C56: shopPrices · ward 1 | D56: 120 | E56: number | F56: count or coefficient | G56: 1 | H56: 100 | I56: READ ONLY
A57: /tuning/shopPrices.ward.1/integer | B57: rule.tuning.shopPrices.ward.1 | C57: shopPrices · ward 1 | D57: TRUE | E57: boolean | F57: count or coefficient | I57: READ ONLY
A58: /tuning/shopPrices.ward.2/value | B58: rule.tuning.shopPrices.ward.2 | C58: shopPrices · ward 2 | D58: 2 | E58: number | F58: count or coefficient | G58: 1 | H58: 100 | I58: Coefficient in: pth * 2, ward: 12 + state.depth * 2, heal: 22 + state.depth * 5,
A59: /tuning/shopPrices.ward.2/category | B59: rule.tuning.shopPrices.ward.2 | C59: shopPrices · ward 2 | D59: Economy | E59: string | F59: count or coefficient | I59: READ ONLY
A60: /tuning/shopPrices.ward.2/label | B60: rule.tuning.shopPrices.ward.2 | C60: shopPrices · ward 2 | D60: shopPrices · ward 2 | E60: string | F60: count or coefficient | I60: READ ONLY
A61: /tuning/shopPrices.ward.2/description | B61: rule.tuning.shopPrices.ward.2 | C61: shopPrices · ward 2 | D61: Coefficient in: pth * 2, ward: 12 + state.depth * 2, heal: 22 + state.depth * 5, | E61: string | F61: count or coefficient | I61: READ ONLY
A62: /tuning/shopPrices.ward.2/unit | B62: rule.tuning.shopPrices.ward.2 | C62: shopPrices · ward 2 | D62: count or coefficient | E62: string | F62: count or coefficient | I62: READ ONLY
A63: /tuning/shopPrices.ward.2/min | B63: rule.tuning.shopPrices.ward.2 | C63: shopPrices · ward 2 | D63: 0 | E63: number | F63: count or coefficient | G63: 1 | H63: 100 | I63: READ ONLY
A64: /tuning/shopPrices.ward.2/max | B64: rule.tuning.shopPrices.ward.2 | C64: shopPrices · ward 2 | D64: 100 | E64: number | F64: count or coefficient | G64: 1 | H64: 100 | I64: READ ONLY
A65: /tuning/shopPrices.ward.2/integer | B65: rule.tuning.shopPrices.ward.2 | C65: shopPrices · ward 2 | D65: TRUE | E65: boolean | F65: count or coefficient | I65: READ ONLY
A66: /tuning/shopPrices.heal.1/value | B66: rule.tuning.shopPrices.heal.1 | C66: shopPrices · heal 1 | D66: 22 | E66: number | F66: count or coefficient | G66: 1 | H66: 100 | I66: Coefficient in: ward: 12 + state.depth * 2, heal: 22 + state.depth * 5, reveal: 18 + s
A67: /tuning/shopPrices.heal.1/category | B67: rule.tuning.shopPrices.heal.1 | C67: shopPrices · heal 1 | D67: Economy | E67: string | F67: count or coefficient | I67: READ ONLY
A68: /tuning/shopPrices.heal.1/label | B68: rule.tuning.shopPrices.heal.1 | C68: shopPrices · heal 1 | D68: shopPrices · heal 1 | E68: string | F68: count or coefficient | I68: READ ONLY
A69: /tuning/shopPrices.heal.1/description | B69: rule.tuning.shopPrices.heal.1 | C69: shopPrices · heal 1 | D69: Coefficient in: ward: 12 + state.depth * 2, heal: 22 + state.depth * 5, reveal: 18 + s | E69: string | F69: count or coefficient | I69: READ ONLY
A70: /tuning/shopPrices.heal.1/unit | B70: rule.tuning.shopPrices.heal.1 | C70: shopPrices · heal 1 | D70: count or coefficient | E70: string | F70: count or coefficient | I70: READ ONLY
A71: /tuning/shopPrices.heal.1/min | B71: rule.tuning.shopPrices.heal.1 | C71: shopPrices · heal 1 | D71: 0 | E71: number | F71: count or coefficient | G71: 1 | H71: 100 | I71: READ ONLY
A72: /tuning/shopPrices.heal.1/max | B72: rule.tuning.shopPrices.heal.1 | C72: shopPrices · heal 1 | D72: 220 | E72: number | F72: count or coefficient | G72: 1 | H72: 100 | I72: READ ONLY
A73: /tuning/shopPrices.heal.1/integer | B73: rule.tuning.shopPrices.heal.1 | C73: shopPrices · heal 1 | D73: TRUE | E73: boolean | F73: count or coefficient | I73: READ ONLY
A74: /tuning/shopPrices.heal.2/value | B74: rule.tuning.shopPrices.heal.2 | C74: shopPrices · heal 2 | D74: 5 | E74: number | F74: count or coefficient | G74: 1 | H74: 100 | I74: Coefficient in: pth * 2, heal: 22 + state.depth * 5, reveal: 18 + state.depth * 3,
A75: /tuning/shopPrices.heal.2/category | B75: rule.tuning.shopPrices.heal.2 | C75: shopPrices · heal 2 | D75: Economy | E75: string | F75: count or coefficient | I75: READ ONLY
A76: /tuning/shopPrices.heal.2/label | B76: rule.tuning.shopPrices.heal.2 | C76: shopPrices · heal 2 | D76: shopPrices · heal 2 | E76: string | F76: count or coefficient | I76: READ ONLY
A77: /tuning/shopPrices.heal.2/description | B77: rule.tuning.shopPrices.heal.2 | C77: shopPrices · heal 2 | D77: Coefficient in: pth * 2, heal: 22 + state.depth * 5, reveal: 18 + state.depth * 3, | E77: string | F77: count or coefficient | I77: READ ONLY
A78: /tuning/shopPrices.heal.2/unit | B78: rule.tuning.shopPrices.heal.2 | C78: shopPrices · heal 2 | D78: count or coefficient | E78: string | F78: count or coefficient | I78: READ ONLY
A79: /tuning/shopPrices.heal.2/min | B79: rule.tuning.shopPrices.heal.2 | C79: shopPrices · heal 2 | D79: 0 | E79: number | F79: count or coefficient | G79: 1 | H79: 100 | I79: READ ONLY
A80: /tuning/shopPrices.heal.2/max | B80: rule.tuning.shopPrices.heal.2 | C80: shopPrices · heal 2 | D80: 100 | E80: number | F80: count or coefficient | G80: 1 | H80: 100 | I80: READ ONLY
A81: /tuning/shopPrices.heal.2/integer | B81: rule.tuning.shopPrices.heal.2 | C81: shopPrices · heal 2 | D81: TRUE | E81: boolean | F81: count or coefficient | I81: READ ONLY
A82: /tuning/shopPrices.reveal.1/value | B82: rule.tuning.shopPrices.reveal.1 | C82: shopPrices · reveal 1 | D82: 18 | E82: number | F82: count or coefficient | G82: 1 | H82: 100 | I82: Coefficient in: al: 22 + state.depth * 5, reveal: 18 + state.depth * 3, }; }
A83: /tuning/shopPrices.reveal.1/category | B83: rule.tuning.shopPrices.reveal.1 | C83: shopPrices · reveal 1 | D83: Economy | E83: string | F83: count or coefficient | I83: READ ONLY
A84: /tuning/shopPrices.reveal.1/label | B84: rule.tuning.shopPrices.reveal.1 | C84: shopPrices · reveal 1 | D84: shopPrices · reveal 1 | E84: string | F84: count or coefficient | I84: READ ONLY
A85: /tuning/shopPrices.reveal.1/description | B85: rule.tuning.shopPrices.reveal.1 | C85: shopPrices · reveal 1 | D85: Coefficient in: al: 22 + state.depth * 5, reveal: 18 + state.depth * 3, }; } | E85: string | F85: count or coefficient | I85: READ ONLY
A86: /tuning/shopPrices.reveal.1/unit | B86: rule.tuning.shopPrices.reveal.1 | C86: shopPrices · reveal 1 | D86: count or coefficient | E86: string | F86: count or coefficient | I86: READ ONLY
A87: /tuning/shopPrices.reveal.1/min | B87: rule.tuning.shopPrices.reveal.1 | C87: shopPrices · reveal 1 | D87: 0 | E87: number | F87: count or coefficient | G87: 1 | H87: 100 | I87: READ ONLY
A88: /tuning/shopPrices.reveal.1/max | B88: rule.tuning.shopPrices.reveal.1 | C88: shopPrices · reveal 1 | D88: 180 | E88: number | F88: count or coefficient | G88: 1 | H88: 100 | I88: READ ONLY
A89: /tuning/shopPrices.reveal.1/integer | B89: rule.tuning.shopPrices.reveal.1 | C89: shopPrices · reveal 1 | D89: TRUE | E89: boolean | F89: count or coefficient | I89: READ ONLY
A90: /tuning/shopPrices.reveal.2/value | B90: rule.tuning.shopPrices.reveal.2 | C90: shopPrices · reveal 2 | D90: 3 | E90: number | F90: count or coefficient | G90: 1 | H90: 100 | I90: Coefficient in: h * 5, reveal: 18 + state.depth * 3, }; }
A91: /tuning/shopPrices.reveal.2/category | B91: rule.tuning.shopPrices.reveal.2 | C91: shopPrices · reveal 2 | D91: Economy | E91: string | F91: count or coefficient | I91: READ ONLY
A92: /tuning/shopPrices.reveal.2/label | B92: rule.tuning.shopPrices.reveal.2 | C92: shopPrices · reveal 2 | D92: shopPrices · reveal 2 | E92: string | F92: count or coefficient | I92: READ ONLY
A93: /tuning/shopPrices.reveal.2/description | B93: rule.tuning.shopPrices.reveal.2 | C93: shopPrices · reveal 2 | D93: Coefficient in: h * 5, reveal: 18 + state.depth * 3, }; } | E93: string | F93: count or coefficient | I93: READ ONLY
A94: /tuning/shopPrices.reveal.2/unit | B94: rule.tuning.shopPrices.reveal.2 | C94: shopPrices · reveal 2 | D94: count or coefficient | E94: string | F94: count or coefficient | I94: READ ONLY
A95: /tuning/shopPrices.reveal.2/min | B95: rule.tuning.shopPrices.reveal.2 | C95: shopPrices · reveal 2 | D95: 0 | E95: number | F95: count or coefficient | G95: 1 | H95: 100 | I95: READ ONLY
A96: /tuning/shopPrices.reveal.2/max | B96: rule.tuning.shopPrices.reveal.2 | C96: shopPrices · reveal 2 | D96: 100 | E96: number | F96: count or coefficient | G96: 1 | H96: 100 | I96: READ ONLY
A97: /tuning/shopPrices.reveal.2/integer | B97: rule.tuning.shopPrices.reveal.2 | C97: shopPrices · reveal 2 | D97: TRUE | E97: boolean | F97: count or coefficient | I97: READ ONLY

Sheet Abilities
A1: Stable field ID | B1: Entity ID | C1: Field / label | D1: Value (edit blue cells) | E1: Type | F1: Unit | G1: Minimum | H1: Maximum | I1: Notes
A2: /abilities/fighter/id | B2: ability.rage | C2: id | D2: ability.rage | E2: string | I2: READ ONLY
A3: /abilities/fighter/name | B3: ability.rage | C3: name | D3: RAGE | E3: string
A4: /abilities/fighter/description | B4: ability.rage | C4: description | D4: Rage: add damage for the rest of this fight. Repeated rage builds a little protection. | E4: string
A5: /abilities/fighter/stackCap | B5: ability.rage | C5: stackCap | D5: 4 | E5: number | G5: 0 | H5: 100000
A6: /abilities/fighter/defenceThreshold | B6: ability.rage | C6: defenceThreshold | D6: 3 | E6: number | G6: 1 | H6: 10000
A7: /abilities/healer/id | B7: ability.sanctuary | C7: id | D7: ability.sanctuary | E7: string | I7: READ ONLY
A8: /abilities/healer/name | B8: ability.sanctuary | C8: name | D8: SANCTUARY | E8: string
A9: /abilities/healer/description | B9: ability.sanctuary | C9: description | D9: Sanctuary: heal every living ally and raise shared team block. | E9: string
A10: /abilities/healer/healBase | B10: ability.sanctuary | C10: healBase | D10: 3 | E10: number | G10: 0 | H10: 100000
A11: /abilities/healer/healLevelDivisor | B11: ability.sanctuary | C11: healLevelDivisor | D11: 2 | E11: number | G11: 1 | H11: 10000
A12: /abilities/healer/blockBase | B12: ability.sanctuary | C12: blockBase | D12: 4 | E12: number | G12: 0 | H12: 100000
A13: /abilities/healer/blockLevelDivisor | B13: ability.sanctuary | C13: blockLevelDivisor | D13: 3 | E13: number | G13: 1 | H13: 10000
A14: /abilities/rogue/id | B14: ability.flurry | C14: id | D14: ability.flurry | E14: string | I14: READ ONLY
A15: /abilities/rogue/name | B15: ability.flurry | C15: name | D15: FLURRY | E15: string
A16: /abilities/rogue/description | B16: ability.flurry | C16: description | D16: Flurry: roll three extra attack reels; matching blades can crit. | E16: string
A17: /abilities/mage/id | B17: ability.nova | C17: id | D17: ability.nova | E17: string | I17: READ ONLY
A18: /abilities/mage/name | B18: ability.nova | C18: name | D18: NOVA | E18: string
A19: /abilities/mage/description | B19: ability.nova | C19: description | D19: Nova: strike every enemy with magic. | E19: string
A20: /abilities/mage/damageBase | B20: ability.nova | C20: damageBase | D20: 4 | E20: number | G20: 0 | H20: 100000
A21: /abilities/mage/damageLevelDivisor | B21: ability.nova | C21: damageLevelDivisor | D21: 2 | E21: number | G21: 1 | H21: 10000
A22: /abilities/poison/id | B22: ability.poison | C22: id | D22: ability.poison | E22: string | I22: READ ONLY
A23: /abilities/poison/name | B23: ability.poison | C23: name | D23: POISON | E23: string
A24: /abilities/poison/description | B24: ability.poison | C24: description | D24: A tiny armour-piercing damage tick per action. | E24: string
A25: /abilities/poison/baseTurns | B25: ability.poison | C25: baseTurns | D25: 1 | E25: number | G25: 0 | H25: 100000
A26: /abilities/poison/maxTurns | B26: ability.poison | C26: maxTurns | D26: 8 | E26: number | G26: 0 | H26: 100000
A27: /abilities/poison/damage | B27: ability.poison | C27: damage | D27: 1 | E27: number | G27: 0 | H27: 100000
A28: /abilities/stimulant/id | B28: ability.stimulant | C28: id | D28: ability.stimulant | E28: string | I28: READ ONLY
A29: /abilities/stimulant/name | B29: ability.stimulant | C29: name | D29: STIMULANT | E29: string
A30: /abilities/stimulant/description | B30: ability.stimulant | C30: description | D30: Temporary damage and protection. | E30: string
A31: /abilities/stimulant/attackBase | B31: ability.stimulant | C31: attackBase | D31: 1 | E31: number | G31: 0 | H31: 100000
A32: /abilities/stimulant/attackDivisor | B32: ability.stimulant | C32: attackDivisor | D32: 3 | E32: number | G32: 1 | H32: 10000
A33: /abilities/stimulant/defenceBase | B33: ability.stimulant | C33: defenceBase | D33: 1 | E33: number | G33: 0 | H33: 100000
A34: /abilities/stimulant/defenceDivisor | B34: ability.stimulant | C34: defenceDivisor | D34: 5 | E34: number | G34: 1 | H34: 10000
A35: /abilities/stimulant/maxPower | B35: ability.stimulant | C35: maxPower | D35: 6 | E35: number | G35: 0 | H35: 100000
A36: /abilities/stimulant/baseTurns | B36: ability.stimulant | C36: baseTurns | D36: 3 | E36: number | G36: 0 | H36: 100000
A37: /abilities/stimulant/maxExtraTurns | B37: ability.stimulant | C37: maxExtraTurns | D37: 3 | E37: number | G37: 0 | H37: 100000

Sheet Roll Analysis
A1: Class | B1: Outcome | C1: Probability | D1: Base damage | E1: Base healing | F1: Base block | G1: Three alike? | H1: Critical probability
A2: class.fighter | B2: attack1 / attack1 / attack1 | C2: =('Reels'!D4/('Reels'!D4+'Reels'!D7+'Reels'!D10+'Reels'!D13+'Reels'!D16+'Reels'!D19))*('Reels'!D22/('Reels'!D22+'Reels'!D25+'Reels'!D28+'Reels'!D31+'Reels'!D34+'Reels'!D37+'Reels'!D40))*('Reels'!D44/('Reels'!D44+'Reels'!D47+'Reels'!D50+'Reels'!D53+'Reels'!D56+'Reels'!D59)) -> 0.024545455 | D2: =IF(OR('Reels'!D2="attack",'Reels'!D2="magic"),CHOOSE('Reels'!D3+1,'Slots'!D29,'Slots'!D30,'Slots'!D31,'Slots'!D32,'Slots'!D33),0)+IF(OR('Reels'!D20="attack",'Reels'!D20="magic"),CHOOSE('Reels'!D21+1,'Slots'!D29,'Slots'!D30,'Slots'!D31,'Slots'!D32,'Slots'!D33),0)+IF(OR('Reels'!D42="attack",'Reels'!D42="magic"),CHOOSE('Reels'!D43+1,'Slots'!D29,'Slots'!D30,'Slots'!D31,'Slots'!D32,'Slots'!D33),0) -> 6 | E2: =IF('Reels'!D2="heal",'Reels'!D3*'Slots'!D24,0)+IF('Reels'!D20="heal",'Reels'!D21*'Slots'!D24,0)+IF('Reels'!D42="heal",'Reels'!D43*'Slots'!D24,0) -> 0 | F2: =IF('Reels'!D2="block",'Reels'!D3*'Slots'!D25,0)+IF('Reels'!D20="block",'Reels'!D21*'Slots'!D25,0)+IF('Reels'!D42="block",'Reels'!D43*'Slots'!D25,0) -> 0 | G2: =AND('Reels'!D2<>"blank",'Reels'!D2<>"class",'Reels'!D2='Reels'!D42,'Reels'!D3='Reels'!D43,OR('Reels'!D20="class",AND('Reels'!D20='Reels'!D2,'Reels'!D21='Reels'!D3))) -> TRUE | H2: =IF(G2,C2,0) -> 0.024545455
A3: class.fighter | B3: attack1 / attack1 / attack2 | C3: =('Reels'!D4/('Reels'!D4+'Reels'!D7+'Reels'!D10+'Reels'!D13+'Reels'!D16+'Reels'!D19))*('Reels'!D22/('Reels'!D22+'Reels'!D25+'Reels'!D28+'Reels'!D31+'Reels'!D34+'Reels'!D37+'Reels'!D40))*('Reels'!D47/('Reels'!D44+'Reels'!D47+'Reels'!D50+'Reels'!D53+'Reels'!D56+'Reels'!D59)) -> 0.013636364 | D3: =IF(OR('Reels'!D2="attack",'Reels'!D2="magic"),CHOOSE('Reels'!D3+1,'Slots'!D29,'Slots'!D30,'Slots'!D31,'Slots'!D32,'Slots'!D33),0)+IF(OR('Reels'!D20="attack",'Reels'!D20="magic"),CHOOSE('Reels'!D21+1,'Slots'!D29,'Slots'!D30,'Slots'!D31,'Slots'!D32,'Slots'!D33),0)+IF(OR('Reels'!D45="attack",'Reels'!D45="magic"),CHOOSE('Reels'!D46+1,'Slots'!D29,'Slots'!D30,'Slots'!D31,'Slots'!D32,'Slots'!D33),0) -> 8 | E3: =IF('Reels'!D2="heal",'Reels'!D3*'Slots'!D24,0)+IF('Reels'!D20="heal",'Reels'!D21*'Slots'!D24,0)+IF('Reels'!D45="heal",'Reels'!D46*'Slots'!D24,0) -> 0 | F3: =IF('Reels'!D2="block",'Reels'!D3*'Slots'!D25,0)+IF('Reels'!D20="block",'Reels'!D21*'Slots'!D25,0)+IF('Reels'!D45="block",'Reels'!D46*'Slots'!D25,0) -> 0 | G3: =AND('Reels'!D2<>"blank",'Reels'!D2<>"class",'Reels'!D2='Reels'!D45,'Reels'!D3='Reels'!D46,OR('Reels'!D20="class",AND('Reels'!D20='Reels'!D2,'Reels'!D21='Reels'!D3))) -> FALSE | H3: =IF(G3,C3,0) -> 0
A4: class.fighter | B4: attack1 / attack1 / block1 | C4: =('Reels'!D4/('Reels'!D4+'Reels'!D7+'Reels'!D10+'Reels'!D13+'Reels'!D16+'Reels'!D19))*('Reels'!D22/('Reels'!D22+'Reels'!D25+'Reels'!D28+'Reels'!D31+'Reels'!D34+'Reels'!D37+'Reels'!D40))*('Reels'!D50/('Reels'!D44+'Reels'!D47+'Reels'!D50+'Reels'!D53+'Reels'!D56+'Reels'!D59)) -> 0.019090909 | D4: =IF(OR('Reels'!D2="attack",'Reels'!D2="magic"),CHOOSE('Reels'!D3+1,'Slots'!D29,'Slots'!D30,'Slots'!D31,'Slots'!D32,'Slots'!D33),0)+IF(OR('Reels'!D20="attack",'Reels'!D20="magic"),CHOOSE('Reels'!D21+1,'Slots'!D29,'Slots'!D30,'Slots'!D31,'Slots'!D32,'Slots'!D33),0)+IF(OR('Reels'!D48="attack",'Reels'!D48="magic"),CHOOSE('Reels'!D49+1,'Slots'!D29,'Slots'!D30,'Slots'!D31,'Slots'!D32,'Slots'!D33),0) -> 4 | E4: =IF('Reels'!D2="heal",'Reels'!D3*'Slots'!D24,0)+IF('Reels'!D20="heal",'Reels'!D21*'Slots'!D24,0)+IF('Reels'!D48="heal",'Reels'!D49*'Slots'!D24,0) -> 0 | F4: =IF('Reels'!D2="block",'Reels'!D3*'Slots'!D25,0)+IF('Reels'!D20="block",'Reels'!D21*'Slots'!D25,0)+IF('Reels'!D48="block",'Reels'!D49*'Slots'!D25,0) -> 1 | G4: =AND('Reels'!D2<>"blank",'Reels'!D2<>"class",'Reels'!D2='Reels'!D48,'Reels'!D3='Reels'!D49,OR('Reels'!D20="class",AND('Reels'!D20='Reels'!D2,'Reels'!D21='Reels'!D3))) -> FALSE | H4: =IF(G4,C4,0) -> 0
A5: class.fighter | B5: attack1 / attack1 / block2 | C5: =('Reels'!D4/('Reels'!D4+'Reels'!D7+'Reels'!D10+'Reels'!D13+'Reels'!D16+'Reels'!D19))*('Reels'!D22/('Reels'!D22+'Reels'!D25+'Reels'!D28+'Reels'!D31+'Reels'!D34+'Reels'!D37+'Reels'!D40))*('Reels'!D53/('Reels'!D44+'Reels'!D47+'Reels'!D50+'Reels'!D53+'Reels'!D56+'Reels'!D59)) -> 0.0081818182 | D5: =IF(OR('Reels'!D2="attack",'Reels'!D2="magic"),CHOOSE('Reels'!D3+1,'Slots'!D29,'Slots'!D30,'Slots'!D31,'Slots'!D32,'Slots'!D33),0)+IF(OR('Reels'!D20="attack",'Reels'!D20="magic"),CHOOSE('Reels'!D21+1,'Slots'!D29,'Slots'!D30,'Slots'!D31,'Slots'!D32,'Slots'!D33),0)+IF(OR('Reels'!D51="attack",'Reels'!D51="magic"),CHOOSE('Reels'!D52+1,'Slots'!D29,'Slots'!D30,'Slots'!D31,'Slots'!D32,'Slots'!D33),0) -> 4 | E5: =IF('Reels'!D2="heal",'Reels'!D3*'Slots'!D24,0)+IF('Reels'!D20="heal",'Reels'!D21*'Slots'!D24,0)+IF('Reels'!D51="heal",'Reels'!D52*'Slots'!D24,0) -> 0 | F5: =IF('Reels'!D2="block",'Reels'!D3*'Slots'!D25,0)+IF('Reels'!D20="block",'Reels'!D21*'Slots'!D25,0)+IF('Reels'!D51="block",'Reels'!D52*'Slots'!D25,0) -> 2 | G5: =AND('Reels'!D2<>"blank",'Reels'!D2<>"class",'Reels'!D2='Reels'!D51,'Reels'!D3='Reels'!D52,OR('Reels'!D20="class",AND('Reels'!D20='Reels'!D2,'Reels'!D21='Reels'!D3))) -> FALSE | H5: =IF(G5,C5,0) -> 0
A6: class.fighter | B6: attack1 / attack1 / heal1 | C6: =('Reels'!D4/('Reels'!D4+'Reels'!D7+'Reels'!D10+'Reels'!D13+'Reels'!D16+'Reels'!D19))*('Reels'!D22/('Reels'!D22+'Reels'!D25+'Reels'!D28+'Reels'!D31+'Reels'!D34+'Reels'!D37+'Reels'!D40))*('Reels'!D56/('Reels'!D44+'Reels'!D47+'Reels'!D50+'Reels'!D53+'Reels'!D56+'Reels'!D59)) -> 0.0027272727 | D6: =IF(OR('Reels'!D2="attack",'Reels'!D2="magic"),CHOOSE('Reels'!D3+1,'Slots'!D29,'Slots'!D30,'Slots'!D31,'Slots'!D32,'Slots'!D33),0)+IF(OR('Reels'!D20="attack",'Reels'!D20="magic"),CHOOSE('Reels'!D21+1,'Slots'!D29,'Slots'!D30,'Slots'!D31,'Slots'!D32,'Slots'!D33),0)+IF(OR('Reels'!D54="attack",'Reels'!D54="magic"),CHOOSE('Reels'!D55+1,'Slots'!D29,'Slots'!D30,'Slots'!D31,'Slots'!D32,'Slots'!D33),0) -> 4 | E6: =IF('Reels'!D2="heal",'Reels'!D3*'Slots'!D24,0)+IF('Reels'!D20="heal",'Reels'!D21*'Slots'!D24,0)+IF('Reels'!D54="heal",'Reels'!D55*'Slots'!D24,0) -> 2 | F6: =IF('Reels'!D2="block",'Reels'!D3*'Slots'!D25,0)+IF('Reels'!D20="block",'Reels'!D21*'Slots'!D25,0)+IF('Reels'!D54="block",'Reels'!D55*'Slots'!D25,0) -> 0 | G6: =AND('Reels'!D2<>"blank",'Reels'!D2<>"class",'Reels'!D2='Reels'!D54,'Reels'!D3='Reels'!D55,OR('Reels'!D20="class",AND('Reels'!D20='Reels'!D2,'Reels'!D21='Reels'!D3))) -> FALSE | H6: =IF(G6,C6,0) -> 0
A7: class.fighter | B7: attack1 / attack1 / blank1 | C7: =('Reels'!D4/('Reels'!D4+'Reels'!D7+'Reels'!D10+'Reels'!D13+'Reels'!D16+'Reels'!D19))*('Reels'!D22/('Reels'!D22+'Reels'!D25+'Reels'!D28+'Reels'!D31+'Reels'!D34+'Reels'!D37+'Reels'!D40))*('Reels'!D59/('Reels'!D44+'Reels'!D47+'Reels'!D50+'Reels'!D53+'Reels'!D56+'Reels'!D59)) -> 0.013636364 | D7: =IF(OR('Reels'!D2="attack",'Reels'!D2="magic"),CHOOSE('Reels'!D3+1,'Slots'!D29,'Slots'!D30,'Slots'!D31,'Slots'!D32,'Slots'!D33),0)+IF(OR('Reels'!D20="attack",'Reels'!D20="magic"),CHOOSE('Reels'!D21+1,'Slots'!D29,'Slots'!D30,'Slots'!D31,'Slots'!D32,'Slots'!D33),0)+IF(OR('Reels'!D57="attack",'Reels'!D57="magic"),CHOOSE('Reels'!D58+1,'Slots'!D29,'Slots'!D30,'Slots'!D31,'Slots'!D32,'Slots'!D33),0) -> 4 | E7: =IF('Reels'!D2="heal",'Reels'!D3*'Slots'!D24,0)+IF('Reels'!D20="heal",'Reels'!D21*'Slots'!D24,0)+IF('Reels'!D57="heal",'Reels'!D58*'Slots'!D24,0) -> 0 | F7: =IF('Reels'!D2="block",'Reels'!D3*'Slots'!D25,0)+IF('Reels'!D20="block",'Reels'!D21*'Slots'!D25,0)+IF('Reels'!D57="block",'Reels'!D58*'Slots'!D25,0) -> 0 | G7: =AND('Reels'!D2<>"blank",'Reels'!D2<>"class",'Reels'!D2='Reels'!D57,'Reels'!D3='Reels'!D58,OR('Reels'!D20="class",AND('Reels'!D20='Reels'!D2,'Reels'!D21='Reels'!D3))) -> FALSE | H7: =IF(G7,C7,0) -> 0
A8: class.fighter | B8: attack1 / attack2 / attack1 | C8: =('Reels'!D4/('Reels'!D4+'Reels'!D7+'Reels'!D10+'Reels'!D13+'Reels'!D16+'Reels'!D19))*('Reels'!D25/('Reels'!D22+'Reels'!D25+'Reels'!D28+'Reels'!D31+'Reels'!D34+'Reels'!D37+'Reels'!D40))*('Reels'!D44/('Reels'!D44+'Reels'!D47+'Reels'!D50+'Reels'!D53+'Reels'!D56+'Reels'!D59)) -> 0.013636364 | D8: =IF(OR('Reels'!D2="attack",'Reels'!D2="magic"),CHOOSE('Reels'!D3+1,'Slots'!D29,'Slots'!D30,'Slots'!D31,'Slots'!D32,'Slots'!D33),0)+IF(OR('Reels'!D23="attack",'Reels'!D23="magic"),CHOOSE('Reels'!D24+1,'Slots'!D29,'Slots'!D30,'Slots'!D31,'Slots'!D32,'Slots'!D33),0)+IF(OR('Reels'!D42="attack",'Reels'!D42="magic"),CHOOSE('Reels'!D43+1,'Slots'!D29,'Slots'!D30,'Slots'!D31,'Slots'!D32,'Slots'!D33),0) -> 8 | E8: =IF('Reels'!D2="heal",'Reels'!D3*'Slots'!D24,0)+IF('Reels'!D23="heal",'Reels'!D24*'Slots'!D24,0)+IF('Reels'!D42="heal",'Reels'!D43*'Slots'!D24,0) -> 0 | F8: =IF('Reels'!D2="block",'Reels'!D3*'Slots'!D25,0)+IF('Reels'!D23="block",'Reels'!D24*'Slots'!D25,0)+IF('Reels'!D42="block",'Reels'!D43*'Slots'!D25,0) -> 0 | G8: =AND('Reels'!D2<>"blank",'Reels'!D2<>"class",'Reels'!D2='Reels'!D42,'Reels'!D3='Reels'!D43,OR('Reels'!D23="class",AND('Reels'!D23='Reels'!D2,'Reels'!D24='Reels'!D3))) -> FALSE | H8: =IF(G8,C8,0) -> 0
A9: class.fighter | B9: attack1 / attack2 / attack2 | C9: =('Reels'!D4/('Reels'!D4+'Reels'!D7+'Reels'!D10+'Reels'!D13+'Reels'!D16+'Reels'!D19))*('Reels'!D25/('Reels'!D22+'Reels'!D25+'Reels'!D28+'Reels'!D31+'Reels'!D34+'Reels'!D37+'Reels'!D40))*('Reels'!D47/('Reels'!D44+'Reels'!D47+'Reels'!D50+'Reels'!D53+'Reels'!D56+'Reels'!D59)) -> 0.0075757576 | D9: =IF(OR('Reels'!D2="attack",'Reels'!D2="magic"),CHOOSE('Reels'!D3+1,'Slots'!D29,'Slots'!D30,'Slots'!D31,'Slots'!D32,'Slots'!D33),0)+IF(OR('Reels'!D23="attack",'Reels'!D23="magic"),CHOOSE('Reels'!D24+1,'Slots'!D29,'Slots'!D30,'Slots'!D31,'Slots'!D32,'Slots'!D33),0)+IF(OR('Reels'!D45="attack",'Reels'!D45="magic"),CHOOSE('Reels'!D46+1,'Slots'!D29,'Slots'!D30,'Slots'!D31,'Slots'!D32,'Slots'!D33),0) -> 10 | E9: =IF('Reels'!D2="heal",'Reels'!D3*'Slots'!D24,0)+IF('Reels'!D23="heal",'Reels'!D24*'Slots'!D24,0)+IF('Reels'!D45="heal",'Reels'!D46*'Slots'!D24,0) -> 0 | F9: =IF('Reels'!D2="block",'Reels'!D3*'Slots'!D25,0)+IF('Reels'!D23="block",'Reels'!D24*'Slots'!D25,0)+IF('Reels'!D45="block",'Reels'!D46*'Slots'!D25,0) -> 0 | G9: =AND('Reels'!D2<>"blank",'Reels'!D2<>"class",'Reels'!D2='Reels'!D45,'Reels'!D3='Reels'!D46,OR('Reels'!D23="class",AND('Reels'!D23='Reels'!D2,'Reels'!D24='Reels'!D3))) -> FALSE | H9: =IF(G9,C9,0) -> 0
A10: class.fighter | B10: attack1 / attack2 / block1 | C10: =('Reels'!D4/('Reels'!D4+'Reels'!D7+'Reels'!D10+'Reels'!D13+'Reels'!D16+'Reels'!D19))*('Reels'!D25/('Reels'!D22+'Reels'!D25+'Reels'!D28+'Reels'!D31+'Reels'!D34+'Reels'!D37+'Reels'!D40))*('Reels'!D50/('Reels'!D44+'Reels'!D47+'Reels'!D50+'Reels'!D53+'Reels'!D56+'Reels'!D59)) -> 0.010606061 | D10: =IF(OR('Reels'!D2="attack",'Reels'!D2="magic"),CHOOSE('Reels'!D3+1,'Slots'!D29,'Slots'!D30,'Slots'!D31,'Slots'!D32,'Slots'!D33),0)+IF(OR('Reels'!D23="attack",'Reels'!D23="magic"),CHOOSE('Reels'!D24+1,'Slots'!D29,'Slots'!D30,'Slots'!D31,'Slots'!D32,'Slots'!D33),0)+IF(OR('Reels'!D48="attack",'Reels'!D48="magic"),CHOOSE('Reels'!D49+1,'Slots'!D29,'Slots'!D30,'Slots'!D31,'Slots'!D32,'Slots'!D33),0) -> 6 | E10: =IF('Reels'!D2="heal",'Reels'!D3*'Slots'!D24,0)+IF('Reels'!D23="heal",'Reels'!D24*'Slots'!D24,0)+IF('Reels'!D48="heal",'Reels'!D49*'Slots'!D24,0) -> 0 | F10: =IF('Reels'!D2="block",'Reels'!D3*'Slots'!D25,0)+IF('Reels'!D23="block",'Reels'!D24*'Slots'!D25,0)+IF('Reels'!D48="block",'Reels'!D49*'Slots'!D25,0) -> 1 | G10: =AND('Reels'!D2<>"blank",'Reels'!D2<>"class",'Reels'!D2='Reels'!D48,'Reels'!D3='Reels'!D49,OR('Reels'!D23="class",AND('Reels'!D23='Reels'!D2,'Reels'!D24='Reels'!D3))) -> FALSE | H10: =IF(G10,C10,0) -> 0
A11: class.fighter | B11: attack1 / attack2 / block2 | C11: =('Reels'!D4/('Reels'!D4+'Reels'!D7+'Reels'!D10+'Reels'!D13+'Reels'!D16+'Reels'!D19))*('Reels'!D25/('Reels'!D22+'Reels'!D25+'Reels'!D28+'Reels'!D31+'Reels'!D34+'Reels'!D37+'Reels'!D40))*('Reels'!D53/('Reels'!D44+'Reels'!D47+'Reels'!D50+'Reels'!D53+'Reels'!D56+'Reels'!D59)) -> 0.0045454545 | D11: =IF(OR('Reels'!D2="attack",'Reels'!D2="magic"),CHOOSE('Reels'!D3+1,'Slots'!D29,'Slots'!D30,'Slots'!D31,'Slots'!D32,'Slots'!D33),0)+IF(OR('Reels'!D23="attack",'Reels'!D23="magic"),CHOOSE('Reels'!D24+1,'Slots'!D29,'Slots'!D30,'Slots'!D31,'Slots'!D32,'Slots'!D33),0)+IF(OR('Reels'!D51="attack",'Reels'!D51="magic"),CHOOSE('Reels'!D52+1,'Slots'!D29,'Slots'!D30,'Slots'!D31,'Slots'!D32,'Slots'!D33),0) -> 6 | E11: =IF('Reels'!D2="heal",'Reels'!D3*'Slots'!D24,0)+IF('Reels'!D23="heal",'Reels'!D24*'Slots'!D24,0)+IF('Reels'!D51="heal",'Reels'!D52*'Slots'!D24,0) -> 0 | F11: =IF('Reels'!D2="block",'Reels'!D3*'Slots'!D25,0)+IF('Reels'!D23="block",'Reels'!D24*'Slots'!D25,0)+IF('Reels'!D51="block",'Reels'!D52*'Slots'!D25,0) -> 2 | G11: =AND('Reels'!D2<>"blank",'Reels'!D2<>"class",'Reels'!D2='Reels'!D51,'Reels'!D3='Reels'!D52,OR('Reels'!D23="class",AND('Reels'!D23='Reels'!D2,'Reels'!D24='Reels'!D3))) -> FALSE | H11: =IF(G11,C11,0) -> 0
A12: class.fighter | B12: attack1 / attack2 / heal1 | C12: =('Reels'!D4/('Reels'!D4+'Reels'!D7+'Reels'!D10+'Reels'!D13+'Reels'!D16+'Reels'!D19))*('Reels'!D25/('Reels'!D22+'Reels'!D25+'Reels'!D28+'Reels'!D31+'Reels'!D34+'Reels'!D37+'Reels'!D40))*('Reels'!D56/('Reels'!D44+'Reels'!D47+'Reels'!D50+'Reels'!D53+'Reels'!D56+'Reels'!D59)) -> 0.0015151515 | D12: =IF(OR('Reels'!D2="attack",'Reels'!D2="magic"),CHOOSE('Reels'!D3+1,'Slots'!D29,'Slots'!D30,'Slots'!D31,'Slots'!D32,'Slots'!D33),0)+IF(OR('Reels'!D23="attack",'Reels'!D23="magic"),CHOOSE('Reels'!D24+1,'Slots'!D29,'Slots'!D30,'Slots'!D31,'Slots'!D32,'Slots'!D33),0)+IF(OR('Reels'!D54="attack",'Reels'!D54="magic"),CHOOSE('Reels'!D55+1,'Slots'!D29,'Slots'!D30,'Slots'!D31,'Slots'!D32,'Slots'!D33),0) -> 6 | E12: =IF('Reels'!D2="heal",'Reels'!D3*'Slots'!D24,0)+IF('Reels'!D23="heal",'Reels'!D24*'Slots'!D24,0)+IF('Reels'!D54="heal",'Reels'!D55*'Slots'!D24,0) -> 2 | F12: =IF('Reels'!D2="block",'Reels'!D3*'Slots'!D25,0)+IF('Reels'!D23="block",'Reels'!D24*'Slots'!D25,0)+IF('Reels'!D54="block",'Reels'!D55*'Slots'!D25,0) -> 0 | G12: =AND('Reels'!D2<>"blank",'Reels'!D2<>"class",'Reels'!D2='Reels'!D54,'Reels'!D3='Reels'!D55,OR('Reels'!D23="class",AND('Reels'!D23='Reels'!D2,'Reels'!D24='Reels'!D3))) -> FALSE | H12: =IF(G12,C12,0) -> 0
A13: class.fighter | B13: attack1 / attack2 / blank1 | C13: =('Reels'!D4/('Reels'!D4+'Reels'!D7+'Reels'!D10+'Reels'!D13+'Reels'!D16+'Reels'!D19))*('Reels'!D25/('Reels'!D22+'Reels'!D25+'Reels'!D28+'Reels'!D31+'Reels'!D34+'Reels'!D37+'Reels'!D40))*('Reels'!D59/('Reels'!D44+'Reels'!D47+'Reels'!D50+'Reels'!D53+'Reels'!D56+'Reels'!D59)) -> 0.0075757576 | D13: =IF(OR('Reels'!D2="attack",'Reels'!D2="magic"),CHOOSE('Reels'!D3+1,'Slots'!D29,'Slots'!D30,'Slots'!D31,'Slots'!D32,'Slots'!D33),0)+IF(OR('Reels'!D23="attack",'Reels'!D23="magic"),CHOOSE('Reels'!D24+1,'Slots'!D29,'Slots'!D30,'Slots'!D31,'Slots'!D32,'Slots'!D33),0)+IF(OR('Reels'!D57="attack",'Reels'!D57="magic"),CHOOSE('Reels'!D58+1,'Slots'!D29,'Slots'!D30,'Slots'!D31,'Slots'!D32,'Slots'!D33),0) -> 6 | E13: =IF('Reels'!D2="heal",'Reels'!D3*'Slots'!D24,0)+IF('Reels'!D23="heal",'Reels'!D24*'Slots'!D24,0)+IF('Reels'!D57="heal",'Reels'!D58*'Slots'!D24,0) -> 0 | F13: =IF('Reels'!D2="block",'Reels'!D3*'Slots'!D25,0)+IF('Reels'!D23="block",'Reels'!D24*'Slots'!D25,0)+IF('Reels'!D57="block",'Reels'!D58*'Slots'!D25,0) -> 0 | G13: =AND('Reels'!D2<>"blank",'Reels'!D2<>"class",'Reels'!D2='Reels'!D57,'Reels'!D3='Reels'!D58,OR('Reels'!D23="class",AND('Reels'!D23='Reels'!D2,'Reels'!D24='Reels'!D3))) -> FALSE | H13: =IF(G13,C13,0) -> 0
A14: class.fighter | B14: attack1 / block1 / attack1 | C14: =('Reels'!D4/('Reels'!D4+'Reels'!D7+'Reels'!D10+'Reels'!D13+'Reels'!D16+'Reels'!D19))*('Reels'!D28/('Reels'!D22+'Reels'!D25+'Reels'!D28+'Reels'!D31+'Reels'!D34+'Reels'!D37+'Reels'!D40))*('Reels'!D44/('Reels'!D44+'Reels'!D47+'Reels'!D50+'Reels'!D53+'Reels'!D56+'Reels'!D59)) -> 0.019090909 | D14: =IF(OR('Reels'!D2="attack",'Reels'!D2="magic"),CHOOSE('Reels'!D3+1,'Slots'!D29,'Slots'!D30,'Slots'!D31,'Slots'!D32,'Slots'!D33),0)+IF(OR('Reels'!D26="attack",'Reels'!D26="magic"),CHOOSE('Reels'!D27+1,'Slots'!D29,'Slots'!D30,'Slots'!D31,'Slots'!D32,'Slots'!D33),0)+IF(OR('Reels'!D42="attack",'Reels'!D42="magic"),CHOOSE('Reels'!D43+1,'Slots'!D29,'Slots'!D30,'Slots'!D31,'Slots'!D32,'Slots'!D33),0) -> 4 | E14: =IF('Reels'!D2="heal",'Reels'!D3*'Slots'!D24,0)+IF('Reels'!D26="heal",'Reels'!D27*'Slots'!D24,0)+IF('Reels'!D42="heal",'Reels'!D43*'Slots'!D24,0) -> 0 | F14: =IF('Reels'!D2="block",'Reels'!D3*'Slots'!D25,0)+IF('Reels'!D26="block",'Reels'!D27*'Slots'!D25,0)+IF('Reels'!D42="block",'Reels'!D43*'Slots'!D25,0) -> 1 | G14: =AND('Reels'!D2<>"blank",'Reels'!D2<>"class",'Reels'!D2='Reels'!D42,'Reels'!D3='Reels'!D43,OR('Reels'!D26="class",AND('Reels'!D26='Reels'!D2,'Reels'!D27='Reels'!D3))) -> FALSE | H14: =IF(G14,C14,0) -> 0
A15: class.fighter | B15: attack1 / block1 / attack2 | C15: =('Reels'!D4/('Reels'!D4+'Reels'!D7+'Reels'!D10+'Reels'!D13+'Reels'!D16+'Reels'!D19))*('Reels'!D28/('Reels'!D22+'Reels'!D25+'Reels'!D28+'Reels'!D31+'Reels'!D34+'Reels'!D37+'Reels'!D40))*('Reels'!D47/('Reels'!D44+'Reels'!D47+'Reels'!D50+'Reels'!D53+'Reels'!D56+'Reels'!D59)) -> 0.010606061 | D15: =IF(OR('Reels'!D2="attack",'Reels'!D2="magic"),CHOOSE('Reels'!D3+1,'Slots'!D29,'Slots'!D30,'Slots'!D31,'Slots'!D32,'Slots'!D33),0)+IF(OR('Reels'!D26="attack",'Reels'!D26="magic"),CHOOSE('Reels'!D27+1,'Slots'!D29,'Slots'!D30,'Slots'!D31,'Slots'!D32,'Slots'!D33),0)+IF(OR('Reels'!D45="attack",'Reels'!D45="magic"),CHOOSE('Reels'!D46+1,'Slots'!D29,'Slots'!D30,'Slots'!D31,'Slots'!D32,'Slots'!D33),0) -> 6 | E15: =IF('Reels'!D2="heal",'Reels'!D3*'Slots'!D24,0)+IF('Reels'!D26="heal",'Reels'!D27*'Slots'!D24,0)+IF('Reels'!D45="heal",'Reels'!D46*'Slots'!D24,0) -> 0 | F15: =IF('Reels'!D2="block",'Reels'!D3*'Slots'!D25,0)+IF('Reels'!D26="block",'Reels'!D27*'Slots'!D25,0)+IF('Reels'!D45="block",'Reels'!D46*'Slots'!D25,0) -> 1 | G15: =AND('Reels'!D2<>"blank",'Reels'!D2<>"class",'Reels'!D2='Reels'!D45,'Reels'!D3='Reels'!D46,OR('Reels'!D26="class",AND('Reels'!D26='Reels'!D2,'Reels'!D27='Reels'!D3))) -> FALSE | H15: =IF(G15,C15,0) -> 0
A16: class.fighter | B16: attack1 / block1 / block1 | C16: =('Reels'!D4/('Reels'!D4+'Reels'!D7+'Reels'!D10+'Reels'!D13+'Reels'!D16+'Reels'!D19))*('Reels'!D28/('Reels'!D22+'Reels'!D25+'Reels'!D28+'Reels'!D31+'Reels'!D34+'Reels'!D37+'Reels'!D40))*('Reels'!D50/('Reels'!D44+'Reels'!D47+'Reels'!D50+'Reels'!D53+'Reels'!D56+'Reels'!D59)) -> 0.014848485 | D16: =IF(OR('Reels'!D2="attack",'Reels'!D2="magic"),CHOOSE('Reels'!D3+1,'Slots'!D29,'Slots'!D30,'Slots'!D31,'Slots'!D32,'Slots'!D33),0)+IF(OR('Reels'!D26="attack",'Reels'!D26="magic"),CHOOSE('Reels'!D27+1,'Slots'!D29,'Slots'!D30,'Slots'!D31,'Slots'!D32,'Slots'!D33),0)+IF(OR('Reels'!D48="attack",'Reels'!D48="magic"),CHOOSE('Reels'!D49+1,'Slots'!D29,'Slots'!D30,'Slots'!D31,'Slots'!D32,'Slots'!D33),0) -> 2 | E16: =IF('Reels'!D2="heal",'Reels'!D3*'Slots'!D24,0)+IF('Reels'!D26="heal",'Reels'!D27*'Slots'!D24,0)+IF('Reels'!D48="heal",'Reels'!D49*'Slots'!D24,0) -> 0 | F16: =IF('Reels'!D2="block",'Reels'!D3*'Slots'!D25,0)+IF('Reels'!D26="block",'Reels'!D27*'Slots'!D25,0)+IF('Reels'!D48="block",'Reels'!D49*'Slots'!D25,0) -> 2 | G16: =AND('Reels'!D2<>"blank",'Reels'!D2<>"class",'Reels'!D2='Reels'!D48,'Reels'!D3='Reels'!D49,OR('Reels'!D26="class",AND('Reels'!D26='Reels'!D2,'Reels'!D27='Reels'!D3))) -> FALSE | H16: =IF(G16,C16,0) -> 0
A17: class.fighter | B17: attack1 / block1 / block2 | C17: =('Reels'!D4/('Reels'!D4+'Reels'!D7+'Reels'!D10+'Reels'!D13+'Reels'!D16+'Reels'!D19))*('Reels'!D28/('Reels'!D22+'Reels'!D25+'Reels'!D28+'Reels'!D31+'Reels'!D34+'Reels'!D37+'Reels'!D40))*('Reels'!D53/('Reels'!D44+'Reels'!D47+'Reels'!D50+'Reels'!D53+'Reels'!D56+'Reels'!D59)) -> 0.0063636364 | D17: =IF(OR('Reels'!D2="attack",'Reels'!D2="magic"),CHOOSE('Reels'!D3+1,'Slots'!D29,'Slots'!D30,'Slots'!D31,'Slots'!D32,'Slots'!D33),0)+IF(OR('Reels'!D26="attack",'Reels'!D26="magic"),CHOOSE('Reels'!D27+1,'Slots'!D29,'Slots'!D30,'Slots'!D31,'Slots'!D32,'Slots'!D33),0)+IF(OR('Reels'!D51="attack",'Reels'!D51="magic"),CHOOSE('Reels'!D52+1,'Slots'!D29,'Slots'!D30,'Slots'!D31,'Slots'!D32,'Slots'!D33),0) -> 2 | E17: =IF('Reels'!D2="heal",'Reels'!D3*'Slots'!D24,0)+IF('Reels'!D26="heal",'Reels'!D27*'Slots'!D24,0)+IF('Reels'!D51="heal",'Reels'!D52*'Slots'!D24,0) -> 0 | F17: =IF('Reels'!D2="block",'Reels'!D3*'Slots'!D25,0)+IF('Reels'!D26="block",'Reels'!D27*'Slots'!D25,0)+IF('Reels'!D51="block",'Reels'!D52*'Slots'!D25,0) -> 3 | G17: =AND('Reels'!D2<>"blank",'Reels'!D2<>"class",'Reels'!D2='Reels'!D51,'Reels'!D3='Reels'!D52,OR('Reels'!D26="class",AND('Reels'!D26='Reels'!D2,'Reels'!D27='Reels'!D3))) -> FALSE | H17: =IF(G17,C17,0) -> 0
A18: class.fighter | B18: attack1 / block1 / heal1 | C18: =('Reels'!D4/('Reels'!D4+'Reels'!D7+'Reels'!D10+'Reels'!D13+'Reels'!D16+'Reels'!D19))*('Reels'!D28/('Reels'!D22+'Reels'!D25+'Reels'!D28+'Reels'!D31+'Reels'!D34+'Reels'!D37+'Reels'!D40))*('Reels'!D56/('Reels'!D44+'Reels'!D47+'Reels'!D50+'Reels'!D53+'Reels'!D56+'Reels'!D59)) -> 0.0021212121 | D18: =IF(OR('Reels'!D2="attack",'Reels'!D2="magic"),CHOOSE('Reels'!D3+1,'Slots'!D29,'Slots'!D30,'Slots'!D31,'Slots'!D32,'Slots'!D33),0)+IF(OR('Reels'!D26="attack",'Reels'!D26="magic"),CHOOSE('Reels'!D27+1,'Slots'!D29,'Slots'!D30,'Slots'!D31,'Slots'!D32,'Slots'!D33),0)+IF(OR('Reels'!D54="attack",'Reels'!D54="magic"),CHOOSE('Reels'!D55+1,'Slots'!D29,'Slots'!D30,'Slots'!D31,'Slots'!D32,'Slots'!D33),0) -> 2 | E18: =IF('Reels'!D2="heal",'Reels'!D3*'Slots'!D24,0)+IF('Reels'!D26="heal",'Reels'!D27*'Slots'!D24,0)+IF('Reels'!D54="heal",'Reels'!D55*'Slots'!D24,0) -> 2 | F18: =IF('Reels'!D2="block",'Reels'!D3*'Slots'!D25,0)+IF('Reels'!D26="block",'Reels'!D27*'Slots'!D25,0)+IF('Reels'!D54="block",'Reels'!D55*'Slots'!D25,0) -> 1 | G18: =AND('Reels'!D2<>"blank",'Reels'!D2<>"class",'Reels'!D2='Reels'!D54,'Reels'!D3='Reels'!D55,OR('Reels'!D26="class",AND('Reels'!D26='Reels'!D2,'Reels'!D27='Reels'!D3))) -> FALSE | H18: =IF(G18,C18,0) -> 0
A19: class.fighter | B19: attack1 / block1 / blank1 | C19: =('Reels'!D4/('Reels'!D4+'Reels'!D7+'Reels'!D10+'Reels'!D13+'Reels'!D16+'Reels'!D19))*('Reels'!D28/('Reels'!D22+'Reels'!D25+'Reels'!D28+'Reels'!D31+'Reels'!D34+'Reels'!D37+'Reels'!D40))*('Reels'!D59/('Reels'!D44+'Reels'!D47+'Reels'!D50+'Reels'!D53+'Reels'!D56+'Reels'!D59)) -> 0.010606061 | D19: =IF(OR('Reels'!D2="attack",'Reels'!D2="magic"),CHOOSE('Reels'!D3+1,'Slots'!D29,'Slots'!D30,'Slots'!D31,'Slots'!D32,'Slots'!D33),0)+IF(OR('Reels'!D26="attack",'Reels'!D26="magic"),CHOOSE('Reels'!D27+1,'Slots'!D29,'Slots'!D30,'Slots'!D31,'Slots'!D32,'Slots'!D33),0)+IF(OR('Reels'!D57="attack",'Reels'!D57="magic"),CHOOSE('Reels'!D58+1,'Slots'!D29,'Slots'!D30,'Slots'!D31,'Slots'!D32,'Slots'!D33),0) -> 2 | E19: =IF('Reels'!D2="heal",'Reels'!D3*'Slots'!D24,0)+IF('Reels'!D26="heal",'Reels'!D27*'Slots'!D24,0)+IF('Reels'!D57="heal",'Reels'!D58*'Slots'!D24,0) -> 0 | F19: =IF('Reels'!D2="block",'Reels'!D3*'Slots'!D25,0)+IF('Reels'!D26="block",'Reels'!D27*'Slots'!D25,0)+IF('Reels'!D57="block",'Reels'!D58*'Slots'!D25,0) -> 1 | G19: =AND('Reels'!D2<>"blank",'Reels'!D2<>"class",'Reels'!D2='Reels'!D57,'Reels'!D3='Reels'!D58,OR('Reels'!D26="class",AND('Reels'!D26='Reels'!D2,'Reels'!D27='Reels'!D3))) -> FALSE | H19: =IF(G19,C19,0) -> 0
A20: class.fighter | B20: attack1 / block2 / attack1 | C20: =('Reels'!D4/('Reels'!D4+'Reels'!D7+'Reels'!D10+'Reels'!D13+'Reels'!D16+'Reels'!D19))*('Reels'!D31/('Reels'!D22+'Reels'!D25+'Reels'!D28+'Reels'!D31+'Reels'!D34+'Reels'!D37+'Reels'!D40))*('Reels'!D44/('Reels'!D44+'Reels'!D47+'Reels'!D50+'Reels'!D53+'Reels'!D56+'Reels'!D59)) -> 0.0081818182 | D20: =IF(OR('Reels'!D2="attack",'Reels'!D2="magic"),CHOOSE('Reels'!D3+1,'Slots'!D29,'Slots'!D30,'Slots'!D31,'Slots'!D32,'Slots'!D33),0)+IF(OR('Reels'!D29="attack",'Reels'!D29="magic"),CHOOSE('Reels'!D30+1,'Slots'!D29,'Slots'!D30,'Slots'!D31,'Slots'!D32,'Slots'!D33),0)+IF(OR('Reels'!D42="attack",'Reels'!D42="magic"),CHOOSE('Reels'!D43+1,'Slots'!D29,'Slots'!D30,'Slots'!D31,'Slots'!D32,'Slots'!D33),0) -> 4 | E20: =IF('Reels'!D2="heal",'Reels'!D3*'Slots'!D24,0)+IF('Reels'!D29="heal",'Reels'!D30*'Slots'!D24,0)+IF('Reels'!D42="heal",'Reels'!D43*'Slots'!D24,0) -> 0 | F20: =IF('Reels'!D2="block",'Reels'!D3*'Slots'!D25,0)+IF('Reels'!D29="block",'Reels'!D30*'Slots'!D25,0)+IF('Reels'!D42="block",'Reels'!D43*'Slots'!D25,0) -> 2 | G20: =AND('Reels'!D2<>"blank",'Reels'!D2<>"class",'Reels'!D2='Reels'!D42,'Reels'!D3='Reels'!D43,OR('Reels'!D29="class",AND('Reels'!D29='Reels'!D2,'Reels'!D30='Reels'!D3))) -> FALSE | H20: =IF(G20,C20,0) -> 0
A21: class.fighter | B21: attack1 / block2 / attack2 | C21: =('Reels'!D4/('Reels'!D4+'Reels'!D7+'Reels'!D10+'Reels'!D13+'Reels'!D16+'Reels'!D19))*('Reels'!D31/('Reels'!D22+'Reels'!D25+'Reels'!D28+'Reels'!D31+'Reels'!D34+'Reels'!D37+'Reels'!D40))*('Reels'!D47/('Reels'!D44+'Reels'!D47+'Reels'!D50+'Reels'!D53+'Reels'!D56+'Reels'!D59)) -> 0.0045454545 | D21: =IF(OR('Reels'!D2="attack",'Reels'!D2="magic"),CHOOSE('Reels'!D3+1,'Slots'!D29,'Slots'!D30,'Slots'!D31,'Slots'!D32,'Slots'!D33),0)+IF(OR('Reels'!D29="attack",'Reels'!D29="magic"),CHOOSE('Reels'!D30+1,'Slots'!D29,'Slots'!D30,'Slots'!D31,'Slots'!D32,'Slots'!D33),0)+IF(OR('Reels'!D45="attack",'Reels'!D45="magic"),CHOOSE('Reels'!D46+1,'Slots'!D29,'Slots'!D30,'Slots'!D31,'Slots'!D32,'Slots'!D33),0) -> 6 | E21: =IF('Reels'!D2="heal",'Reels'!D3*'Slots'!D24,0)+IF('Reels'!D29="heal",'Reels'!D30*'Slots'!D24,0)+IF('Reels'!D45="heal",'Reels'!D46*'Slots'!D24,0) -> 0 | F21: =IF('Reels'!D2="block",'Reels'!D3*'Slots'!D25,0)+IF('Reels'!D29="block",'Reels'!D30*'Slots'!D25,0)+IF('Reels'!D45="block",'Reels'!D46*'Slots'!D25,0) -> 2 | G21: =AND('Reels'!D2<>"blank",'Reels'!D2<>"class",'Reels'!D2='Reels'!D45,'Reels'!D3='Reels'!D46,OR('Reels'!D29="class",AND('Reels'!D29='Reels'!D2,'Reels'!D30='Reels'!D3))) -> FALSE | H21: =IF(G21,C21,0) -> 0
A22: class.fighter | B22: attack1 / block2 / block1 | C22: =('Reels'!D4/('Reels'!D4+'Reels'!D7+'Reels'!D10+'Reels'!D13+'Reels'!D16+'Reels'!D19))*('Reels'!D31/('Reels'!D22+'Reels'!D25+'Reels'!D28+'Reels'!D31+'Reels'!D34+'Reels'!D37+'Reels'!D40))*('Reels'!D50/('Reels'!D44+'Reels'!D47+'Reels'!D50+'Reels'!D53+'Reels'!D56+'Reels'!D59)) -> 0.0063636364 | D22: =IF(OR('Reels'!D2="attack",'Reels'!D2="magic"),CHOOSE('Reels'!D3+1,'Slots'!D29,'Slots'!D30,'Slots'!D31,'Slots'!D32,'Slots'!D33),0)+IF(OR('Reels'!D29="attack",'Reels'!D29="magic"),CHOOSE('Reels'!D30+1,'Slots'!D29,'Slots'!D30,'Slots'!D31,'Slots'!D32,'Slots'!D33),0)+IF(OR('Reels'!D48="attack",'Reels'!D48="magic"),CHOOSE('Reels'!D49+1,'Slots'!D29,'Slots'!D30,'Slots'!D31,'Slots'!D32,'Slots'!D33),0) -> 2 | E22: =IF('Reels'!D2="heal",'Reels'!D3*'Slots'!D24,0)+IF('Reels'!D29="heal",'Reels'!D30*'Slots'!D24,0)+IF('Reels'!D48="heal",'Reels'!D49*'Slots'!D24,0) -> 0 | F22: =IF('Reels'!D2="block",'Reels'!D3*'Slots'!D25,0)+IF('Reels'!D29="block",'Reels'!D30*'Slots'!D25,0)+IF('Reels'!D48="block",'Reels'!D49*'Slots'!D25,0) -> 3 | G22: =AND('Reels'!D2<>"blank",'Reels'!D2<>"class",'Reels'!D2='Reels'!D48,'Reels'!D3='Reels'!D49,OR('Reels'!D29="class",AND('Reels'!D29='Reels'!D2,'Reels'!D30='Reels'!D3))) -> FALSE | H22: =IF(G22,C22,0) -> 0
A23: class.fighter | B23: attack1 / block2 / block2 | C23: =('Reels'!D4/('Reels'!D4+'Reels'!D7+'Reels'!D10+'Reels'!D13+'Reels'!D16+'Reels'!D19))*('Reels'!D31/('Reels'!D22+'Reels'!D25+'Reels'!D28+'Reels'!D31+'Reels'!D34+'Reels'!D37+'Reels'!D40))*('Reels'!D53/('Reels'!D44+'Reels'!D47+'Reels'!D50+'Reels'!D53+'Reels'!D56+'Reels'!D59)) -> 0.0027272727 | D23: =IF(OR('Reels'!D2="attack",'Reels'!D2="magic"),CHOOSE('Reels'!D3+1,'Slots'!D29,'Slots'!D30,'Slots'!D31,'Slots'!D32,'Slots'!D33),0)+IF(OR('Reels'!D29="attack",'Reels'!D29="magic"),CHOOSE('Reels'!D30+1,'Slots'!D29,'Slots'!D30,'Slots'!D31,'Slots'!D32,'Slots'!D33),0)+IF(OR('Reels'!D51="attack",'Reels'!D51="magic"),CHOOSE('Reels'!D52+1,'Slots'!D29,'Slots'!D30,'Slots'!D31,'Slots'!D32,'Slots'!D33),0) -> 2 | E23: =IF('Reels'!D2="heal",'Reels'!D3*'Slots'!D24,0)+IF('Reels'!D29="heal",'Reels'!D30*'Slots'!D24,0)+IF('Reels'!D51="heal",'Reels'!D52*'Slots'!D24,0) -> 0 | F23: =IF('Reels'!D2="block",'Reels'!D3*'Slots'!D25,0)+IF('Reels'!D29="block",'Reels'!D30*'Slots'!D25,0)+IF('Reels'!D51="block",'Reels'!D52*'Slots'!D25,0) -> 4 | G23: =AND('Reels'!D2<>"blank",'Reels'!D2<>"class",'Reels'!D2='Reels'!D51,'Reels'!D3='Reels'!D52,OR('Reels'!D29="class",AND('Reels'!D29='Reels'!D2,'Reels'!D30='Reels'!D3))) -> FALSE | H23: =IF(G23,C23,0) -> 0
A24: class.fighter | B24: attack1 / block2 / heal1 | C24: =('Reels'!D4/('Reels'!D4+'Reels'!D7+'Reels'!D10+'Reels'!D13+'Reels'!D16+'Reels'!D19))*('Reels'!D31/('Reels'!D22+'Reels'!D25+'Reels'!D28+'Reels'!D31+'Reels'!D34+'Reels'!D37+'Reels'!D40))*('Reels'!D56/('Reels'!D44+'Reels'!D47+'Reels'!D50+'Reels'!D53+'Reels'!D56+'Reels'!D59)) -> 0.00090909091 | D24: =IF(OR('Reels'!D2="attack",'Reels'!D2="magic"),CHOOSE('Reels'!D3+1,'Slots'!D29,'Slots'!D30,'Slots'!D31,'Slots'!D32,'Slots'!D33),0)+IF(OR('Reels'!D29="attack",'Reels'!D29="magic"),CHOOSE('Reels'!D30+1,'Slots'!D29,'Slots'!D30,'Slots'!D31,'Slots'!D32,'Slots'!D33),0)+IF(OR('Reels'!D54="attack",'Reels'!D54="magic"),CHOOSE('Reels'!D55+1,'Slots'!D29,'Slots'!D30,'Slots'!D31,'Slots'!D32,'Slots'!D33),0) -> 2 | E24: =IF('Reels'!D2="heal",'Reels'!D3*'Slots'!D24,0)+IF('Reels'!D29="heal",'Reels'!D30*'Slots'!D24,0)+IF('Reels'!D54="heal",'Reels'!D55*'Slots'!D24,0) -> 2 | F24: =IF('Reels'!D2="block",'Reels'!D3*'Slots'!D25,0)+IF('Reels'!D29="block",'Reels'!D30*'Slots'!D25,0)+IF('Reels'!D54="block",'Reels'!D55*'Slots'!D25,0) -> 2 | G24: =AND('Reels'!D2<>"blank",'Reels'!D2<>"class",'Reels'!D2='Reels'!D54,'Reels'!D3='Reels'!D55,OR('Reels'!D29="class",AND('Reels'!D29='Reels'!D2,'Reels'!D30='Reels'!D3))) -> FALSE | H24: =IF(G24,C24,0) -> 0
A25: class.fighter | B25: attack1 / block2 / blank1 | C25: =('Reels'!D4/('Reels'!D4+'Reels'!D7+'Reels'!D10+'Reels'!D13+'Reels'!D16+'Reels'!D19))*('Reels'!D31/('Reels'!D22+'Reels'!D25+'Reels'!D28+'Reels'!D31+'Reels'!D34+'Reels'!D37+'Reels'!D40))*('Reels'!D59/('Reels'!D44+'Reels'!D47+'Reels'!D50+'Reels'!D53+'Reels'!D56+'Reels'!D59)) -> 0.0045454545 | D25: =IF(OR('Reels'!D2="attack",'Reels'!D2="magic"),CHOOSE('Reels'!D3+1,'Slots'!D29,'Slots'!D30,'Slots'!D31,'Slots'!D32,'Slots'!D33),0)+IF(OR('Reels'!D29="attack",'Reels'!D29="magic"),CHOOSE('Reels'!D30+1,'Slots'!D29,'Slots'!D30,'Slots'!D31,'Slots'!D32,'Slots'!D33),0)+IF(OR('Reels'!D57="attack",'Reels'!D57="magic"),CHOOSE('Reels'!D58+1,'Slots'!D29,'Slots'!D30,'Slots'!D31,'Slots'!D32,'Slots'!D33),0) -> 2 | E25: =IF('Reels'!D2="heal",'Reels'!D3*'Slots'!D24,0)+IF('Reels'!D29="heal",'Reels'!D30*'Slots'!D24,0)+IF('Reels'!D57="heal",'Reels'!D58*'Slots'!D24,0) -> 0 | F25: =IF('Reels'!D2="block",'Reels'!D3*'Slots'!D25,0)+IF('Reels'!D29="block",'Reels'!D30*'Slots'!D25,0)+IF('Reels'!D57="block",'Reels'!D58*'Slots'!D25,0) -> 2 | G25: =AND('Reels'!D2<>"blank",'Reels'!D2<>"class",'Reels'!D2='Reels'!D57,'Reels'!D3='Reels'!D58,OR('Reels'!D29="class",AND('Reels'!D29='Reels'!D2,'Reels'!D30='Reels'!D3))) -> FALSE | H25: =IF(G25,C25,0) -> 0
A26: class.fighter | B26: attack1 / heal1 / attack1 | C26: =('Reels'!D4/('Reels'!D4+'Reels'!D7+'Reels'!D10+'Reels'!D13+'Reels'!D16+'Reels'!D19))*('Reels'!D34/('Reels'!D22+'Reels'!D25+'Reels'!D28+'Reels'!D31+'Reels'!D34+'Reels'!D37+'Reels'!D40))*('Reels'!D44/('Reels'!D44+'Reels'!D47+'Reels'!D50+'Reels'!D53+'Reels'!D56+'Reels'!D59)) -> 0.0027272727 | D26: =IF(OR('Reels'!D2="attack",'Reels'!D2="magic"),CHOOSE('Reels'!D3+1,'Slots'!D29,'Slots'!D30,'Slots'!D31,'Slots'!D32,'Slots'!D33),0)+IF(OR('Reels'!D32="attack",'Reels'!D32="magic"),CHOOSE('Reels'!D33+1,'Slots'!D29,'Slots'!D30,'Slots'!D31,'Slots'!D32,'Slots'!D33),0)+IF(OR('Reels'!D42="attack",'Reels'!D42="magic"),CHOOSE('Reels'!D43+1,'Slots'!D29,'Slots'!D30,'Slots'!D31,'Slots'!D32,'Slots'!D33),0) -> 4 | E26: =IF('Reels'!D2="heal",'Reels'!D3*'Slots'!D24,0)+IF('Reels'!D32="heal",'Reels'!D33*'Slots'!D24,0)+IF('Reels'!D42="heal",'Reels'!D43*'Slots'!D24,0) -> 2 | F26: =IF('Reels'!D2="block",'Reels'!D3*'Slots'!D25,0)+IF('Reels'!D32="block",'Reels'!D33*'Slots'!D25,0)+IF('Reels'!D42="block",'Reels'!D43*'Slots'!D25,0) -> 0 | G26: =AND('Reels'!D2<>"blank",'Reels'!D2<>"class",'Reels'!D2='Reels'!D42,'Reels'!D3='Reels'!D43,OR('Reels'!D32="class",AND('Reels'!D32='Reels'!D2,'Reels'!D33='Reels'!D3))) -> FALSE | H26: =IF(G26,C26,0) -> 0
A27: class.fighter | B27: attack1 / heal1 / attack2 | C27: =('Reels'!D4/('Reels'!D4+'Reels'!D7+'Reels'!D10+'Reels'!D13+'Reels'!D16+'Reels'!D19))*('Reels'!D34/('Reels'!D22+'Reels'!D25+'Reels'!D28+'Reels'!D31+'Reels'!D34+'Reels'!D37+'Reels'!D40))*('Reels'!D47/('Reels'!D44+'Reels'!D47+'Reels'!D50+'Reels'!D53+'Reels'!D56+'Reels'!D59)) -> 0.0015151515 | D27: =IF(OR('Reels'!D2="attack",'Reels'!D2="magic"),CHOOSE('Reels'!D3+1,'Slots'!D29,'Slots'!D30,'Slots'!D31,'Slots'!D32,'Slots'!D33),0)+IF(OR('Reels'!D32="attack",'Reels'!D32="magic"),CHOOSE('Reels'!D33+1,'Slots'!D29,'Slots'!D30,'Slots'!D31,'Slots'!D32,'Slots'!D33),0)+IF(OR('Reels'!D45="attack",'Reels'!D45="magic"),CHOOSE('Reels'!D46+1,'Slots'!D29,'Slots'!D30,'Slots'!D31,'Slots'!D32,'Slots'!D33),0) -> 6 | E27: =IF('Reels'!D2="heal",'Reels'!D3*'Slots'!D24,0)+IF('Reels'!D32="heal",'Reels'!D33*'Slots'!D24,0)+IF('Reels'!D45="heal",'Reels'!D46*'Slots'!D24,0) -> 2 | F27: =IF('Reels'!D2="block",'Reels'!D3*'Slots'!D25,0)+IF('Reels'!D32="block",'Reels'!D33*'Slots'!D25,0)+IF('Reels'!D45="block",'Reels'!D46*'Slots'!D25,0) -> 0 | G27: =AND('Reels'!D2<>"blank",'Reels'!D2<>"class",'Reels'!D2='Reels'!D45,'Reels'!D3='Reels'!D46,OR('Reels'!D32="class",AND('Reels'!D32='Reels'!D2,'Reels'!D33='Reels'!D3))) -> FALSE | H27: =IF(G27,C27,0) -> 0
A28: class.fighter | B28: attack1 / heal1 / block1 | C28: =('Reels'!D4/('Reels'!D4+'Reels'!D7+'Reels'!D10+'Reels'!D13+'Reels'!D16+'Reels'!D19))*('Reels'!D34/('Reels'!D22+'Reels'!D25+'Reels'!D28+'Reels'!D31+'Reels'!D34+'Reels'!D37+'Reels'!D40))*('Reels'!D50/('Reels'!D44+'Reels'!D47+'Reels'!D50+'Reels'!D53+'Reels'!D56+'Reels'!D59)) -> 0.0021212121 | D28: =IF(OR('Reels'!D2="attack",'Reels'!D2="magic"),CHOOSE('Reels'!D3+1,'Slots'!D29,'Slots'!D30,'Slots'!D31,'Slots'!D32,'Slots'!D33),0)+IF(OR('Reels'!D32="attack",'Reels'!D32="magic"),CHOOSE('Reels'!D33+1,'Slots'!D29,'Slots'!D30,'Slots'!D31,'Slots'!D32,'Slots'!D33),0)+IF(OR('Reels'!D48="attack",'Reels'!D48="magic"),CHOOSE('Reels'!D49+1,'Slots'!D29,'Slots'!D30,'Slots'!D31,'Slots'!D32,'Slots'!D33),0) -> 2 | E28: =IF('Reels'!D2="heal",'Reels'!D3*'Slots'!D24,0)+IF('Reels'!D32="heal",'Reels'!D33*'Slots'!D24,0)+IF('Reels'!D48="heal",'Reels'!D49*'Slots'!D24,0) -> 2 | F28: =IF('Reels'!D2="block",'Reels'!D3*'Slots'!D25,0)+IF('Reels'!D32="block",'Reels'!D33*'Slots'!D25,0)+IF('Reels'!D48="block",'Reels'!D49*'Slots'!D25,0) -> 1 | G28: =AND('Reels'!D2<>"blank",'Reels'!D2<>"class",'Reels'!D2='Reels'!D48,'Reels'!D3='Reels'!D49,OR('Reels'!D32="class",AND('Reels'!D32='Reels'!D2,'Reels'!D33='Reels'!D3))) -> FALSE | H28: =IF(G28,C28,0) -> 0
A29: class.fighter | B29: attack1 / heal1 / block2 | C29: =('Reels'!D4/('Reels'!D4+'Reels'!D7+'Reels'!D10+'Reels'!D13+'Reels'!D16+'Reels'!D19))*('Reels'!D34/('Reels'!D22+'Reels'!D25+'Reels'!D28+'Reels'!D31+'Reels'!D34+'Reels'!D37+'Reels'!D40))*('Reels'!D53/('Reels'!D44+'Reels'!D47+'Reels'!D50+'Reels'!D53+'Reels'!D56+'Reels'!D59)) -> 0.00090909091 | D29: =IF(OR('Reels'!D2="attack",'Reels'!D2="magic"),CHOOSE('Reels'!D3+1,'Slots'!D29,'Slots'!D30,'Slots'!D31,'Slots'!D32,'Slots'!D33),0)+IF(OR('Reels'!D32="attack",'Reels'!D32="magic"),CHOOSE('Reels'!D33+1,'Slots'!D29,'Slots'!D30,'Slots'!D31,'Slots'!D32,'Slots'!D33),0)+IF(OR('Reels'!D51="attack",'Reels'!D51="magic"),CHOOSE('Reels'!D52+1,'Slots'!D29,'Slots'!D30,'Slots'!D31,'Slots'!D32,'Slots'!D33),0) -> 2 | E29: =IF('Reels'!D2="heal",'Reels'!D3*'Slots'!D24,0)+IF('Reels'!D32="heal",'Reels'!D33*'Slots'!D24,0)+IF('Reels'!D51="heal",'Reels'!D52*'Slots'!D24,0) -> 2 | F29: =IF('Reels'!D2="block",'Reels'!D3*'Slots'!D25,0)+IF('Reels'!D32="block",'Reels'!D33*'Slots'!D25,0)+IF('Reels'!D51="block",'Reels'!D52*'Slots'!D25,0) -> 2 | G29: =AND('Reels'!D2<>"blank",'Reels'!D2<>"class",'Reels'!D2='Reels'!D51,'Reels'!D3='Reels'!D52,OR('Reels'!D32="class",AND('Reels'!D32='Reels'!D2,'Reels'!D33='Reels'!D3))) -> FALSE | H29: =IF(G29,C29,0) -> 0
A30: class.fighter | B30: attack1 / heal1 / heal1 | C30: =('Reels'!D4/('Reels'!D4+'Reels'!D7+'Reels'!D10+'Reels'!D13+'Reels'!D16+'Reels'!D19))*('Reels'!D34/('Reels'!D22+'Reels'!D25+'Reels'!D28+'Reels'!D31+'Reels'!D34+'Reels'!D37+'Reels'!D40))*('Reels'!D56/('Reels'!D44+'Reels'!D47+'Reels'!D50+'Reels'!D53+'Reels'!D56+'Reels'!D59)) -> 0.0003030303 | D30: =IF(OR('Reels'!D2="attack",'Reels'!D2="magic"),CHOOSE('Reels'!D3+1,'Slots'!D29,'Slots'!D30,'Slots'!D31,'Slots'!D32,'Slots'!D33),0)+IF(OR('Reels'!D32="attack",'Reels'!D32="magic"),CHOOSE('Reels'!D33+1,'Slots'!D29,'Slots'!D30,'Slots'!D31,'Slots'!D32,'Slots'!D33),0)+IF(OR('Reels'!D54="attack",'Reels'!D54="magic"),CHOOSE('Reels'!D55+1,'Slots'!D29,'Slots'!D30,'Slots'!D31,'Slots'!D32,'Slots'!D33),0) -> 2 | E30: =IF('Reels'!D2="heal",'Reels'!D3*'Slots'!D24,0)+IF('Reels'!D32="heal",'Reels'!D33*'Slots'!D24,0)+IF('Reels'!D54="heal",'Reels'!D55*'Slots'!D24,0) -> 4 | F30: =IF('Reels'!D2="block",'Reels'!D3*'Slots'!D25,0)+IF('Reels'!D32="block",'Reels'!D33*'Slots'!D25,0)+IF('Reels'!D54="block",'Reels'!D55*'Slots'!D25,0) -> 0 | G30: =AND('Reels'!D2<>"blank",'Reels'!D2<>"class",'Reels'!D2='Reels'!D54,'Reels'!D3='Reels'!D55,OR('Reels'!D32="class",AND('Reels'!D32='Reels'!D2,'Reels'!D33='Reels'!D3))) -> FALSE | H30: =IF(G30,C30,0) -> 0
A31: class.fighter | B31: attack1 / heal1 / blank1 | C31: =('Reels'!D4/('Reels'!D4+'Reels'!D7+'Reels'!D10+'Reels'!D13+'Reels'!D16+'Reels'!D19))*('Reels'!D34/('Reels'!D22+'Reels'!D25+'Reels'!D28+'Reels'!D31+'Reels'!D34+'Reels'!D37+'Reels'!D40))*('Reels'!D59/('Reels'!D44+'Reels'!D47+'Reels'!D50+'Reels'!D53+'Reels'!D56+'Reels'!D59)) -> 0.0015151515 | D31: =IF(OR('Reels'!D2="attack",'Reels'!D2="magic"),CHOOSE('Reels'!D3+1,'Slots'!D29,'Slots'!D30,'Slots'!D31,'Slots'!D32,'Slots'!D33),0)+IF(OR('Reels'!D32="attack",'Reels'!D32="magic"),CHOOSE('Reels'!D33+1,'Slots'!D29,'Slots'!D30,'Slots'!D31,'Slots'!D32,'Slots'!D33),0)+IF(OR('Reels'!D57="attack",'Reels'!D57="magic"),CHOOSE('Reels'!D58+1,'Slots'!D29,'Slots'!D30,'Slots'!D31,'Slots'!D32,'Slots'!D33),0) -> 2 | E31: =IF('Reels'!D2="heal",'Reels'!D3*'Slots'!D24,0)+IF('Reels'!D32="heal",'Reels'!D33*'Slots'!D24,0)+IF('Reels'!D57="heal",'Reels'!D58*'Slots'!D24,0) -> 2 | F31: =IF('Reels'!D2="block",'Reels'!D3*'Slots'!D25,0)+IF('Reels'!D32="block",'Reels'!D33*'Slots'!D25,0)+IF('Reels'!D57="block",'Reels'!D58*'Slots'!D25,0) -> 0 | G31: =AND('Reels'!D2<>"blank",'Reels'!D2<>"class",'Reels'!D2='Reels'!D57,'Reels'!D3='Reels'!D58,OR('Reels'!D32="class",AND('Reels'!D32='Reels'!D2,'Reels'!D33='Reels'!D3))) -> FALSE | H31: =IF(G31,C31,0) -> 0
A32: class.fighter | B32: attack1 / blank1 / attack1 | C32: =('Reels'!D4/('Reels'!D4+'Reels'!D7+'Reels'!D10+'Reels'!D13+'Reels'!D16+'Reels'!D19))*('Reels'!D37/('Reels'!D22+'Reels'!D25+'Reels'!D28+'Reels'!D31+'Reels'!D34+'Reels'!D37+'Reels'!D40))*('Reels'!D44/('Reels'!D44+'Reels'!D47+'Reels'!D50+'Reels'!D53+'Reels'!D56+'Reels'!D59)) -> 0.013636364 | D32: =IF(OR('Reels'!D2="attack",'Reels'!D2="magic"),CHOOSE('Reels'!D3+1,'Slots'!D29,'Slots'!D30,'Slots'!D31,'Slots'!D32,'Slots'!D33),0)+IF(OR('Reels'!D35="attack",'Reels'!D35="magic"),CHOOSE('Reels'!D36+1,'Slots'!D29,'Slots'!D30,'Slots'!D31,'Slots'!D32,'Slots'!D33),0)+IF(OR('Reels'!D42="attack",'Reels'!D42="magic"),CHOOSE('Reels'!D43+1,'Slots'!D29,'Slots'!D30,'Slots'!D31,'Slots'!D32,'Slots'!D33),0) -> 4 | E32: =IF('Reels'!D2="heal",'Reels'!D3*'Slots'!D24,0)+IF('Reels'!D35="heal",'Reels'!D36*'Slots'!D24,0)+IF('Reels'!D42="heal",'Reels'!D43*'Slots'!D24,0) -> 0 | F32: =IF('Reels'!D2="block",'Reels'!D3*'Slots'!D25,0)+IF('Reels'!D35="block",'Reels'!D36*'Slots'!D25,0)+IF('Reels'!D42="block",'Reels'!D43*'Slots'!D25,0) -> 0 | G32: =AND('Reels'!D2<>"blank",'Reels'!D2<>"class",'Reels'!D2='Reels'!D42,'Reels'!D3='Reels'!D43,OR('Reels'!D35="class",AND('Reels'!D35='Reels'!D2,'Reels'!D36='Reels'!D3))) -> FALSE | H32: =IF(G32,C32,0) -> 0
A33: class.fighter | B33: attack1 / blank1 / attack2 | C33: =('Reels'!D4/('Reels'!D4+'Reels'!D7+'Reels'!D10+'Reels'!D13+'Reels'!D16+'Reels'!D19))*('Reels'!D37/('Reels'!D22+'Reels'!D25+'Reels'!D28+'Reels'!D31+'Reels'!D34+'Reels'!D37+'Reels'!D40))*('Reels'!D47/('Reels'!D44+'Reels'!D47+'Reels'!D50+'Reels'!D53+'Reels'!D56+'Reels'!D59)) -> 0.0075757576 | D33: =IF(OR('Reels'!D2="attack",'Reels'!D2="magic"),CHOOSE('Reels'!D3+1,'Slots'!D29,'Slots'!D30,'Slots'!D31,'Slots'!D32,'Slots'!D33),0)+IF(OR('Reels'!D35="attack",'Reels'!D35="magic"),CHOOSE('Reels'!D36+1,'Slots'!D29,'Slots'!D30,'Slots'!D31,'Slots'!D32,'Slots'!D33),0)+IF(OR('Reels'!D45="attack",'Reels'!D45="magic"),CHOOSE('Reels'!D46+1,'Slots'!D29,'Slots'!D30,'Slots'!D31,'Slots'!D32,'Slots'!D33),0) -> 6 | E33: =IF('Reels'!D2="heal",'Reels'!D3*'Slots'!D24,0)+IF('Reels'!D35="heal",'Reels'!D36*'Slots'!D24,0)+IF('Reels'!D45="heal",'Reels'!D46*'Slots'!D24,0) -> 0 | F33: =IF('Reels'!D2="block",'Reels'!D3*'Slots'!D25,0)+IF('Reels'!D35="block",'Reels'!D36*'Slots'!D25,0)+IF('Reels'!D45="block",'Reels'!D46*'Slots'!D25,0) -> 0 | G33: =AND('Reels'!D2<>"blank",'Reels'!D2<>"class",'Reels'!D2='Reels'!D45,'Reels'!D3='Reels'!D46,OR('Reels'!D35="class",AND('Reels'!D35='Reels'!D2,'Reels'!D36='Reels'!D3))) -> FALSE | H33: =IF(G33,C33,0) -> 0
A34: class.fighter | B34: attack1 / blank1 / block1 | C34: =('Reels'!D4/('Reels'!D4+'Reels'!D7+'Reels'!D10+'Reels'!D13+'Reels'!D16+'Reels'!D19))*('Reels'!D37/('Reels'!D22+'Reels'!D25+'Reels'!D28+'Reels'!D31+'Reels'!D34+'Reels'!D37+'Reels'!D40))*('Reels'!D50/('Reels'!D44+'Reels'!D47+'Reels'!D50+'Reels'!D53+'Reels'!D56+'Reels'!D59)) -> 0.010606061 | D34: =IF(OR('Reels'!D2="attack",'Reels'!D2="magic"),CHOOSE('Reels'!D3+1,'Slots'!D29,'Slots'!D30,'Slots'!D31,'Slots'!D32,'Slots'!D33),0)+IF(OR('Reels'!D35="attack",'Reels'!D35="magic"),CHOOSE('Reels'!D36+1,'Slots'!D29,'Slots'!D30,'Slots'!D31,'Slots'!D32,'Slots'!D33),0)+IF(OR('Reels'!D48="attack",'Reels'!D48="magic"),CHOOSE('Reels'!D49+1,'Slots'!D29,'Slots'!D30,'Slots'!D31,'Slots'!D32,'Slots'!D33),0) -> 2 | E34: =IF('Reels'!D2="heal",'Reels'!D3*'Slots'!D24,0)+IF('Reels'!D35="heal",'Reels'!D36*'Slots'!D24,0)+IF('Reels'!D48="heal",'Reels'!D49*'Slots'!D24,0) -> 0 | F34: =IF('Reels'!D2="block",'Reels'!D3*'Slots'!D25,0)+IF('Reels'!D35="block",'Reels'!D36*'Slots'!D25,0)+IF('Reels'!D48="block",'Reels'!D49*'Slots'!D25,0) -> 1 | G34: =AND('Reels'!D2<>"blank",'Reels'!D2<>"class",'Reels'!D2='Reels'!D48,'Reels'!D3='Reels'!D49,OR('Reels'!D35="class",AND('Reels'!D35='Reels'!D2,'Reels'!D36='Reels'!D3))) -> FALSE | H34: =IF(G34,C34,0) -> 0
A35: class.fighter | B35: attack1 / blank1 / block2 | C35: =('Reels'!D4/('Reels'!D4+'Reels'!D7+'Reels'!D10+'Reels'!D13+'Reels'!D16+'Reels'!D19))*('Reels'!D37/('Reels'!D22+'Reels'!D25+'Reels'!D28+'Reels'!D31+'Reels'!D34+'Reels'!D37+'Reels'!D40))*('Reels'!D53/('Reels'!D44+'Reels'!D47+'Reels'!D50+'Reels'!D53+'Reels'!D56+'Reels'!D59)) -> 0.0045454545 | D35: =IF(OR('Reels'!D2="attack",'Reels'!D2="magic"),CHOOSE('Reels'!D3+1,'Slots'!D29,'Slots'!D30,'Slots'!D31,'Slots'!D32,'Slots'!D33),0)+IF(OR('Reels'!D35="attack",'Reels'!D35="magic"),CHOOSE('Reels'!D36+1,'Slots'!D29,'Slots'!D30,'Slots'!D31,'Slots'!D32,'Slots'!D33),0)+IF(OR('Reels'!D51="attack",'Reels'!D51="magic"),CHOOSE('Reels'!D52+1,'Slots'!D29,'Slots'!D30,'Slots'!D31,'Slots'!D32,'Slots'!D33),0) -> 2 | E35: =IF('Reels'!D2="heal",'Reels'!D3*'Slots'!D24,0)+IF('Reels'!D35="heal",'Reels'!D36*'Slots'!D24,0)+IF('Reels'!D51="heal",'Reels'!D52*'Slots'!D24,0) -> 0 | F35: =IF('Reels'!D2="block",'Reels'!D3*'Slots'!D25,0)+IF('Reels'!D35="block",'Reels'!D36*'Slots'!D25,0)+IF('Reels'!D51="block",'Reels'!D52*'Slots'!D25,0) -> 2 | G35: =AND('Reels'!D2<>"blank",'Reels'!D2<>"class",'Reels'!D2='Reels'!D51,'Reels'!D3='Reels'!D52,OR('Reels'!D35="class",AND('Reels'!D35='Reels'!D2,'Reels'!D36='Reels'!D3))) -> FALSE | H35: =IF(G35,C35,0) -> 0
A36: class.fighter | B36: attack1 / blank1 / heal1 | C36: =('Reels'!D4/('Reels'!D4+'Reels'!D7+'Reels'!D10+'Reels'!D13+'Reels'!D16+'Reels'!D19))*('Reels'!D37/('Reels'!D22+'Reels'!D25+'Reels'!D28+'Reels'!D31+'Reels'!D34+'Reels'!D37+'Reels'!D40))*('Reels'!D56/('Reels'!D44+'Reels'!D47+'Reels'!D50+'Reels'!D53+'Reels'!D56+'Reels'!D59)) -> 0.0015151515 | D36: =IF(OR('Reels'!D2="attack",'Reels'!D2="magic"),CHOOSE('Reels'!D3+1,'Slots'!D29,'Slots'!D30,'Slots'!D31,'Slots'!D32,'Slots'!D33),0)+IF(OR('Reels'!D35="attack",'Reels'!D35="magic"),CHOOSE('Reels'!D36+1,'Slots'!D29,'Slots'!D30,'Slots'!D31,'Slots'!D32,'Slots'!D33),0)+IF(OR('Reels'!D54="attack",'Reels'!D54="magic"),CHOOSE('Reels'!D55+1,'Slots'!D29,'Slots'!D30,'Slots'!D31,'Slots'!D32,'Slots'!D33),0) -> 2 | E36: =IF('Reels'!D2="heal",'Reels'!D3*'Slots'!D24,0)+IF('Reels'!D35="heal",'Reels'!D36*'Slots'!D24,0)+IF('Reels'!D54="heal",'Reels'!D55*'Slots'!D24,0) -> 2 | F36: =IF('Reels'!D2="block",'Reels'!D3*'Slots'!D25,0)+IF('Reels'!D35="block",'Reels'!D36*'Slots'!D25,0)+IF('Reels'!D54="block",'Reels'!D55*'Slots'!D25,0) -> 0 | G36: =AND('Reels'!D2<>"blank",'Reels'!D2<>"class",'Reels'!D2='Reels'!D54,'Reels'!D3='Reels'!D55,OR('Reels'!D35="class",AND('Reels'!D35='Reels'!D2,'Reels'!D36='Reels'!D3))) -> FALSE | H36: =IF(G36,C36,0) -> 0
A37: class.fighter | B37: attack1 / blank1 / blank1 | C37: =('Reels'!D4/('Reels'!D4+'Reels'!D7+'Reels'!D10+'Reels'!D13+'Reels'!D16+'Reels'!D19))*('Reels'!D37/('Reels'!D22+'Reels'!D25+'Reels'!D28+'Reels'!D31+'Reels'!D34+'Reels'!D37+'Reels'!D40))*('Reels'!D59/('Reels'!D44+'Reels'!D47+'Reels'!D50+'Reels'!D53+'Reels'!D56+'Reels'!D59)) -> 0.0075757576 | D37: =IF(OR('Reels'!D2="attack",'Reels'!D2="magic"),CHOOSE('Reels'!D3+1,'Slots'!D29,'Slots'!D30,'Slots'!D31,'Slots'!D32,'Slots'!D33),0)+IF(OR('Reels'!D35="attack",'Reels'!D35="magic"),CHOOSE('Reels'!D36+1,'Slots'!D29,'Slots'!D30,'Slots'!D31,'Slots'!D32,'Slots'!D33),0)+IF(OR('Reels'!D57="attack",'Reels'!D57="magic"),CHOOSE('Reels'!D58+1,'Slots'!D29,'Slots'!D30,'Slots'!D31,'Slots'!D32,'Slots'!D33),0) -> 2 | E37: =IF('Reels'!D2="heal",'Reels'!D3*'Slots'!D24,0)+IF('Reels'!D35="heal",'Reels'!D36*'Slots'!D24,0)+IF('Reels'!D57="heal",'Reels'!D58*'Slots'!D24,0) -> 0 | F37: =IF('Reels'!D2="block",'Reels'!D3*'Slots'!D25,0)+IF('Reels'!D35="block",'Reels'!D36*'Slots'!D25,0)+IF('Reels'!D57="block",'Reels'!D58*'Slots'!D25,0) -> 0 | G37: =AND('Reels'!D2<>"blank",'Reels'!D2<>"class",'Reels'!D2='Reels'!D57,'Reels'!D3='Reels'!D58,OR('Reels'!D35="class",AND('Reels'!D35='Reels'!D2,'Reels'!D36='Reels'!D3))) -> FALSE | H37: =IF(G37,C37,0) -> 0
A38: class.fighter | B38: attack1 / class1 / attack1 | C38: =('Reels'!D4/('Reels'!D4+'Reels'!D7+'Reels'!D10+'Reels'!D13+'Reels'!D16+'Reels'!D19))*('Reels'!D40/('Reels'!D22+'Reels'!D25+'Reels'!D28+'Reels'!D31+'Reels'!D34+'Reels'!D37+'Reels'!D40))*('Reels'!D44/('Reels'!D44+'Reels'!D47+'Reels'!D50+'Reels'!D53+'Reels'!D56+'Reels'!D59)) -> 0.0081818182 | D38: =IF(OR('Reels'!D2="attack",'Reels'!D2="magic"),CHOOSE('Reels'!D3+1,'Slots'!D29,'Slots'!D30,'Slots'!D31,'Slots'!D32,'Slots'!D33),0)+IF(OR('Reels'!D38="attack",'Reels'!D38="magic"),CHOOSE('Reels'!D39+1,'Slots'!D29,'Slots'!D30,'Slots'!D31,'Slots'!D32,'Slots'!D33),0)+IF(OR('Reels'!D42="attack",'Reels'!D42="magic"),CHOOSE('Reels'!D43+1,'Slots'!D29,'Slots'!D30,'Slots'!D31,'Slots'!D32,'Slots'!D33),0) -> 4 | E38: =IF('Reels'!D2="heal",'Reels'!D3*'Slots'!D24,0)+IF('Reels'!D38="heal",'Reels'!D39*'Slots'!D24,0)+IF('Reels'!D42="heal",'Reels'!D43*'Slots'!D24,0) -> 0 | F38: =IF('Reels'!D2="block",'Reels'!D3*'Slots'!D25,0)+IF('Reels'!D38="block",'Reels'!D39*'Slots'!D25,0)+IF('Reels'!D42="block",'Reels'!D43*'Slots'!D25,0) -> 0 | G38: =AND('Reels'!D2<>"blank",'Reels'!D2<>"class",'Reels'!D2='Reels'!D42,'Reels'!D3='Reels'!D43,OR('Reels'!D38="class",AND('Reels'!D38='Reels'!D2,'Reels'!D39='Reels'!D3))) -> TRUE | H38: =IF(G38,C38,0) -> 0.0081818182
A39: class.fighter | B39: attack1 / class1 / attack2 | C39: =('Reels'!D4/('Reels'!D4+'Reels'!D7+'Reels'!D10+'Reels'!D13+'Reels'!D16+'Reels'!D19))*('Reels'!D40/('Reels'!D22+'Reels'!D25+'Reels'!D28+'Reels'!D31+'Reels'!D34+'Reels'!D37+'Reels'!D40))*('Reels'!D47/('Reels'!D44+'Reels'!D47+'Reels'!D50+'Reels'!D53+'Reels'!D56+'Reels'!D59)) -> 0.0045454545 | D39: =IF(OR('Reels'!D2="attack",'Reels'!D2="magic"),CHOOSE('Reels'!D3+1,'Slots'!D29,'Slots'!D30,'Slots'!D31,'Slots'!D32,'Slots'!D33),0)+IF(OR('Reels'!D38="attack",'Reels'!D38="magic"),CHOOSE('Reels'!D39+1,'Slots'!D29,'Slots'!D30,'Slots'!D31,'Slots'!D32,'Slots'!D33),0)+IF(OR('Reels'!D45="attack",'Reels'!D45="magic"),CHOOSE('Reels'!D46+1,'Slots'!D29,'Slots'!D30,'Slots'!D31,'Slots'!D32,'Slots'!D33),0) -> 6 | E39: =IF('Reels'!D2="heal",'Reels'!D3*'Slots'!D24,0)+IF('Reels'!D38="heal",'Reels'!D39*'Slots'!D24,0)+IF('Reels'!D45="heal",'Reels'!D46*'Slots'!D24,0) -> 0 | F39: =IF('Reels'!D2="block",'Reels'!D3*'Slots'!D25,0)+IF('Reels'!D38="block",'Reels'!D39*'Slots'!D25,0)+IF('Reels'!D45="block",'Reels'!D46*'Slots'!D25,0) -> 0 | G39: =AND('Reels'!D2<>"blank",'Reels'!D2<>"class",'Reels'!D2='Reels'!D45,'Reels'!D3='Reels'!D46,OR('Reels'!D38="class",AND('Reels'!D38='Reels'!D2,'Reels'!D39='Reels'!D3))) -> FALSE | H39: =IF(G39,C39,0) -> 0
A40: class.fighter | B40: attack1 / class1 / block1 | C40: =('Reels'!D4/('Reels'!D4+'Reels'!D7+'Reels'!D10+'Reels'!D13+'Reels'!D16+'Reels'!D19))*('Reels'!D40/('Reels'!D22+'Reels'!D25+'Reels'!D28+'Reels'!D31+'Reels'!D34+'Reels'!D37+'Reels'!D40))*('Reels'!D50/('Reels'!D44+'Reels'!D47+'Reels'!D50+'Reels'!D53+'Reels'!D56+'Reels'!D59)) -> 0.0063636364 | D40: =IF(OR('Reels'!D2="attack",'Reels'!D2="magic"),CHOOSE('Reels'!D3+1,'Slots'!D29,'Slots'!D30,'Slots'!D31,'Slots'!D32,'Slots'!D33),0)+IF(OR('Reels'!D38="attack",'Reels'!D38="magic"),CHOOSE('Reels'!D39+1,'Slots'!D29,'Slots'!D30,'Slots'!D31,'Slots'!D32,'Slots'!D33),0)+IF(OR('Reels'!D48="attack",'Reels'!D48="magic"),CHOOSE('Reels'!D49+1,'Slots'!D29,'Slots'!D30,'Slots'!D31,'Slots'!D32,'Slots'!D33),0) -> 2 | E40: =IF('Reels'!D2="heal",'Reels'!D3*'Slots'!D24,0)+IF('Reels'!D38="heal",'Reels'!D39*'Slots'!D24,0)+IF('Reels'!D48="heal",'Reels'!D49*'Slots'!D24,0) -> 0 | F40: =IF('Reels'!D2="block",'Reels'!D3*'Slots'!D25,0)+IF('Reels'!D38="block",'Reels'!D39*'Slots'!D25,0)+IF('Reels'!D48="block",'Reels'!D49*'Slots'!D25,0) -> 1 | G40: =AND('Reels'!D2<>"blank",'Reels'!D2<>"class",'Reels'!D2='Reels'!D48,'Reels'!D3='Reels'!D49,OR('Reels'!D38="class",AND('Reels'!D38='Reels'!D2,'Reels'!D39='Reels'!D3))) -> FALSE | H40: =IF(G40,C40,0) -> 0
A41: class.fighter | B41: attack1 / class1 / block2 | C41: =('Reels'!D4/('Reels'!D4+'Reels'!D7+'Reels'!D10+'Reels'!D13+'Reels'!D16+'Reels'!D19))*('Reels'!D40/('Reels'!D22+'Reels'!D25+'Reels'!D28+'Reels'!D31+'Reels'!D34+'Reels'!D37+'Reels'!D40))*('Reels'!D53/('Reels'!D44+'Reels'!D47+'Reels'!D50+'Reels'!D53+'Reels'!D56+'Reels'!D59)) -> 0.0027272727 | D41: =IF(OR('Reels'!D2="attack",'Reels'!D2="magic"),CHOOSE('Reels'!D3+1,'Slots'!D29,'Slots'!D30,'Slots'!D31,'Slots'!D32,'Slots'!D33),0)+IF(OR('Reels'!D38="attack",'Reels'!D38="magic"),CHOOSE('Reels'!D39+1,'Slots'!D29,'Slots'!D30,'Slots'!D31,'Slots'!D32,'Slots'!D33),0)+IF(OR('Reels'!D51="attack",'Reels'!D51="magic"),CHOOSE('Reels'!D52+1,'Slots'!D29,'Slots'!D30,'Slots'!D31,'Slots'!D32,'Slots'!D33),0) -> 2 | E41: =IF('Reels'!D2="heal",'Reels'!D3*'Slots'!D24,0)+IF('Reels'!D38="heal",'Reels'!D39*'Slots'!D24,0)+IF('Reels'!D51="heal",'Reels'!D52*'Slots'!D24,0) -> 0 | F41: =IF('Reels'!D2="block",'Reels'!D3*'Slots'!D25,0)+IF('Reels'!D38="block",'Reels'!D39*'Slots'!D25,0)+IF('Reels'!D51="block",'Reels'!D52*'Slots'!D25,0) -> 2 | G41: =AND('Reels'!D2<>"blank",'Reels'!D2<>"class",'Reels'!D2='Reels'!D51,'Reels'!D3='Reels'!D52,OR('Reels'!D38="class",AND('Reels'!D38='Reels'!D2,'Reels'!D39='Reels'!D3))) -> FALSE | H41: =IF(G41,C41,0) -> 0
A42: class.fighter | B42: attack1 / class1 / heal1 | C42: =('Reels'!D4/('Reels'!D4+'Reels'!D7+'Reels'!D10+'Reels'!D13+'Reels'!D16+'Reels'!D19))*('Reels'!D40/('Reels'!D22+'Reels'!D25+'Reels'!D28+'Reels'!D31+'Reels'!D34+'Reels'!D37+'Reels'!D40))*('Reels'!D56/('Reels'!D44+'Reels'!D47+'Reels'!D50+'Reels'!D53+'Reels'!D56+'Reels'!D59)) -> 0.00090909091 | D42: =IF(OR('Reels'!D2="attack",'Reels'!D2="magic"),CHOOSE('Reels'!D3+1,'Slots'!D29,'Slots'!D30,'Slots'!D31,'Slots'!D32,'Slots'!D33),0)+IF(OR('Reels'!D38="attack",'Reels'!D38="magic"),CHOOSE('Reels'!D39+1,'Slots'!D29,'Slots'!D30,'Slots'!D31,'Slots'!D32,'Slots'!D33),0)+IF(OR('Reels'!D54="attack",'Reels'!D54="magic"),CHOOSE('Reels'!D55+1,'Slots'!D29,'Slots'!D30,'Slots'!D31,'Slots'!D32,'Slots'!D33),0) -> 2 | E42: =IF('Reels'!D2="heal",'Reels'!D3*'Slots'!D24,0)+IF('Reels'!D38="heal",'Reels'!D39*'Slots'!D24,0)+IF('Reels'!D54="heal",'Reels'!D55*'Slots'!D24,0) -> 2 | F42: =IF('Reels'!D2="block",'Reels'!D3*'Slots'!D25,0)+IF('Reels'!D38="block",'Reels'!D39*'Slots'!D25,0)+IF('Reels'!D54="block",'Reels'!D55*'Slots'!D25,0) -> 0 | G42: =AND('Reels'!D2<>"blank",'Reels'!D2<>"class",'Reels'!D2='Reels'!D54,'Reels'!D3='Reels'!D55,OR('Reels'!D38="class",AND('Reels'!D38='Reels'!D2,'Reels'!D39='Reels'!D3))) -> FALSE | H42: =IF(G42,C42,0) -> 0
A43: class.fighter | B43: attack1 / class1 / blank1 | C43: =('Reels'!D4/('Reels'!D4+'Reels'!D7+'Reels'!D10+'Reels'!D13+'Reels'!D16+'Reels'!D19))*('Reels'!D40/('Reels'!D22+'Reels'!D25+'Reels'!D28+'Reels'!D31+'Reels'!D34+'Reels'!D37+'Reels'!D40))*('Reels'!D59/('Reels'!D44+'Reels'!D47+'Reels'!D50+'Reels'!D53+'Reels'!D56+'Reels'!D59)) -> 0.0045454545 | D43: =IF(OR('Reels'!D2="attack",'Reels'!D2="magic"),CHOOSE('Reels'!D3+1,'Slots'!D29,'Slots'!D30,'Slots'!D31,'Slots'!D32,'Slots'!D33),0)+IF(OR('Reels'!D38="attack",'Reels'!D38="magic"),CHOOSE('Reels'!D39+1,'Slots'!D29,'Slots'!D30,'Slots'!D31,'Slots'!D32,'Slots'!D33),0)+IF(OR('Reels'!D57="attack",'Reels'!D57="magic"),CHOOSE('Reels'!D58+1,'Slots'!D29,'Slots'!D30,'Slots'!D31,'Slots'!D32,'Slots'!D33),0) -> 2 | E43: =IF('Reels'!D2="heal",'Reels'!D3*'Slots'!D24,0)+IF('Reels'!D38="heal",'Reels'!D39*'Slots'!D24,0)+IF('Reels'!D57="heal",'Reels'!D58*'Slots'!D24,0) -> 0 | F43: =IF('Reels'!D2="block",'Reels'!D3*'Slots'!D25,0)+IF('Reels'!D38="block",'Reels'!D39*'Slots'!D25,0)+IF('Reels'!D57="block",'Reels'!D58*'Slots'!D25,0) -> 0 | G43: =AND('Reels'!D2<>"blank",'Reels'!D2<>"class",'Reels'!D2='Reels'!D57,'Reels'!D3='Reels'!D58,OR('Reels'!D38="class",AND('Reels'!D38='Reels'!D2,'Reels'!D39='Reels'!D3))) -> FALSE | H43: =IF(G43,C43,0) -> 0
A44: class.fighter | B44: attack2 / attack1 / attack1 | C44: =('Reels'!D7/('Reels'!D4+'Reels'!D7+'Reels'!D10+'Reels'!D13+'Reels'!D16+'Reels'!D19))*('Reels'!D22/('Reels'!D22+'Reels'!D25+'Reels'!D28+'Reels'!D31+'Reels'!D34+'Reels'!D37+'Reels'!D40))*('Reels'!D44/('Reels'!D44+'Reels'!D47+'Reels'!D50+'Reels'!D53+'Reels'!D56+'Reels'!D59)) -> 0.013636364 | D44: =IF(OR('Reels'!D5="attack",'Reels'!D5="magic"),CHOOSE('Reels'!D6+1,'Slots'!D29,'Slots'!D30,'Slots'!D31,'Slots'!D32,'Slots'!D33),0)+IF(OR('Reels'!D20="attack",'Reels'!D20="magic"),CHOOSE('Reels'!D21+1,'Slots'!D29,'Slots'!D30,'Slots'!D31,'Slots'!D32,'Slots'!D33),0)+IF(OR('Reels'!D42="attack",'Reels'!D42="magic"),CHOOSE('Reels'!D43+1,'Slots'!D29,'Slots'!D30,'Slots'!D31,'Slots'!D32,'Slots'!D33),0) -> 8 | E44: =IF('Reels'!D5="heal",'Reels'!D6*'Slots'!D24,0)+IF('Reels'!D20="heal",'Reels'!D21*'Slots'!D24,0)+IF('Reels'!D42="heal",'Reels'!D43*'Slots'!D24,0) -> 0 | F44: =IF('Reels'!D5="block",'Reels'!D6*'Slots'!D25,0)+IF('Reels'!D20="block",'Reels'!D21*'Slots'!D25,0)+IF('Reels'!D42="block",'Reels'!D43*'Slots'!D25,0) -> 0 | G44: =AND('Reels'!D5<>"blank",'Reels'!D5<>"class",'Reels'!D5='Reels'!D42,'Reels'!D6='Reels'!D43,OR('Reels'!D20="class",AND('Reels'!D20='Reels'!D5,'Reels'!D21='Reels'!D6))) -> FALSE | H44: =IF(G44,C44,0) -> 0
A45: class.fighter | B45: attack2 / attack1 / attack2 | C45: =('Reels'!D7/('Reels'!D4+'Reels'!D7+'Reels'!D10+'Reels'!D13+'Reels'!D16+'Reels'!D19))*('Reels'!D22/('Reels'!D22+'Reels'!D25+'Reels'!D28+'Reels'!D31+'Reels'!D34+'Reels'!D37+'Reels'!D40))*('Reels'!D47/('Reels'!D44+'Reels'!D47+'Reels'!D50+'Reels'!D53+'Reels'!D56+'Reels'!D59)) -> 0.0075757576 | D45: =IF(OR('Reels'!D5="attack",'Reels'!D5="magic"),CHOOSE('Reels'!D6+1,'Slots'!D29,'Slots'!D30,'Slots'!D31,'Slots'!D32,'Slots'!D33),0)+IF(OR('Reels'!D20="attack",'Reels'!D20="magic"),CHOOSE('Reels'!D21+1,'Slots'!D29,'Slots'!D30,'Slots'!D31,'Slots'!D32,'Slots'!D33),0)+IF(OR('Reels'!D45="attack",'Reels'!D45="magic"),CHOOSE('Reels'!D46+1,'Slots'!D29,'Slots'!D30,'Slots'!D31,'Slots'!D32,'Slots'!D33),0) -> 10 | E45: =IF('Reels'!D5="heal",'Reels'!D6*'Slots'!D24,0)+IF('Reels'!D20="heal",'Reels'!D21*'Slots'!D24,0)+IF('Reels'!D45="heal",'Reels'!D46*'Slots'!D24,0) -> 0 | F45: =IF('Reels'!D5="block",'Reels'!D6*'Slots'!D25,0)+IF('Reels'!D20="block",'Reels'!D21*'Slots'!D25,0)+IF('Reels'!D45="block",'Reels'!D46*'Slots'!D25,0) -> 0 | G45: =AND('Reels'!D5<>"blank",'Reels'!D5<>"class",'Reels'!D5='Reels'!D45,'Reels'!D6='Reels'!D46,OR('Reels'!D20="class",AND('Reels'!D20='Reels'!D5,'Reels'!D21='Reels'!D6))) -> FALSE | H45: =IF(G45,C45,0) -> 0
A46: class.fighter | B46: attack2 / attack1 / block1 | C46: =('Reels'!D7/('Reels'!D4+'Reels'!D7+'Reels'!D10+'Reels'!D13+'Reels'!D16+'Reels'!D19))*('Reels'!D22/('Reels'!D22+'Reels'!D25+'Reels'!D28+'Reels'!D31+'Reels'!D34+'Reels'!D37+'Reels'!D40))*('Reels'!D50/('Reels'!D44+'Reels'!D47+'Reels'!D50+'Reels'!D53+'Reels'!D56+'Reels'!D59)) -> 0.010606061 | D46: =IF(OR('Reels'!D5="attack",'Reels'!D5="magic"),CHOOSE('Reels'!D6+1,'Slots'!D29,'Slots'!D30,'Slots'!D31,'Slots'!D32,'Slots'!D33),0)+IF(OR('Reels'!D20="attack",'Reels'!D20="magic"),CHOOSE('Reels'!D21+1,'Slots'!D29,'Slots'!D30,'Slots'!D31,'Slots'!D32,'Slots'!D33),0)+IF(OR('Reels'!D48="attack",'Reels'!D48="magic"),CHOOSE('Reels'!D49+1,'Slots'!D29,'Slots'!D30,'Slots'!D31,'Slots'!D32,'Slots'!D33),0) -> 6 | E46: =IF('Reels'!D5="heal",'Reels'!D6*'Slots'!D24,0)+IF('Reels'!D20="heal",'Reels'!D21*'Slots'!D24,0)+IF('Reels'!D48="heal",'Reels'!D49*'Slots'!D24,0) -> 0 | F46: =IF('Reels'!D5="block",'Reels'!D6*'Slots'!D25,0)+IF('Reels'!D20="block",'Reels'!D21*'Slots'!D25,0)+IF('Reels'!D48="block",'Reels'!D49*'Slots'!D25,0) -> 1 | G46: =AND('Reels'!D5<>"blank",'Reels'!D5<>"class",'Reels'!D5='Reels'!D48,'Reels'!D6='Reels'!D49,OR('Reels'!D20="class",AND('Reels'!D20='Reels'!D5,'Reels'!D21='Reels'!D6))) -> FALSE | H46: =IF(G46,C46,0) -> 0
A47: class.fighter | B47: attack2 / attack1 / block2 | C47: =('Reels'!D7/('Reels'!D4+'Reels'!D7+'Reels'!D10+'Reels'!D13+'Reels'!D16+'Reels'!D19))*('Reels'!D22/('Reels'!D22+'Reels'!D25+'Reels'!D28+'Reels'!D31+'Reels'!D34+'Reels'!D37+'Reels'!D40))*('Reels'!D53/('Reels'!D44+'Reels'!D47+'Reels'!D50+'Reels'!D53+'Reels'!D56+'Reels'!D59)) -> 0.0045454545 | D47: =IF(OR('Reels'!D5="attack",'Reels'!D5="magic"),CHOOSE('Reels'!D6+1,'Slots'!D29,'Slots'!D30,'Slots'!D31,'Slots'!D32,'Slots'!D33),0)+IF(OR('Reels'!D20="attack",'Reels'!D20="magic"),CHOOSE('Reels'!D21+1,'Slots'!D29,'Slots'!D30,'Slots'!D31,'Slots'!D32,'Slots'!D33),0)+IF(OR('Reels'!D51="attack",'Reels'!D51="magic"),CHOOSE('Reels'!D52+1,'Slots'!D29,'Slots'!D30,'Slots'!D31,'Slots'!D32,'Slots'!D33),0) -> 6 | E47: =IF('Reels'!D5="heal",'Reels'!D6*'Slots'!D24,0)+IF('Reels'!D20="heal",'Reels'!D21*'Slots'!D24,0)+IF('Reels'!D51="heal",'Reels'!D52*'Slots'!D24,0) -> 0 | F47: =IF('Reels'!D5="block",'Reels'!D6*'Slots'!D25,0)+IF('Reels'!D20="block",'Reels'!D21*'Slots'!D25,0)+IF('Reels'!D51="block",'Reels'!D52*'Slots'!D25,0) -> 2 | G47: =AND('Reels'!D5<>"blank",'Reels'!D5<>"class",'Reels'!D5='Reels'!D51,'Reels'!D6='Reels'!D52,OR('Reels'!D20="class",AND('Reels'!D20='Reels'!D5,'Reels'!D21='Reels'!D6))) -> FALSE | H47: =IF(G47,C47,0) -> 0
A48: class.fighter | B48: attack2 / attack1 / heal1 | C48: =('Reels'!D7/('Reels'!D4+'Reels'!D7+'Reels'!D10+'Reels'!D13+'Reels'!D16+'Reels'!D19))*('Reels'!D22/('Reels'!D22+'Reels'!D25+'Reels'!D28+'Reels'!D31+'Reels'!D34+'Reels'!D37+'Reels'!D40))*('Reels'!D56/('Reels'!D44+'Reels'!D47+'Reels'!D50+'Reels'!D53+'Reels'!D56+'Reels'!D59)) -> 0.0015151515 | D48: =IF(OR('Reels'!D5="attack",'Reels'!D5="magic"),CHOOSE('Reels'!D6+1,'Slots'!D29,'Slots'!D30,'Slots'!D31,'Slots'!D32,'Slots'!D33),0)+IF(OR('Reels'!D20="attack",'Reels'!D20="magic"),CHOOSE('Reels'!D21+1,'Slots'!D29,'Slots'!D30,'Slots'!D31,'Slots'!D32,'Slots'!D33),0)+IF(OR('Reels'!D54="attack",'Reels'!D54="magic"),CHOOSE('Reels'!D55+1,'Slots'!D29,'Slots'!D30,'Slots'!D31,'Slots'!D32,'Slots'!D33),0) -> 6 | E48: =IF('Reels'!D5="heal",'Reels'!D6*'Slots'!D24,0)+IF('Reels'!D20="heal",'Reels'!D21*'Slots'!D24,0)+IF('Reels'!D54="heal",'Reels'!D55*'Slots'!D24,0) -> 2 | F48: =IF('Reels'!D5="block",'Reels'!D6*'Slots'!D25,0)+IF('Reels'!D20="block",'Reels'!D21*'Slots'!D25,0)+IF('Reels'!D54="block",'Reels'!D55*'Slots'!D25,0) -> 0 | G48: =AND('Reels'!D5<>"blank",'Reels'!D5<>"class",'Reels'!D5='Reels'!D54,'Reels'!D6='Reels'!D55,OR('Reels'!D20="class",AND('Reels'!D20='Reels'!D5,'Reels'!D21='Reels'!D6))) -> FALSE | H48: =IF(G48,C48,0) -> 0
A49: class.fighter | B49: attack2 / attack1 / blank1 | C49: =('Reels'!D7/('Reels'!D4+'Reels'!D7+'Reels'!D10+'Reels'!D13+'Reels'!D16+'Reels'!D19))*('Reels'!D22/('Reels'!D22+'Reels'!D25+'Reels'!D28+'Reels'!D31+'Reels'!D34+'Reels'!D37+'Reels'!D40))*('Reels'!D59/('Reels'!D44+'Reels'!D47+'Reels'!D50+'Reels'!D53+'Reels'!D56+'Reels'!D59)) -> 0.0075757576 | D49: =IF(OR('Reels'!D5="attack",'Reels'!D5="magic"),CHOOSE('Reels'!D6+1,'Slots'!D29,'Slots'!D30,'Slots'!D31,'Slots'!D32,'Slots'!D33),0)+IF(OR('Reels'!D20="attack",'Reels'!D20="magic"),CHOOSE('Reels'!D21+1,'Slots'!D29,'Slots'!D30,'Slots'!D31,'Slots'!D32,'Slots'!D33),0)+IF(OR('Reels'!D57="attack",'Reels'!D57="magic"),CHOOSE('Reels'!D58+1,'Slots'!D29,'Slots'!D30,'Slots'!D31,'Slots'!D32,'Slots'!D33),0) -> 6 | E49: =IF('Reels'!D5="heal",'Reels'!D6*'Slots'!D24,0)+IF('Reels'!D20="heal",'Reels'!D21*'Slots'!D24,0)+IF('Reels'!D57="heal",'Reels'!D58*'Slots'!D24,0) -> 0 | F49: =IF('Reels'!D5="block",'Reels'!D6*'Slots'!D25,0)+IF('Reels'!D20="block",'Reels'!D21*'Slots'!D25,0)+IF('Reels'!D57="block",'Reels'!D58*'Slots'!D25,0) -> 0 | G49: =AND('Reels'!D5<>"blank",'Reels'!D5<>"class",'Reels'!D5='Reels'!D57,'Reels'!D6='Reels'!D58,OR('Reels'!D20="class",AND('Reels'!D20='Reels'!D5,'Reels'!D21='Reels'!D6))) -> FALSE | H49: =IF(G49,C49,0) -> 0
A50: class.fighter | B50: attack2 / attack2 / attack1 | C50: =('Reels'!D7/('Reels'!D4+'Reels'!D7+'Reels'!D10+'Reels'!D13+'Reels'!D16+'Reels'!D19))*('Reels'!D25/('Reels'!D22+'Reels'!D25+'Reels'!D28+'Reels'!D31+'Reels'!D34+'Reels'!D37+'Reels'!D40))*('Reels'!D44/('Reels'!D44+'Reels'!D47+'Reels'!D50+'Reels'!D53+'Reels'!D56+'Reels'!D59)) -> 0.0075757576 | D50: =IF(OR('Reels'!D5="attack",'Reels'!D5="magic"),CHOOSE('Reels'!D6+1,'Slots'!D29,'Slots'!D30,'Slots'!D31,'Slots'!D32,'Slots'!D33),0)+IF(OR('Reels'!D23="attack",'Reels'!D23="magic"),CHOOSE('Reels'!D24+1,'Slots'!D29,'Slots'!D30,'Slots'!D31,'Slots'!D32,'Slots'!D33),0)+IF(OR('Reels'!D42="attack",'Reels'!D42="magic"),CHOOSE('Reels'!D43+1,'Slots'!D29,'Slots'!D30,'Slots'!D31,'Slots'!D32,'Slots'!D33),0) -> 10 | E50: =IF('Reels'!D5="heal",'Reels'!D6*'Slots'!D24,0)+IF('Reels'!D23="heal",'Reels'!D24*'Slots'!D24,0)+IF('Reels'!D42="heal",'Reels'!D43*'Slots'!D24,0) -> 0 | F50: =IF('Reels'!D5="block",'Reels'!D6*'Slots'!D25,0)+IF('Reels'!D23="block",'Reels'!D24*'Slots'!D25,0)+IF('Reels'!D42="block",'Reels'!D43*'Slots'!D25,0) -> 0 | G50: =AND('Reels'!D5<>"blank",'Reels'!D5<>"class",'Reels'!D5='Reels'!D42,'Reels'!D6='Reels'!D43,OR('Reels'!D23="class",AND('Reels'!D23='Reels'!D5,'Reels'!D24='Reels'!D6))) -> FALSE | H50: =IF(G50,C50,0) -> 0
A51: class.fighter | B51: attack2 / attack2 / attack2 | C51: =('Reels'!D7/('Reels'!D4+'Reels'!D7+'Reels'!D10+'Reels'!D13+'Reels'!D16+'Reels'!D19))*('Reels'!D25/('Reels'!D22+'Reels'!D25+'Reels'!D28+'Reels'!D31+'Reels'!D34+'Reels'!D37+'Reels'!D40))*('Reels'!D47/('Reels'!D44+'Reels'!D47+'Reels'!D50+'Reels'!D53+'Reels'!D56+'Reels'!D59)) -> 0.0042087542 | D51: =IF(OR('Reels'!D5="attack",'Reels'!D5="magic"),CHOOSE('Reels'!D6+1,'Slots'!D29,'Slots'!D30,'Slots'!D31,'Slots'!D32,'Slots'!D33),0)+IF(OR('Reels'!D23="attack",'Reels'!D23="magic"),CHOOSE('Reels'!D24+1,'Slots'!D29,'Slots'!D30,'Slots'!D31,'Slots'!D32,'Slots'!D33),0)+IF(OR('Reels'!D45="attack",'Reels'!D45="magic"),CHOOSE('Reels'!D46+1,'Slots'!D29,'Slots'!D30,'Slots'!D31,'Slots'!D32,'Slots'!D33),0) -> 12 | E51: =IF('Reels'!D5="heal",'Reels'!D6*'Slots'!D24,0)+IF('Reels'!D23="heal",'Reels'!D24*'Slots'!D24,0)+IF('Reels'!D45="heal",'Reels'!D46*'Slots'!D24,0) -> 0 | F51: =IF('Reels'!D5="block",'Reels'!D6*'Slots'!D25,0)+IF('Reels'!D23="block",'Reels'!D24*'Slots'!D25,0)+IF('Reels'!D45="block",'Reels'!D46*'Slots'!D25,0) -> 0 | G51: =AND('Reels'!D5<>"blank",'Reels'!D5<>"class",'Reels'!D5='Reels'!D45,'Reels'!D6='Reels'!D46,OR('Reels'!D23="class",AND('Reels'!D23='Reels'!D5,'Reels'!D24='Reels'!D6))) -> TRUE | H51: =IF(G51,C51,0) -> 0.0042087542
A52: class.fighter | B52: attack2 / attack2 / block1 | C52: =('Reels'!D7/('Reels'!D4+'Reels'!D7+'Reels'!D10+'Reels'!D13+'Reels'!D16+'Reels'!D19))*('Reels'!D25/('Reels'!D22+'Reels'!D25+'Reels'!D28+'Reels'!D31+'Reels'!D34+'Reels'!D37+'Reels'!D40))*('Reels'!D50/('Reels'!D44+'Reels'!D47+'Reels'!D50+'Reels'!D53+'Reels'!D56+'Reels'!D59)) -> 0.0058922559 | D52: =IF(OR('Reels'!D5="attack",'Reels'!D5="magic"),CHOOSE('Reels'!D6+1,'Slots'!D29,'Slots'!D30,'Slots'!D31,'Slots'!D32,'Slots'!D33),0)+IF(OR('Reels'!D23="attack",'Reels'!D23="magic"),CHOOSE('Reels'!D24+1,'Slots'!D29,'Slots'!D30,'Slots'!D31,'Slots'!D32,'Slots'!D33),0)+IF(OR('Reels'!D48="attack",'Reels'!D48="magic"),CHOOSE('Reels'!D49+1,'Slots'!D29,'Slots'!D30,'Slots'!D31,'Slots'!D32,'Slots'!D33),0) -> 8 | E52: =IF('Reels'!D5="heal",'Reels'!D6*'Slots'!D24,0)+IF('Reels'!D23="heal",'Reels'!D24*'Slots'!D24,0)+IF('Reels'!D48="heal",'Reels'!D49*'Slots'!D24,0) -> 0 | F52: =IF('Reels'!D5="block",'Reels'!D6*'Slots'!D25,0)+IF('Reels'!D23="block",'Reels'!D24*'Slots'!D25,0)+IF('Reels'!D48="block",'Reels'!D49*'Slots'!D25,0) -> 1 | G52: =AND('Reels'!D5<>"blank",'Reels'!D5<>"class",'Reels'!D5='Reels'!D48,'Reels'!D6='Reels'!D49,OR('Reels'!D23="class",AND('Reels'!D23='Reels'!D5,'Reels'!D24='Reels'!D6))) -> FALSE | H52: =IF(G52,C52,0) -> 0
